Workbook

Sheet Task List
B2: Task List | C2: Assigned to | D2: Status Update | E2: Comments
B3: Budget | C3: Sanjana , Snehal | D3: Budget appoved | E3: PR done for budget line items
B4: Registration form for Researchers (LPI and MPI) | C4: Aakash , Ruchi | D4: Follow-ups ongoing with Hub spocs | E4: 103 PIs registered
B5: Marketing and Branding | C5: Marketing team | D5: Base creatives ready, to be reviewed
B6: Event flow and Agenda | C6: Sanjana / Hardik / Kiran sir | D6: Tentative agenda ready
B7: Registration Kit | C7: HR & Swapneel/ Aditya | D7: Order placed for 200 as of now
B8: Memento | C8: Aakash, Sanjana, Swapneel | D8: Order placed for 12 Qubit crystals
B9: Poster Presentation | C9: Ruchi & Marketing | D9: Follow-ups ongoing with Hub spocs
B10: Tech Expo | C10: Elton & Marketing team | D10: Follow-ups ongoing with Hub spocs
B11: Logistics (RP, Rooms, local transport, inside IITB transport) | C11: Puja/ Deepawali
B12: WiFi and Technical Support | C12: Wajid
B13: VIPs coordination and comms | C13: Puja
B14: Hub/TG Presentations | C14: Srishti, Puja | D14: Template sent to CEOs, deadline April 05
B15: Venue readiness and Event Management monitoring | C15: Santosh, Swapneel and Aditya
B16: Registration Desk | C16: Key Event
B17: Stall Set-up | C17: Elton & Aakash | D17: 20 booth locations identified
B18: Photography and Videography | C18: Key Event
B19: Media and PR | C19: Aakash/Key Events
B20: GH Accommodation - Room allotment | C20: Deepawali/ Puja | D20: 67 Rooms Booked, Awaiting list of attendees from DST/MGB/MTRC
B21: Hostel Accommodation | C21: Deepawali/ Puja | D21: 35 room booking done | E21: Student list to be finalized once poster registrations are received
B22: Gate Pass | C22: Deepawali/Puja/Ruchi
B23: Technical Bulletin | C23: Joyita/Prasobh + Marketing team | D23: Content received from IITB, IISc. Bulletin structure to be decided
B24: Poster Presentation Template | C24: Marketing team | D24: Rutuja to work on A0 size poster template
B25: Students to submit Posters as per template | C25: Ruchi | D25: Emailers to be sent by 25-26, deadline - April 4
B26: Poster Presentation Awards | C26: Marketing + Admin
B27: VIP Escort Volunteers | D27: To be decided
B30: Event Day
B31: Logistics - cab support (9-12) | C31: Deepawali, Srishti
B32: GH and hostel accommodation support (9-12) | C32: Santosh
B33: GH to RP movement | C33: Santosh, Abhishek
B34: Parking at RP | C34: Santosh, Aditya
B35: Tea/Coffee setup at venue plus green room | C35: Swapneel
B36: Registration desk | C36: Key Event + Ruchi, Aditi
B37: Ground floor staff | C37: Puja, Deepawali
B38: VIP Elevator support | C38: Santosh, Aditya
B39: 8th floor staff | C39: Snehal
B40: 9th floor staff | C40: Sanjana, Elton, Joyita, Aditi
B41: Memento, gift arrangement backstage | C41: Jeenal
B42: Ushers | C42: Key Event, Jeenal, Rachana
... B63: VIP Handling overall | C63: Puja

Sheet Attendee List
B2: Sr. No | C2: Name | D2: Institute | E2: Hub | F2: Email | G2: Tag
B3: 1 | C3: Dr. Akshay Naik | D3: Indian Institute of Science Bangalore | E3: IIT Bombay | F3: anaik@iisc.ac.in | G3: PI
B4: 2 | C4: Dr. Akshay Singh | D4: Indian Institute of Science Bangalore | E4: IISc Bangalore | F4: aksy@iisc.ac.in | G4: PI
B5: 3 | C5: Dr. Amitangshu Pal | D5: Indian Institute of Technology Kanpur | E5: IIT Bombay | F5: amitangshu@cse.iitk.ac.in | G5: PI
B6: 4 | C6: Dr. Anil Shaji | D6: Indian Institute of Science Education and Research Thiruvananthapuram | E6: IISc Bangalore | F6: shaji@iisertvm.ac.in | G6: PI
B7: 5 | C7: Dr. Anirban Mitra | D7: Indian Institute of Technology Roorkee | E7: IIT Delhi | F7: anirban.mitra@ph.iitr.ac.in | G7: PI
B8: 6 | C8: Dr. Ankur Raina | D8: Indian Institute of Science Education and Research Bhopal | E8: IIT Madras | F8: ankur@iiserb.ac.in | G8: PI
B9: 7 | C9: Dr. Anshul Jaiswal | D9: Indian Institute of Technology Roorkee | E9: IIT Madras | F9: anshul.jaiswal@ece.iitr.ac.in | G9: PI
B10: 8 | C10: Dr. Anshuman Kumar | D10: Indian Institute of Technology Bombay | E10: IIT Delhi | F10: anshuman.kumar@iitb.ac. in | G10: PI
B11: 9 | C11: Dr. Arijit Sharma | D11: Indian Institute of Technology Tirupati | E11: IIT Madras | F11: arijit@iittp.ac.in | G11: PI
B12: 10 | C12: Dr. Ashok K Mohapatra | D12: National Institue of Science Education and Research Bhubaneswar | E12: IISc Bangalore | F12: a.mohapatra@niser.ac.in | G12: PI
B13: 11 | C13: Dr. Awanish Pandey | D13: Indian Institute of Technology Delhi | E13: IISc Bangalore | F13: awanish@ee.iitd.ac.in | G13: PI
B14: 12 | C14: Dr. Baladitya Suri | D14: Indian Institute of Science Bangalore | E14: IISc Bangalore | F14: surib@iisc.ac.in | G14: PI
... B143: 141 | C143: Shubham Utreja | D143: Prenishq | E143: I-Hub QTF, IISER Pune | F143: shubhamutreja77@gmail.com | G143: Expo
B144: 142 | C144: Sunil Sud | D144: QuNu Labs Pvt Ltd | E144: I-Hub QTF, IISER Pune | G144: Expo
B145: 143 | C145: Arsh Ahmed | D145: QuNu Labs Pvt Ltd | E145: I-Hub QTF, IISER Pune | G145: Expo
B146: 144 | C146: Vamsi Krishna | D146: QpiAI Pvt Ltd | E146: I-Hub QTF, IISER Pune | F146: vamsi.k@qpiai.tech | G146: Expo
B147: 145 | C147: Firoz Tahashildar | D147: QpiAI Pvt Ltd | E147: I-Hub QTF, IISER Pune | F147: Firoz.t@qpiai.tech | G147: Expo
B148: 146 | C148: Devendra Mishra | D148: Quantum AI Global (QAIG) | E148: IIT Madras | F148: devendra.mishra@qulabs.ai | G148: Expo
B149: 147 | C149: Sanjay Chittore | D149: Quantum AI Global (QAIG) | E149: IIT Madras | F149: sanjay@thequantum.ai | G149: Expo
B150: 148 | C150: Ashutosh Singh | D150: IITM CDOT Samgnya Technologies Foundation | E150: IIT Madras | F150: ashutosh@ee.iitm.ac.in | G150: Expo
B151: 149 | C151: Anagha Gayatri M | D151: IITM CDOT Samgnya Technologies Foundation | E151: IIT Madras | F151: anaghagayathri@smail.iitm.ac.in | G151: Expo
B152: 150 | C152: Abhilash Kumar Das | D152: IITM CDOT Samgnya Technologies Foundation | E152: IIT Madras | F152: abhilashkd@iitbhilai.ac.in | G152: Expo
B153: 151 | C153: Anirudh Jaiswal | D153: IITM CDOT Samgnya Technologies Foundation | E153: IIT Madras | G153: Expo
B154: 152 | C154: Bhaskar Sarkar | D154: IITM CDOT Samgnya Technologies Foundation | E154: IIT Madras | F154: bhaskarsarkar1213@gmail.com | G154: Expo
B155: 153 | C155: Abhay Dulta | D155: IITM CDOT Samgnya Technologies Foundation | E155: IIT Madras | F155: phz228454@iitd.ac.in | G155: Expo
B156: 154 | C156: Shubham Prajapati | D156: Synergy Quantum | E156: IIT Madras | F156: shubham.prajapati@synergyquantum.in | G156: Expo
B157: 155 | C157: Snehal Sharma | D157: Synergy Quantum | E157: IIT Madras | F157: snehal@synergyquantum.in | G157: Expo
B158: 156 | C158: Aniket Nag | D158: Qmet Tech Foundation | E158: IIT Bombay | F158: aniketnag24@iitk.ac.in | G158: Expo
B159: 157 | C159: Pranay Mohta | D159: Qmet Tech Foundation | E159: IIT Bombay | F159: pmohta@iitk.ac.in | G159: Expo
B160: 158 | C160: Praveen Hegde | D160: Qmet Tech Foundation | E160: IIT Bombay | F160: p.hegde@physics.iitm.ac.in | G160: Expo
B161: 159 | C161: John Jesudasan | D161: Qmet Tech Foundation | E161: IIT Bombay | F161: johnj.tifr@gmail.com | G161: Expo
B162: 160 | C162: Pooja Gunjal | D162: Qmet Tech Foundation | E162: IIT Bombay | F162: poojagunjal1212@gmail.com | G162: Expo
B163: 161 | C163: Roopa J | D163: Qmet Tech Foundation | E163: IIT Bombay | F163: roopaj@iisc.ac.in | G163: Expo
B164: 162 | C164: Purna Pal | D164: Qmet Tech Foundation | E164: IIT Bombay | F164: purnapal@iisc.ac.in | G164: Expo
B165: 163 | C165: Shouvik Mukherjee | D165: Nostradamus | E165: IIT Bombay | F165: shouvik@qubeats.com | G165: Expo
... B217: 215 | C217: Prof. S Arunkumar | D217: Gandhi Institute of Technology and Management, Gandhinagar, Visakhapatnam, Andhra Pradesh | E217: Teaching Lab | F217: dean_cse@gitam.edu | G217: Teaching Lab
B218: 216 | C218: Prof. Ravindra Kumar Sinha | D218: Delhi Technological University | E218: Teaching Lab | F218: dr_rk_sinha@yahoo.com | G218: Teaching Lab | H218: name to be confirmed
B219: 217 | C219: Dr. Girish J | D219: GMR Institute of Technology, Rajam, Srikakulam, Andhra Pradesh | E219: Teaching Lab | F219: Dr.Girish.Jammigumpula@gmrgroup.in | G219: Teaching Lab
B220: 218 | C220: Dr.Sumalatha Lingamgunta | D220: University College of Engineering Kakinada, East Godavari, Kakinada, Andhra Pradesh | E220: Teaching Lab | F220: lsumalatha@jntucek.ac.in | G220: Teaching Lab
B221: 219 | C221: Dr.Suneetha Eluri | D221: University College of Engineering Kakinada, East Godavari, Kakinada, Andhra Pradesh | E221: Teaching Lab | F221: lsumalatha@jntucek.ac.in | G221: Teaching Lab
B222: 220 | C222: Prof. Anagh Bhaumik | D222: IIT Gandhinagar | E222: Teaching Lab | F222: anagh.bhaumik@iitgn.ac.in | G222: Teaching Lab
B223: 221 | C223: Dr. Aswath Babu | D223: Indian Institute of Information Technology, Dharwad | E223: Teaching Lab | F223: aswath@iiitdwd.ac.in | G223: Teaching Lab
B224: 222 | C224: Prof. Aman Mahajan | D224: Guru Nanak Dev University | E224: Teaching Lab | F224: aman.phy@gndu.ac.in | G224: Teaching Lab
B225: 223 | C225: Dr. Venkata Krishnaiah Kummara | D225: Rajeev Gandhi Memorial College of Engineering and Technology | E225: Teaching Lab | F225: kvkphd84@gmail.com | G225: Teaching Lab
B226: 224 | C226: Dr. Sadu Chiranjeevi | D226: Rajiv Gandhi University of Knowledge Technologies | E226: Teaching Lab | F226: schiranjeevi@rguktn.ac.in | G226: Teaching Lab
B227: 225 | C227: Dr. Dheeraj Kumar Sinha | D227: Indian Institute of Information Technology Bihar | E227: Teaching Lab | F227: dksinha.ece@iiitbh.ac.in | G227: Teaching Lab
B228: 226 | C228: Prof. Sanjeev Kumar | D228: Punjab Engineering College | E228: Teaching Lab | F228: sanjeev@pec.edu.in | G228: Teaching Lab
B229: 227 | C229: Prof. Thomas Andrews Joseph | D229: Shri G.S. Institute of Tech. and Science, Indore, Madhya Pradesh | E229: Teaching Lab | F229: jtandrews@sgsits.ac.in | G229: Teaching Lab
B230: 228 | C230: Dr. Babasaheb Raghunath Sankapal | E230: Teaching Lab | F230: brsankapal@phy.vnit.ac.in | G230: Teaching Lab
B231: 229 | C231: Prof. Jyoti Prakash Kar | D231: National Institute of Technology Rourkela | E231: Teaching Lab | F231: karjp@nitrkl.ac.in | G231: Teaching Lab
B232: 230 | C232: Dr. V Narayanan | D232: IIT Jodhpur | E232: Teaching Lab | F232: vnara@iitj.ac.in | G232: Teaching Lab
B233: 231 | C233: Dr. Haree Shankar Meganathan | D233: Rajalakshmi Institute of Technology | E233: Teaching Lab | F233: sasikumar.s@ritchennai.edu.in | G233: Teaching Lab
B234: 232 | C234: Prof. C. Muthamizhchelvan | D234: SRM Institute of Science and Technology | E234: Teaching Lab | F234: vc@srmist.edu.in | G234: Teaching Lab
B235: 233 | C235: Dr. Atul Kumar | D235: IIT BHU | E235: Teaching Lab | F235: atul.ece@iitbhu.ac.in | G235: Teaching Lab
B236: 234 | C236: Mr. Kishan Kumar Kejriwal | D236: MCKV Institute of Engineering | E236: Teaching Lab | F236: soma.bandyopadhyay@mckvie.edu.in | G236: Teaching Lab
B237: 235 | C237: Dr. Sunil Gupta | D237: QuNu Labs Pvt Ltd | E237: I-Hub QTF | F237: sunil@qnulabs.com | G237: Startup
B238: 236 | C238: Dilip Singh | D238: QuNu Labs Pvt Ltd | E238: I-Hub QTF | F238: dilip@qunulabs.com | G238: Startup
B239: 237 | C239: Dr. Nagendra Nagaraja | D239: QpiAI Pvt Ltd | E239: I-Hub QTF | F239: nagendra.nagaraja@qpiai.tech | G239: Startup
B240: 238 | C240: Sourav Sarkar | D240: Sense-XT Innovations Pvt Ltd | E240: IIT Bombay | F240: sourav.sarkar@jadavpuruniversity.in | G240: Startup
B241: 239 | C241: Pranab Dutta | D241: GDQLabs Pvt Ltd | E241: IIT Bombay | F241: pranab@gdqlabs.com | G241: Startup
B242: 240 | C242: Swavagyashree | D242: Orvis Semi Pvt Ltd | E242: IIT Bombay | F242: swavagyashree@orvissemi.com | G242: Startup
B243: 241 | C243: Subu Gupta | D243: Quantum Biosciences Pvt Ltd | E243: IIT Bombay | F243: subu@quantumbiosciences.ai | G243: Startup
B244: 242 | C244: Hardik Joshi | D244: Qmet Tech Foundation | E244: IIT Bombay | G244: Organizer
B245: 243 | C245: Sanjana Nene | D245: Qmet Tech Foundation | E245: IIT Bombay | G245: Organizer
B246: 244 | C246: Snehal Gosavi | D246: Qmet Tech Foundation | E246: IIT Bombay | G246: Organizer
B247: 245 | C247: Srishti Girish | D247: Qmet Tech Foundation | E247: IIT Bombay | G247: Organizer
B248: 246 | C248: Elton Noronha | D248: Qmet Tech Foundation | E248: IIT Bombay | G248: Organizer
B249: 247 | C249: Ruchi Singh | D249: Qmet Tech Foundation | E249: IIT Bombay | G249: Organizer
B250: 248 | C250: Puja Chakraborty | D250: Qmet Tech Foundation | E250: IIT Bombay | G250: Organizer
B251: 249 | C251: Rachana Shiriskar | D251: Qmet Tech Foundation | E251: IIT Bombay | G251: Organizer
B252: 250 | C252: Aditi Yadav | D252: Qmet Tech Foundation | E252: IIT Bombay | G252: Organizer
B253: 251 | C253: Jeenal Kalal | D253: Qmet Tech Foundation | E253: IIT Bombay | G253: Organizer
B254: 252 | C254: Santosh Shedge | D254: Qmet Tech Foundation | E254: IIT Bombay | G254: Organizer
B255: 253 | C255: Deepawali Khade | D255: Qmet Tech Foundation | E255: IIT Bombay | G255: Organizer
... B270: 268 | C270: Varsha Ingale | D270: Qmet Tech Foundation | E270: IIT Bombay | G270: Organizer
B271: 269 | C271: Dr. Maheshwar Mangat | D271: IIT Bombay | E271: IIT Bombay | F271: maheshwar.mangat@iitb.ac.in <maheshwar.mangat@iitb.ac.in> | G271: Delegate
B272: 270 | C272: Prof. Ajay Kumar Sood | G272: Delegate
B273: 271 | C273: Dr. Ajai Chowdhry | G273: Delegate
B274: 272 | C274: V K Saraswat | G274: Delegate
B275: 273 | C275: Prof. Abhay Karandikar | G275: Delegate
B276: 274 | C276: Dr. JBV Reddy | G276: Delegate
B277: 275 | C277: Dr. Preeti Banzal | G277: Delegate
B278: 276 | C278: Anurag Mishra | G278: Delegate
B279: 277 | C279: Dr. Swati Rawal Dang | G279: Delegate
B280: 278 | C280: Ishan Jawa | G280: Delegate
B281: 279 | C281: Joynarayan Mukherjee | G281: Delegate
B282: 280 | C282: Bhavani Nakka | G282: Delegate
B283: 281 | C283: Prof. P. J. Narayanan | G283: Delegate
... B303: 301 | C303: Arindam Ghosh | G303: Delegate

Sheet TECH EXPO BOOTH Details
A1: Sr. no. | B1: Name of the Hub | C1: Name on the Fascia | D1: Power Requirements | E1: Booth Fascia/ Name | F1: Team Member 1 Name - First Name | G1: Team Member 1 Name - Last Name | H1: Gender | I1: Email Address | J1: Phone Number | K1: Team Member 2 Name - First Name | L1: Team Member 2 Name - Last Name | M1: Gender | N1: Email Address | O1: Phone Number | P1: Upload Product/Technology Image (300 dpi) | Q1: Technology Focus | R1: Brief Description of Your Startup and Product (in 200 words)
A2: BANGALORE
A3: Booth 1 | B3: Foundation for QC Innovation IISc Bangalore | C3: Neutral atom and trapped ion quantum computer | D3: 2 | E3: Neutral atom and trapped ion quantum computer | F3: Saptarishi | G3: Chaudhuri | H3: Male | I3: srishic@rri.res.in | J3: (+91) 7259899430 | K3: Umakant | L3: Rapol | M3: Male | N3: umakant.rapol@iiserpune.ac.in | O3: (+91) 9689908421 | P3: https://www.jotform.com/uploads/Qmet/260672027148052/6494586702916808495/Display.png | Q3: Atom and ion based quantum computing | R3: Our technology consortium focuses on indigenously developing neutral atom and trapped ion based quantum computing platform. While two cloud accessible system will soon be operational and work towards demonstration of the technology readiness is ongoing, we also intend to productise both the full stack system as well as many peripheral components. During the AQC, there will be one 3D scaled down display unit of the actual set-up hosted at RRI + components developed at IISER Pune, NISER Bhubaneswar and IIT Roorkee and IIT Guwahati.
A4: Booth 2 | B4: Foundation for QC Innovation IISc Bangalore | C4: A Highly Scalable Quantum Computer using Silicon Qubits (sharing) | D4: 3 X 220V | E4: A Highly Scalable Quantum Computer using Silicon Qubits (sharing) | F4: Pulak (also part of poster) | G4: Ghoshal | H4: Male | I4: eez248406@ee.iitd.ac.in | J4: (+91) 7290804546 | K4: Deepesh (also part of poster) | L4: Sharma | M4: Male | N4: deepesh.sharma@ee.iitd.ac.in | O4: (+91) 9858911301 | P4: https://www.jotform.com/uploads/Qmet/260672027148052/6495553635606105708/TG3-IITD-Quantum-Computer-Schematic.jpg | Q4: Quantum Computing | R4: To achieve a beyond NISQ (>1000 qubits) quantum computer, high density qubits, passives, and wiring are essential. Silicon CMOS process has the optimum BEOL for such work. With minor tweaks in standard CMOS, a derivative process for fabrication of quantum dot-based qubits can be created, and an all-Silicon Quantum Computer can be realized. In this Technical Group (TG3), we are developing the system at all levels, starting from system-level and then going down to the chip and qubit levels. Our mission objective is to demonstrate a working quantum computer with 50 qubits. | S4: To be merged with Cryogenic electronics for spin qubits
B5: Foundation for QC Innovation IISc Bangalore | C5: Cryogenic Electronics for Spin qubits (sharing) | D5: NA | E5: Cryogenic Electronics for Spin qubits (sharing) | F5: Rajat (also part of poster) | G5: Bharadwaj | H5: Male | I5: rajat21@iisertvm.ac.in | J5: (+91) 9933832246 | K5: Varsha | L5: Jangir | M5: Female | N5: 204120010@iitb.ac.in | P5: https://www.jotform.com/uploads/Qmet/260672027148052/6496502828185510048/nqm%20sub-low_8300.png | Q5: Silicon Quantum Dot Spin Qubits | R5: A suite of advanced cryogenic and qubit-control devices designed to ensure high-fidelity signal integrity and effective noise suppression in quantum experiments. The Cryo Damp-24 is a 24-channel low-pass filter based on a copper powder-epoxy composite, offering a cut-off frequency of 300 MHz for efficient attenuation of high-frequency noise. The μ Shield-12 incorporates 12 isolated DC lines in a compact module, providing comparable filtering performance with enhanced isolation. The San Noise-25 device features a finite ground coplanar waveguide fabricated on sapphire with aluminium, enabling superior thermalization and achieving a cut-off frequency below 100 kHz. Complementing these, the Cryo Pass-L24 is a fully customizable, modular 24-channel cryogenic low-pass filter. For qubit control, the Q-Nest provides a modular PCB system enclosed within a shielding enclosure, supporting 24 DC lines, 8 ohmic lines, and integrated passive filtering. Finally, the Q-CARD-24080601 is a versatile qubit control and readout platform incorporating DC, ohmic, RF, and readout lines, along with environmental shielding, LED integration, and ESD protection mechanisms for robust and reliable operation.
A6: Booth 3 | B6: Foundation for QC Innovation IISc Bangalore | C6: 6 qubit photonic system (sharing) | D6: 4 socket, 10Amp 240V | E6: 6 qubit photonic system (sharing) | F6: Sujai | G6: Matta | H6: Male | I6: sujaimatta@iisc.ac.in | J6: (+91) 9491238120 | K6: Soumya | L6: Asokan | M6: Female | N6: soumyaasokan@iisc.ac.in | O6: (+91) 9567246448 | P6: https://www.jotform.com/uploads/Qmet/260672027148052/6496277264281228497/6qubit-QC.png | Q6: Photonic Quantum Computing | R6: It's a device developed at Photonic Quantum Computing TG at IISc. A 6-qubit photonic system with provision for implementing 4 two-qubit gates, 4 single-qubit gates, and generating a 6-qubit maximally entangled state. Image is a representation; it will be packaged.
B7: Foundation for QC Innovation IISc Bangalore | C7: Photonics Quantum Processor 9(sharing) | D7: No | E7: Photonics Quantum Processor 9(sharing) | F7: Shankar Kumar | G7: Selvaraja | H7: Male | I7: shankarks@iisc.ac.in | J7: (91) 9481283513 | P7: https://www.jotform.com/uploads/Qmet/260672027148052/6502142416158167143/Picture1.png | Q7: Photonics quantum processor | R7: Display of a model of a photonics quantum processor, Wafer display with photonic circuit, single photon emitter chip and testing jig display. | S7: 6.50214e+18
A8: Booth 4 | B8: Foundation for QC Innovation IISc Bangalore | C8: Control & Measurement Electronics for Superconducting Qubits | D8: 4 / 220V | E8: Control & Measurement Electronics for Superconducting Qubits | F8: Shantharam | G8: Kalipatnapu | H8: Male | I8: shantharamk@iisc.ac.in | J8: (+91) 8972246283 | K8: Venkata Pavan Kalyan | L8: Missula | M8: Male | N8: pavkalyan100@gmail.com | O8: (+91) 7294874910 | P8: https://www.jotform.com/uploads/Qmet/260672027148052/6495812735188358844/ConElec-SuperCQ.jpg | Q8: Superconducting Qubits | R8: We will display prototypes of FPGA based control & measurement electronics, cryogenic filters , and Josephson Parametric Amplifiers
A10: PUNE
A11: Sr. no. | B11: Name of the Hub | C11: Name on the Fascia | D11: Power Requirements | E11: Booth Fascia/ Name | F11: Team Member 1 Name - First Name | G11: Team Member 1 Name - Last Name | H11: Gender | I11: Email Address | J11: Phone Number | K11: Team Member 2 Name - First Name | L11: Team Member 2 Name - Last Name | M11: Gender | N11: Email Address | O11: Phone Number | P11: Upload Product/Technology Image (300 dpi) | Q11: Technology Focus | R11: Brief Description of Your Startup and Product (in 200 words)
A12: Booth 1 | B12: I-Hub QTF, IISER Pune | C12: Quanastra Pvt Ltd | D12: 2 | E12: Quanastra Pvt Ltd | F12: Vidur | G12: Raj | H12: Male | I12: vidur.raj@quanastra.com | J12: (+91) 9205771590 | K12: Anand | L12: Mohan | M12: Male | N12: s21027@students.iitmandi.ac.in | O12: (+91) 7678310811 | P12: https://www.jotform.com/uploads/Qmet/260672027148052/6495604869251620860/Picture1.png | Q12: Quantum Sensing | R12: Quanastra is a deep-tech startup operating at the forefront of quantum and photonics technologies, with a long-term vision to establish itself as a hub for quantum and photonics chip manufacturing. In near term, we are developing Single photon detectors, and associated hardware under national Quantum Mission. Some of our market ready products: UHV Fiber Feedthrough, DC cryoelectronic wiring, High Precision Microampere Current. Some of these we will be showcasing at the IIT Bombay Expo. | S12: 6.4956e+18
B13: I-Hub QTF, IISER Pune | C13: SCI-COM SOFTWARE INDIA PRIVATE LIMITED | D13: 4 | E13: SCI-COM SOFTWARE INDIA PRIVATE LIMITED | F13: Vaishnavi | G13: Vaichal | H13: Female | I13: vaishnavi.vaichal@scicomsoftware.com | J13: (+91) 7768074457 | K13: Suhas | L13: Kulkarni | M13: Male | N13: suhas.kulkarni@scicomsoftware.com | O13: (+91) 9403768214 | P13: https://www.jotform.com/uploads/Qmet/260672027148052/6495522526427438722/IMG_1743.JPEG | Q13: Instrumentation and Control for Quantum Technology Research and Development | R13: SCI-COM was founded in 1998 and has been working in areas such as signal and image processing, high-speed FPGA electronics, Digital Signal Processing and microcontroller-based boards, RF modules, power distribution modules (industrial and MIL-grade), software development, and embedded systems. We also provide independent verification and validation services for DRDO and other PSUs. iQUANTROL-1.0 is an Instrumentation and Control Unit to be used in Laboratory Setups for Quantum Technology Research and Development. This unit provides a host computer based GUI Application to configure different Instrumentation and Control parameters required by the Laboratory Setup. It has a high performance electronics platform interfaced over ethernet with the host PC to perform real time functions such as high speed signal generation, high speed signal sampling/acquisition, signal processing for signal features estimation, control loops implementation through embedded software and diagnostics/log reports.
A14: Booth 2 | B14: I-Hub QTF, IISER Pune | C14: Prenishq | D14: 4 | E14: Prenishq | F14: Bodhaditya | G14: Santra | H14: Male | I14: bodhaditya.santra@gmail.com | J14: (+91) 7047373599 | K14: Shubham | L14: Utreja | M14: Male | N14: shubhamutreja77@gmail.com | O14: (+91) 9829825823 | P14: https://www.jotform.com/uploads/Qmet/260672027148052/6495799308513351203/Prenishq%20Laser%20Launch%20flyer%20revised.pdf | Q14: High precision diode laser for quantum computing, sensing, metrology and communication | R14: Prenishq Pvt. Ltd., a spin-off from IIT Delhi and supported by the National Quantum Mission manufactures high precision diode lasers for quantum computing, sensing, metrology and communication. The Prenishq Opal Laser is a high-performance, precision-engineered system designed for quantum research, education, and advanced experiments. With exceptional beam quality, stability, and long-term durability, it’s ideal for seamless integration into scientific and quantum equipment. These lasers stand out for its low cost of ownership, ease of installation, minimal maintenance, light weight, and assured availability to promise. Combining performance, efficiency, and accessibility, Prenishq’s lasers position India at the forefront of laser technology and quantum innovation.
A15: Booth 3 | B15: I-Hub QTF, IISER Pune | C15: QuNu Labs Private Limited | D15: 2 | E15: QuNu Labs Private Limited | F15: Sunil | G15: Sud | H15: Male | J15: (+91) 7899791155 | K15: Arsh Ahmed | M15: Male | P15: https://www.jotform.com/uploads/Qmet/260672027148052/6496353206325463976/QNu%20Product.png | Q15: Quantum Communication | R15: QNu Labs is India’s pioneering quantum cybersecurity company focused on building technologies that protect digital infrastructure from future quantum computing threats. Founded in 2016 and incubated at IIT Madras Research Park, the company’s mission is to make India self-reliant in digital security while enabling a global transition toward quantum-safe communication. As quantum computing advances, today’s encryption methods such as RSA and ECC will become vulnerable, posing serious risks to governments, financial systems, telecom networks, and critical infrastructure. QNu Labs addresses this challenge through an indigenous ecosystem of quantum-safe technologies that combine hardware and software innovations. Its portfolio includes Armos (Quantum Key Distribution), Tropos (Quantum Random Number Generator), the QShield crypto-agile security platform, and quantum communication chips for secure edge systems. QNu’s hybrid architecture integrates quantum physics-based security with post-quantum cryptography, enabling organizations to transition to quantum-safe infrastructure without replacing existing systems. These solutions secure communications, data, and identity across sectors such as defence, telecom, banking, and government. With multiple patents, defence validations, and real-world deployments—including long-distance quantum networks—QNu Labs is positioning India at the forefront of the emerging quantum security era, enabling governments and enterprises to achieve digital sovereignty, long-term data protection, and resilient cybersecurity for the post-quantum world.
A16: Booth 4 | B16: I-Hub QTF, IISER Pune | C16: QpiAI India Private Limited | D16: 2 sockets 220v | E16: QpiAI India Private Limited | F16: Vamsi | G16: Krishna | H16: Male | I16: vamsi.k@qpiai.tech | J16: (91) 7895873873 | K16: Firoz | L16: Tahashildar | M16: Male | N16: Firoz.t@qpiai.tech | O16: () 7353155091 | P16: https://www.jotform.com/uploads/Qmet/260672027148052/6500608394918164434/IMG_1064%20%281%29.jpeg | Q16: Quantum error correction | R16: QpiAI QEC is developed to enhance qubit reliability and system performance. Using advanced algorithms , it detects and corrects errors in real time, improving fidelity and extending coherence time of physical qubits. The system implements a distance-5 rotated surface code using 49 physical qubits. Each decoder instance runs on a single QpiAI Kaveri QPU, which provides 64 qubits, allowing one decoder instance per chip. The architecture is optimized to support efficient decoding and integration with existing quantum hardware. | S16: 6.50061e+18
A19: MADRAS
A20: Sr. no. | B20: Name of the Hub | C20: Name on the Fascia | D20: Power Requirements | E20: Booth Fascia/ Name | F20: Team Member 1 Name - First Name | G20: Team Member 1 Name - Last Name | H20: Gender | I20: Email Address | J20: Phone Number | K20: Team Member 2 Name - First Name | L20: Team Member 2 Name - Last Name | M20: Gender | N20: Email Address | O20: Phone Number | P20: Upload Product/Technology Image (300 dpi) | Q20: Technology Focus | R20: Brief Description of Your Startup and Product (in 200 words)
A21: Booth 1 | B21: IITM CDOT Samgnya Technologies Foundation at IIT Madras | C21: Quantum AI Global (QAIG) | D21: 3 | E21: Quantum AI Global (QAIG) | F21: Devendra | G21: Mishra | H21: Male | I21: devendra.mishra@qulabs.ai | J21: (+91) 7398725444 | K21: Sanjay | L21: Chittore | M21: Male | N21: sanjay@thequantum.ai | O21: (+91) 9700699999 | P21: https://www.jotform.com/uploads/Qmet/260672027148052/6506955152498788044/QAIG.jpg | Q21: Quantum Key Distribution & Q-Memory | R21: Enhancing QAIG’s atomic memory system to be compatible with telecom wavelengths significantly broadens its applicability across quantum communication systems. It enables quantum key distribution (QKD) and quantum networking over existing fiber links by shifting photons into the low-loss telecom band. | S21: 6.50696e+18
A22: Booth 2 | B22: IITM CDOT Samgnya Technologies Foundation at IIT Madras | C22: QuiLA - TG! | D22: 4 | E22: QuiLA - TG! | F22: Ashutosh | G22: Singh | H22: Male | I22: ashutosh@ee.iitm.ac.in | J22: (+91) 9122866323 | K22: Anagha Gayatri | L22: M | M22: Female | N22: anaghagayathri@smail.iitm.ac.in | O22: (+91) 8754325797 | P22: https://www.jotform.com/uploads/Qmet/260672027148052/6502691282497432140/QuiLA.jpg | Q22: QuiLA | R22: Working under TG-1 with Prof. Anil Prabhakar | S22: 6.50269e+18
B23: IITM CDOT Samgnya Technologies Foundation at IIT Madras | C23: Settlor Lab, IIT Kanpur | D23: 3 | F23: Abhilash Kumar | G23: Das | H23: Male | I23: abhilashkd@iitbhilai.ac.in | J23: (+91) 8617844701 | P23: https://www.jotform.com/uploads/Qmet/260672027148052/6501556695026954019/CWLite.jpeg | Q23: Side Channel Analysis | R23: CRYSTALS-Kyber is a CCA2-secure key encapsulation mechanism defined over the quotient ring ( Z_q[x]/(X^n + 1) ), with parameters ( q = 3329 ) and ( n = 256 ). It has three variants—Kyber-512, Kyber-768, and Kyber-1024—based on different security levels. The scheme consists of three main operations: key generation, encapsulation, and decapsulation. Although the algorithm itself is secure, its hardware implementation is vulnerable to side-channel attacks due to inherent physical leakage. This work demonstrates a successful attack using Correlation Power Analysis (CPA). For trace acquisition, ChipWhisperer CW305 was used along with ChipWhisperer Lite, enabling efficient and cost-effective power trace collection. A total of 50,000 random and 50,000 fixed traces were captured to perform TVLA (Test Vector Leakage Assessment). The results showed TVLA values consistently above 4.5, often exceeding 20 and even reaching beyond 40, confirming significant leakage. The attack targets the decapsulation step, specifically the computation ( v - s^T u ), focusing on the point-wise multiplication ( s^T . u ). A chosen ciphertext attack was conducted on the hardware implementation, which operates with a latency of 256 clock cycles. Approximately 10,000 traces were required to recover one coefficient of the secret key, resulting in about 280,000 traces to extract the full key. | S23: 6.50156e+18
B24: IITM CDOT Samgnya Technologies Foundation at IIT Madras | C24: IIT Bhilai: Fault Injection Attack on Kyber-768 | D24: 2 sockets, 220V | H24: Male | J24: (+91) 9362672150 | K24: Anirudh | L24: Jaiswal | M24: Male | O24: (+91) 7439215216 | P24: https://www.jotform.com/uploads/Qmet/260672027148052/6502483482521778987/cw-lite-32.jpg.jpeg | Q24: Clock glitching | R24: The team will demonstrate a practical fault-injection attack (published in ASIACRYPT 2021 by Xagawa et al.) on Key Encapsulation Mechanism (CRYSTALS-Kyber) using ChipWhisperer Lite Part - I. The demo is followed by the recovery of long-term secret. First, the board specifications are configured, the firmware is compiled, and the clock glitching parameters are set before running the main glitching script. The process then involves sweeping through the maximum ranges of the parameters, namely width (w) and offset (o). By analyzing combinations of (w, o, ext_o), instances of crashes and resets can be identified, which confirm that the glitch is affecting the execution pipeline of the algorithm. The parameter ext_o plays a crucial role, as it determines when the capture board inserts the glitch after receiving the trigger, allowing precise control of the glitch timing at the nanosecond level within a clock cycle. As a result, the expected outcomes include downgrading the security of Kyber-768 from CCA-secure to CPA-secure through fault injection, and obtaining a 32-byte shared secret K for any crafted ciphertext. | S24: 6.50248e+18
A25: Booth 3 | B25: IITM CDOT Samgnya Technologies Foundation at IIT Madras | C25: TAHQEECAT | D25: 3 | E25: TAHQEECAT | F25: Bhaskar | G25: Sarkar | H25: Male | I25: bkanseri@physics.iitd.ac.in | J25: (+91) 9811026412 | K25: Abhay | L25: Dutta | M25: Male | N25: phz228454@iitd.ac.in | O25: (+91) 9811026412 | P25: https://www.jotform.com/uploads/Qmet/260672027148052/6506962512498199842/TAHQEECAT.jpg | Q25: Entangled photon source at telecom wavelength | R25: Trusted-node Free Hybrid Quantum Secure Communication Network (TAHQEECAT) | S25: 6.50696e+18
A26: Booth 4 | B26: IITM CDOT Samgnya Technologies Foundation at IIT Madras | C26: Synergy Quantum | D26: 3 | E26: Synergy Quantum | F26: Shubham | G26: Prajapati | H26: Male | I26: shubham.prajapati@synergyquantum.in | J26: (+91) 9818987581 | K26: Snehal | L26: Sharma | M26: Female | N26: snehal@synergyquantum.in | O26: (+91) 7276249440 | P26: https://www.jotform.com/uploads/Qmet/260672027148052/6506943952498197516/SynergyQuantum.jpg | Q26: PQC-Secure 5G Core | R26: We are focused on Post Quantum Cryptography and we are currently incubated with Samgnya on Quantum Secure 5GCore | S26: 6.50694e+18
A31: BOMBAY
A32: Sr. no. | B32: Name of the Hub | C32: Name on the Fascia | D32: Power Requirements | E32: Booth Fascia/ Name | F32: Team Member 1 Name - First Name | G32: Team Member 1 Name - Last Name | H32: Gender | I32: Email Address | J32: Phone Number | K32: Team Member 2 Name - First Name | L32: Team Member 2 Name - Last Name | M32: Gender | N32: Email Address | O32: Phone Number | P32: Upload Product/Technology Image (300 dpi) | Q32: Technology Focus | R32: Brief Description of Your Startup and Product (in 200 words)
A33: Booth 1 | B33: Qmet Tech Foundation at IIT Bombay | C33: Quantum Imaging Techncial Group, IIT Kanpur | D33: One Socket (5/15 Amp) for Image Rotator and Two Sockets (5/15 Amp) | E33: Quantum Imaging Techncial Group, IIT Kanpur | F33: Aniket | G33: Nag | H33: Male | I33: aniketnag24@iitk.ac.in | J33: (+91) 8972799320 | K33: Pranay (also in poster) | L33: Mohta | M33: Male | N33: pmohta@iitk.ac.in | O33: () 7980625513 | P33: https://www.jotform.com/uploads/Qmet/260672027148052/6501594666024789905/coherence%20detector.jpg https://www.jotform.com/uploads/Qmet/260672027148052/6501594666024789905/image%20rotator.jpg | Q33: Quantum imaging and high-dimensional quantum information | R33: 1. Image Rotator: This can be used for rotating any wavefront with ( Angular Deviation < 1 milli-radian and Mean Polarisation Change < 5%). The commercially available IRs have angular deviation > 100 milli-radian and Mean Polarisation Changes are > 40%). This can be commercialised and will have application in high-dimensional classical and quantum information and quantum imaging. 2. Spatial Coherence Detector: Device for measuring spatial coherence. This is a detector for measuring complex spatial coherence of light, with more than 95% fidelity in the presence of background noise of signal to noise ratio (SNR) as low as 1/10. This is a crucial device for noise-resilient imaging. | S33: 6.50159e+18
A34: Booth 2 | B34: Qmet Tech Foundation at IIT Bombay | C34: - Magnetic microscope based on NV- centers in diamond (sharing) | D34: 15A | F34: Prasobh | G34: Padmanabhan | H34: Male | I34: prasobh.padmanabhan@qmettech.com | J34: (+91) 8073277036 | K34: Shishir | L34: Dasika | M34: Male | N34: shishir.dasika@qmettech.com | O34: () 73820336590 | P34: https://www.jotform.com/uploads/Qmet/260672027148052/6502451804853886749/QDM_Image.jpg | Q34: NV Centre Sensing | R34: The Quantum Diamond Microscopes (QDM) works in room temperature and generates magnetic field maps, which can be used for the detection of Hardware trojans. The QDM maps the magnetic field of a chip while it processes the data. By comparing this map to a trusted chip, defense analysts can spot tiny, unauthorized circuits that shouldn't be there. Similarly, these magnetic field maps can be used for the defect detection of chips. They can also help in non-destructively reverse engineering the chips, by revealing the internal architecture. Qmet’s quantum diamond microscope delivers high-performance magnetic imaging by combining a magnetic field sensitivity of 0.7 µT/√Hz with a spatial resolution of 1 µm. This configuration allows for the detection of subtle magnetic field variations while maintaining the ability to resolve localized features at the micron scale. The system features a 100 µm field of view, enabling simultaneous wide-field characterization of magnetic textures or current distributions across a significant sample area. Side illumination, Normal illumination and Cryogenic setup of QDM are available in the lab. Technical specifications: Sensitivity: 0.7 µT/√Hz, Resolution: 1 um, FOV: 100 µm | S34: 6.50245e+18
B35: Qmet Tech Foundation at IIT Bombay | C35: Quantum Diamond Magnetometer | D35: 15A | F35: Vinayak | G35: Rane | H35: Male | I35: vinayak.rane@qmettech.com | J35: (+91) 9867236112 | K35: Abhijeet | L35: Ghodgaonkar | M35: Male | N35: abhijeet.ghodgaonkar@qmettech.com | O35: () 9962648741 | P35: https://www.jotform.com/uploads/Qmet/260672027148052/6502460634853052624/MagPI_Image_8231.jpg | Q35: NV Centre Sensing | R35: Quantum magnetometers offer a potential alternative for aerial navigation in environments where GPS is unreliable. By utilizing the Earth’s magnetic field, these sensors provide a passive navigation source that is difficult to defeat. While the technology is still maturing, it holds specific value for defense and space sectors requiring positioning redundancy in contested or remote areas. Additionally, the high sensitivity of these devices may improve the detection of localized magnetic anomalies, such as those generated by submerged vessels or metallic structures. Ultimately, integrating quantum magnetometry into existing sensor suites could provide a potential solution to vulnerabilities of satellite-dependent systems. Qmet’s magnetometer offers high-precision magnetic field characterization with a sensitivity of 0.7 nT/√Hz and full vector measurement capabilities. Operating within a bandwidth of DC to 0.1 kHz, the system is optimized for stable static measurements and low-frequency signal detection. It features an expansive dynamic range spanning from pT to mT levels, allowing it to transition seamlessly between measuring subtle fluctuations and strong magnetic environments. Consuming 50 W of power, the device is designed to maintain robust performance for industrial or laboratory-grade applications. We have already working on improving the form factor to make it compatible with a variety of mobile applications. Technical specifications: Sensitivity: 0.7 pT/√Hz Bandwidth: DC – 0.1 kHz, Dynamic Range: pT to mT, Power: 50 W, Vector capability: Yes | S35: 6.50246e+18
B36: Qmet Tech Foundation at IIT Bombay | C36: Quantum Diamond Magnetometer (sharing) | D36: 4 sockets with 230 V Ac | F36: Vinayak | G36: Rane | H36: Male | I36: vinaya.rane@qmettech.com | J36: (+91) 9867236112 | K36: Abhijeet | L36: Ghodgaonkar | M36: Male | N36: abhijeet.ghodgaonkar@qmettech.com | O36: (+91) 9962648741 | P36: https://www.jotform.com/uploads/Qmet/260672027148052/6502478419741009952/MagPI_Photo_2898.JPG | Q36: NV Centre Sensing | R36: Quantum magnetometers offer a potential alternative for aerial navigation in environments where GPS is unreliable. By utilizing the Earth’s magnetic field, these sensors provide a passive navigation source that is difficult to defeat. While the technology is still maturing, it holds specific value for defense and space sectors requiring positioning redundancy in contested or remote areas. Additionally, the high sensitivity of these devices may improve the detection of localized magnetic anomalies, such as those generated by submerged vessels or metallic structures. Ultimately, integrating quantum magnetometry into existing sensor suites could provide a potential solution to vulnerabilities of satellite-dependent systems. Qmet’s magnetometer offers high-precision magnetic field characterization with a sensitivity of 0.7 nT/√Hz and full vector measurement capabilities. Operating within a bandwidth of DC to 0.1 kHz, the system is optimized for stable static measurements and low-frequency signal detection. It features an expansive dynamic range spanning from pT to mT levels, allowing it to transition seamlessly between measuring subtle fluctuations and strong magnetic environments. Consuming 50 W of power, the device is designed to maintain robust performance for industrial or laboratory-grade applications. We have already working on improving the form factor to make it compatible with a variety of mobile applications. Technical specifications: Sensitivity: 0.7 nT/√Hz Bandwidth: DC – 0.1 kHz, Dynamic Range: pT to mT, Power: 50 W, Vector capability: Yes | S36: 6.50248e+18
B37: Qmet Tech Foundation at IIT Bombay | C37: Lab grown diamond | D37: 0 | F37: M. S. Ramachandra Rao | G37: M | H37: Male | I37: msrrao@iitm.ac.in | J37: (+91) 7397316470 | K37: Rajeev | L37: Gandhi | M37: Male | P37: https://www.jotform.com/uploads/Qmet/260672027148052/6506911136333847079/DiamondSamples_RP_3526.png | Q37: NV centre sensing | R37: These are high-quality high purity diamond samples made by India Centre for Labgrown Diamonds (InCent LGD) at IIT Madras. As part of the centre we also have characterisation facilities that researchers and companies can access. | S37: 6.50691e+18
B38: Qmet Tech Foundation at IIT Bombay | C38: Control electronics (SPELLab, IITM) | D38: 1 | F38: Suthinthraraj | G38: B | H38: Male | I38: ep23b052@smail.iitm.ac.in | J38: (+91) 7010895601 | K38: Aadit | L38: Chugh | M38: Male | N38: ep22b019@smail.iitm.ac.in | P38: https://www.jotform.com/uploads/Qmet/260672027148052/6506926056339673188/control%20electronics.jpg | Q38: Control electronics for NV sensing but can be useful for quantum tech too | R38: These are products we are developing under the NQM mission in the SPELLab (PI: Praveen Bhallamudi). These are control electronics products that include: Synchronisation pulse generators for quantum control sequences, frequency detectors (alternate to zero cross type), PLL. We have PoCs for these. We are currently working on developing digital lock-in with PLL and PID controllers for scanned probe controllers. | S38: 6.50693e+18
B39: Qmet Tech Foundation at IIT Bombay | C39: ISMO Biophotonics | D39: 0 | F39: Ikram | G39: Khan | H39: Male | I39: Ikram@ismobiophotonics.com | J39: (+91) 95515 59159 | K39: Praveen | L39: Hegde | M39: Male | N39: p.hegde@physics.iitm.ac.in | P39: https://www.jotform.com/uploads/Qmet/260672027148052/6506935246337613220/ISMO%20Balanced%20detector.jpg | Q39: Photodetectors for quantum technologies | R39: ISMO Biophotonics aims at the development of cutting edge medical devices. As part of our work with optics, they are also developing photodetectors in conjunction with SPELLab at IITM. They are being used in NV sensing and other experiments. (https://ismobiophotonics.com) | S39: 6.50694e+18
B40: Qmet Tech Foundation at IIT Bombay | C40: Quazartech | D40: No | F40: Joshua | G40: Mattew | H40: Male | I40: support@quazartech.com | J40: (+91) 1141828927 | K40: Deshdeep | L40: Sahdev | M40: Male | P40: https://www.jotform.com/uploads/Qmet/260672027148052/6506951446337177374/QT-AFM.jpg | Q40: Scanned probe microscope and probes | R40: Quazar Tech have developed a quartz tuning fork (QTF)- based AFM system that is highly cost effective (~3X less price) and is well suited for the development of NV-diamond based scanned probe microscopes. They also make the QTF scanning probes as well. Their first AFM system has just been successfully installed at SPELLab at IITM and is performed well during testing with standardised samples. | S40: 6.50695e+18
B41: Qmet Tech Foundation at IIT Bombay | C41: TIFR-QMet cryogenic inertial positioner | D41: four 5 amps power point with switches. | F41: John | G41: Jesudasan | H41: Male | I41: johnj.tifr@gmail.com | J41: (+91) 9869279569 | K41: Pooja | L41: Gunjal | M41: Female | N41: poojagunjal1212@gmail.com | O41: (+91) 8010538448 | P41: https://www.jotform.com/uploads/Qmet/260672027148052/6506815553427022903/Picsart_26-03-30_17-33-41-145.jpg | Q41: we develop a compact, low cost Nanopositioning system capable of precise motion at nanometer scale over millimetre ranges and operating at cryogenic temperature (down to 2.0 K) | R41: The inertial nanopositioner has a very compact, lightweight and simple construction and operates using a slip-stick mechanism driven by piezoelectric actuation. The basic design has three principal parts. The active part is a piezoelectric ceramic stack, glued to a moving stage on one side and the other side is glued to a triangular metallic monorail, acting as the guiding rod. The system is supported by a fully automated, microcontroller-based control electronics with computer interfacing. Sawtooth waveform with an amplitude of 6 to 60 volts is essential in driving the piezoelectric element. We generate a sawtooth waveform using analog output from a microcontroller and OP-amp based amplifier. We use LabVIEW or python-based user interface to control the mode of operation, amplitude and frequency of the sawtooth. X and Y nanopositioner can be stack on the Z-nanopositioner. Currently fabricated two stacks of X-Y-Z nanopositioners, each with footprints of 15 × 15 mm² and 24 × 24 mm², respectively. Also the position of the nanopositioner can be sensed with an Encoder module which is incorporated within the nanopositioner. | S41: 6.50682e+18
A42: Booth 3 | B42: Qmet Tech Foundation at IIT Bombay | C42: V-PAR Microsystems Pvt. Ltd. | D42: 2 sockets and One monitor | E42: V-PAR Microsystems Pvt. Ltd. | F42: Roopa | G42: J | H42: Female | I42: roopaj@iisc.ac.in | J42: (91) 9739815213 | K42: Purna | L42: Pal | M42: Female | N42: purnapal@iisc.ac.in | O42: (91) 8617013318 | P42: https://www.jotform.com/uploads/Qmet/260672027148052/6504131075184348606/Vapor%20cell-Tech.jpeg | Q42: Chip-Scale Atomic Metrology | R42: Our startup is a deep-tech venture focused on the indigenization of high-performance MEMS alkali vapor cells, the essential "physics package" for miniaturized quantum technologies. By moving away from traditional, manual glass-blowing techniques toward automated, wafer-level semiconductor batch fabrication, we produce hermetically sealed Rubidium and Cesium cells at a scale and precision previously unavailable in the domestic market. Our core product enables the transition of quantum sensors from bulky laboratory setups to chip-scale components, specifically targeting the Strategic Sector for ISRO and DRDO's GPS-denied navigation and satellite timing requirements. Beyond defense, we provide the hardware foundation for 5G/6G network synchronization and advanced medical brain imaging via Optically Pumped Magnetometers (OPMs). Based within the IISc-CeNSE ecosystem, we bridge the critical gap between complex quantum physics and industrial mass production. Our mission is to secure a sovereign, ITAR-free supply chain for the global quantum metrology market, offering high-reliability, low-power sensing solutions that are ready for seamless integration into the next generation of aerospace, telecommunications, and healthcare infrastructure. | S42: 6.50413e+18
A43: Booth 4 | B43: Qmet Tech Foundation at IIT Bombay | C43: QuBeats | D43: 2 sockets/ 220 VAC | E43: QuBeats | F43: Shouvik | G43: Mukherjee | H43: Male | I43: shouvik@qubeats.com | J43: (+91) 8777488192 | K43: Pritam | L43: Das | M43: Male | N43: pritam@qubeats.com
A46: DELHI
A47: Sr. no. | B47: Name of the Hub | C47: Name on the Fascia | D47: Power Requirements | E47: Booth Fascia/ Name | F47: Team Member 1 Name - First Name | G47: Team Member 1 Name - Last Name | H47: Gender | I47: Email Address | J47: Phone Number | K47: Team Member 2 Name - First Name | L47: Team Member 2 Name - Last Name | M47: Gender | N47: Email Address | O47: Phone Number | P47: Upload Product/Technology Image (300 dpi) | Q47: Technology Focus | R47: Brief Description of Your Startup and Product (in 200 words)
A48: Booth 1 | B48: QMD Foundation at IIT Delhi | C48: III-V Semiconductor based LNA and SPAD | D48: 3/220 | E48: III-V Semiconductor based LNA and SPAD | F48: Rajendra | G48: Singh | H48: Male | I48: rsingh@physics.iitd.ac.in | J48: (91) 9582774442 | K48: Samaresh | L48: Das | M48: Male | N48: samareshdas@care.iitd.ac.in | O48: (91) 9899130814 | P48: https://www.jotform.com/uploads/Qmet/260672027148052/6501600758606575847/Picture2.jpg | Q48: Quantum Materials and Devices | R48: Low Noise Amplifier (LNA) • High-performance LNAs using SiGe technology with a COTS transistor tested at room temperature • Achieved noise figure < 1.4 dB over 1.5–4.5 GHz • InP-based dies introduced to reduce noise figure and improve input matching • Operating frequency range: 1–5 GHz • Two-stage cascaded and balanced LNAs investigated • Devices use 200 μm and 150 μm gate-width InP HEMTs • Cascaded LNA performance (296 K, unconditionally stable): o Gain: 25.4 dB o Noise figure: < 0.9 dB o Input return loss: > 5.6 dB • Achieved performance parameters: o Return loss: > 15 dB o Gain: 24.7 dB o Noise figure: < 1.18 dB Single-Photon Avalanche Detector (SPAD) • Device structure: InGaAs/InP SAGCM SPAD • Layers: absorption, grading, charge, and multiplication regions • TCAD simulations used to study: o Charge layer engineering o Zn diffusion effects o Breakdown characteristics • Electric field confined in multiplication region (~3.5 × 10⁵ V/cm) • Absorption region maintains low electric field (< 1 × 10⁵ V/cm) • Device designed for 1550 nm wavelength (telecommunication band) • Fabrication includes hard mask design for planar and mesa SPADs • Integrated simulation and fabrication improve: o Photon Detection Efficiency (PDE) o Noise performance | S48: 6.5016e+18
A49: Booth 2 | B49: QMD Foundation at IIT Delhi | C49: 2D Photon Emitter & Avalanche Detector Arrays | D49: 3/220V | E49: 2D Photon Emitter & Avalanche Detector Arrays | F49: Prof. Saurabh | G49: Lodha | H49: Male | I49: slodha@iitb.ac.in | J49: (+91) 9819927460 | K49: Prof. Anshuman | L49: Kumar | M49: Male | N49: anshuman.kumar@iitb.ac.in | O49: (+91) 9958713346 | P49: https://www.jotform.com/uploads/Qmet/260672027148052/6501616470659994834/2D%20Photon%20Emitter%20%26%20Detector%20Arrays.jpg | Q49: Qunatum Materials & Devices | R49: 1. India’s 1st (a) quantum emitter array chip and (b) submicron 2D Avalanche photodetector and. 2. Images and Schematics of (a) hBN based device with integrated nanocavity for optimized and (b) brightness WSe₂ flake based device with Ti/Pt/Au (5 nm/30 nm/100 nm) and Ti/Ni/Au (5 nm/30 nm/100 nm) contacts. 3. Optical images of (a) the device on Si/SiO2 substrate for potential application of large area arrays of SPE arrays and (b) an array of ALD grown MoS2 transistors transferred on a back gate Si/SiO2 substrate for potential application of large area arrays of APDs. | S49: 6.50162e+18
A50: Booth 3 | B50: QMD Foundation at IIT Delhi | C50: 2D Transfer Setup & Precision Power Supply | D50: 3/220V | E50: 2D Transfer Setup & Precision Power Supply | F50: Prof. Ashish | G50: Arora | H50: Male | I50: ashish.arora@iiserpune.ac.in | J50: (+91) 9892294386 | P50: https://www.jotform.com/uploads/Qmet/260672027148052/6501618690652254627/2D%20Transfer%20Setup%20%26%20Precision%20Power%20Supply.jpg | Q50: Qunatum Materials & Devices | R50: (a) Key feature of 2D materials transfer setup: 1. Advanced optical & imaging capabilities: Includes Koehler illumination, integrated photoluminescence imaging/spectroscopy (532 nm excitation), and reflectance spectroscopy (450–750 nm). 2. Flexible sample handling & automation: Supports tilt/rotation, up to 20 mm substrates, heating to 180 °C, remote XYZ control, and custom imaging software. (b) High performance electronics engineered power supply for quantum technologies: Precision ~ 1–10 ppm current & voltage sources | S50: 6.50162e+18
A51: Booth 4 | B51: QMD Foundation at IIT Delhi | C51: Silicon Nitride Micro Ring Resonators (MRR) and Optical Nanofiber (ONF) Tip | D51: 3/220 | E51: Silicon Nitride Micro Ring Resonators (MRR) and Optical Nanofiber (ONF) Tip | F51: Shailendra Kumar | G51: Varshney | H51: Male | I51: skvarshney@ece.iitkgp.ac.in | J51: (91) 3222-283504 | K51: Rajesh | L51: Kumar | M51: Male | N51: rajesh.kumar@ph.iitr.ac.in | O51: (91) 4869 | P51: https://www.jotform.com/uploads/Qmet/260672027148052/6501626320656386319/TG3.png | Q51: Quantum Materials and Devices | R51: Si3N4 Micro Ring Resonators • High-Q, low-loss resonators on Silicon Nitride platforms for narrow linewidth filtering, frequency comb generation, and photon-pair production via nonlinear optics • Si3N4 waveguides optimized for zero-dispersion operation over 700–1100 nm were designed with thicknesses of 200–500 nm and heights of 100–200 nm • First-round fabrication of micro-ring resonators with bus–waveguide coupling gaps ≥200 nm successfully completed, enabling wavelength-selective routing and resonant enhancement for quantum photonic circuits • Coupled ring–bus structures used to control light coupling for filtering, switching, and nonlinear interactions. Optical nanofiber (ONF) Tip Fabricated Probe • Optical nanofiber tapered tips allow strong evanescent field interaction for single-photon coupling and near-field sensing. • Sub-wavelength diameter (D < lamda) . • Fundamental mode (HE11) as the only guided mode • Strong Transverse Confinement of evanescent field manipulating atoms and photons • Quantum Channel in inline fiber network demonstrated. | S51: 6.50163e+18

Sheet footfall
L1: Hardik
L2: sanjana
B3: Expo | C3: 25 | D3: 20/20 | L3: srishti
B4: Poster | C4: 29 | D4: 16/17 | L4: elton
B5: Student/JRF/SRF | C5: 24 | L5: ruchi
B6: PI | C6: 104 | D6: (including IISER Pune PD) | L6: aakash
B7: Qmet | C7: 28 | L7: rutuja
B8: DST / MGB/ MTRC | C8: 30 | L8: snehal
B9: CEO | C9: 5 | L9: swapneel
B10: Remaining Hubs Staff | C10: 10 | L10: wajid
B11: Announcements | C11: 29 | L11: deepawali
B12: Total | C12: =SUM(C3:C11) -> 284 | L12: rachana
L13: joyita
L14: santosh
L15: shishir
L16: prashobh
L17: vinayak
L18: abhijeet
L19: aditi
L20: pavithra
L21: jeenal
L22: heena
L23: nitin
L24: aditya
... L28: Puja

Sheet Registrations
A1: Submission Date | B1: Name - First Name | C1: Name - Last Name | D1: Category | E1: Name of the Hub/Institution | F1: Contact Number | G1: E-mail | H1: Designation | I1: Your Company/Institution | J1: City/Town | K1: Hub | L1: Corrected Hub values | M1: TG | N1: Correct TG Names | P1: PI Name
A2: 46079.852 | B2: Ankur | C2: Raina | D2: Academician/Researcher | E2: IISER BHOPAL | F2: (+91) 9900495182 | G2: ankur@iiserb.ac.in | H2: Assistant Professor | J2: Bhopal | K2: =VLOOKUP(G2,Dataset!F:H,2,0) -> IIT Madras | L2: IIT Madras | M2: =VLOOKUP(G2,Dataset!F:H,3,0) -> TAHQEECAT
A3: 46079.9 | B3: Neel Kanth | C3: Kundu | D3: Academician/Researcher | E3: Quantum Communications | F3: (+91) 9891901100 | G3: neelkanth@iitd.ac.in | H3: Assistant Professor | J3: New Delhi | K3: =VLOOKUP(G3,Dataset!F:H,2,0) -> IIT Madras | L3: IIT Madras | M3: =VLOOKUP(G3,Dataset!F:H,3,0) -> TAHQEECAT
A4: 46079.905 | B4: Veeresh Vidyadhar | C4: Deshpande | D4: Academician/Researcher | E4: Indian Institute of Technology Bombay | F4: (91) 9108878742 | G4: veeresh@gmail.com | H4: Associate Professor | J4: Mumbai | K4: =VLOOKUP(G4,Dataset!F:H,2,0) -> #N/A | L4: IIT Bombay|IISc Banglore | M4: =VLOOKUP(G4,Dataset!F:H,3,0) -> #N/A | N4: TG 1 Kasturi Saha | TG 5 Quantum Computers with superconducting qubits
A5: 46080.655 | B5: Ravikiran | C5: Yeleswarapu | D5: Academician/Researcher | E5: BITS-Pilani Hyderabad, HUB: Quantum Computing HUB,IISC | F5: (+91) 8008547840 | G5: ravikiran.y@hyderabad.bits-pilani.ac.in | H5: Asst Professor | J5: Hyderabad | K5: =VLOOKUP(G5,Dataset!F:H,2,0) -> IISc Bangalore | L5: IISc Bangalore | M5: =VLOOKUP(G5,Dataset!F:H,3,0) -> TG 3 Design and Demonstration of a Highly Scalable Quantum Computer using Semiconducting Qubits | N5: TG 3 Design and Demonstration of a Highly Scalable Quantum Computer using Semiconducting Qubits
A6: 46082.977 | B6: Prasana | C6: Sahoo | D6: Academician/Researcher | E6: QMD/IIT Delhi Hub | F6: (+91) 7894525638 | G6: prasanasahoo@gmail.com | H6: Assistant Professor | J6: Kharagpur | K6: =VLOOKUP(G6,Dataset!F:H,2,0) -> #N/A | L6: IIT Delhi | M6: =VLOOKUP(G6,Dataset!F:H,3,0) -> #N/A | N6: TG2: Wafer-scale Emitter and Detector Arrays for Multi-wavelength RoomTemperature Photonic Quantum Technologie
A7: 46083.48 | B7: Prof. Rajesh | C7: Kumar | D7: Academician/Researcher | E7: QMD/ IITR | F7: (+91) 9643028327 | G7: rajesh.kumar@ph.iitr.ac.in | H7: Associate Professor | J7: Roorkee | K7: =VLOOKUP(G7,Dataset!F:H,2,0) -> #N/A | L7: IIT Delhi | M7: =VLOOKUP(G7,Dataset!F:H,3,0) -> #N/A | N7: TG3:WaveguideandIntegratedQuantumPhotonics
A8: 46084.82 | B8: Natarajan | C8: Venkatachalam | D8: Govt | F8: (+91) 9943195161 | G8: natarajan@setsindia.net | H8: Scientist E | I8: SETS | J8: Chennai | K8: =VLOOKUP(G8,Dataset!F:H,2,0) -> IISc Bangalore | L8: IISc Bangalore | M8: =VLOOKUP(G8,Dataset!F:H,3,0) -> QuILA | N8: QuILA
A9: 46085.454 | B9: Siddharth | C9: Tallur | D9: Academician/Researcher | E9: Qmet/IIT Bombay | F9: (+91) 8291020571 | G9: stallur@ee.iitb.ac.in | H9: Associate Professor | J9: Mumbai | K9: =VLOOKUP(G9,Dataset!F:H,2,0) -> IIT Bombay | L9: IIT Bombay | M9: =VLOOKUP(G9,Dataset!F:H,3,0) -> TG 3 Kasturi Saha | N9: TG 3 Kasturi Saha
A10: 46085.454 | B10: Phani | C10: Peddibhotla | D10: Academician/Researcher | E10: Qmet | F10: (+91) 8978535980 | G10: phani@iiserb.ac.in | H10: Asst. Prof. | J10: Bhopal | K10: =VLOOKUP(G10,Dataset!F:H,2,0) -> IIT Bombay | L10: IIT Bombay | M10: =VLOOKUP(G10,Dataset!F:H,3,0) -> TG 2 Saikat Ghosh | N10: TG 2 Saikat Ghosh
A11: 46085.455 | B11: Tanmoy | C11: Basu | D11: Academician/Researcher | E11: Quantum Sensing/TCG CREST | F11: (+91) 9040227037 | G11: tanmoy.basu@tcgcrest.org | H11: Assistant Professor | J11: Kolkata | K11: =VLOOKUP(G11,Dataset!F:H,2,0) -> IIT Bombay | L11: IIT Bombay | M11: =VLOOKUP(G11,Dataset!F:H,3,0) -> TG 3 Kasturi Saha | N11: TG 3 Kasturi Saha
A12: 46085.469 | B12: Santanu | C12: Talukder | D12: Academician/Researcher | E12: QMet | F12: (+91) 9632716218 | G12: santanu@iiserb.ac.in | H12: Associate Professor | J12: Bhopal | K12: =VLOOKUP(G12,Dataset!F:H,2,0) -> IIT Bombay | L12: IIT Bombay | M12: =VLOOKUP(G12,Dataset!F:H,3,0) -> TG 3 Kasturi Saha | N12: TG 3 Kasturi Saha
A13: 46085.471 | B13: Ambarish | C13: Ghosh | D13: Academician/Researcher | E13: IISc | F13: (95350) 22265 | G13: ambarish@iisc.ac.in | H13: Professor | J13: Bangalore | K13: =VLOOKUP(G13,Dataset!F:H,2,0) -> IIT Bombay | L13: IIT Bombay | M13: =VLOOKUP(G13,Dataset!F:H,3,0) -> TG 3 Kasturi Saha | N13: TG 3 Kasturi Saha
A14: 46085.491 | B14: Venkata Jayasurya | C14: Yallapragada | D14: Academician/Researcher | E14: IIT Kanpur | F14: (+91) 9441885075 | G14: jayasurya@iitk.ac.in | H14: Assistant Professor | J14: Kanpur | K14: =VLOOKUP(G14,Dataset!F:H,2,0) -> IIT Bombay | L14: IIT Bombay | M14: =VLOOKUP(G14,Dataset!F:H,3,0) -> TG 1 Anand Jha | N14: TG 1 Anand Jha
A15: 46085.502 | B15: Kasturi | C15: Saha | D15: Academician/Researcher | E15: Qmet Tech Foundation | F15: (+91) 8291020871 | G15: pic@qmettech.com | H15: Project Director | J15: Mumbai | K15: =VLOOKUP(G15,Dataset!F:H,2,0) -> IIT Bombay | L15: IIT Bombay | M15: =VLOOKUP(G15,Dataset!F:H,3,0) -> TG 3 Kasturi Saha | N15: TG 3 Kasturi Saha
A16: 46085.536 | B16: Bimalendu | C16: Deb | D16: Academician/Researcher | E16: Quantum sesing | F16: (91) 8420265902 | G16: msbd@iacs.res.in | H16: Professor | J16: Kolkata | K16: =VLOOKUP(G16,Dataset!F:H,2,0) -> IIT Bombay | L16: IIT Bombay | M16: =VLOOKUP(G16,Dataset!F:H,3,0) -> TG 2 Saikat Ghosh | N16: TG 2 Saikat Ghosh
A17: 46085.623 | B17: Sanjib | C17: Dey | D17: Academician/Researcher | E17: Quantum Sensing and Metrology/IIT Bombay | F17: (+91) 8617433466 | G17: sanjibd@goa.bits-pilani.ac.in | H17: Assistant Professor | J17: Goa | K17: =VLOOKUP(G17,Dataset!F:H,2,0) -> IIT Bombay | L17: IIT Bombay | M17: =VLOOKUP(G17,Dataset!F:H,3,0) -> TG 2 Saikat Ghosh | N17: TG 2 Saikat Ghosh
A18: 46085.828 | B18: Debapriya | C18: Basu Roy | D18: Academician/Researcher | E18: IIT Kanpur | F18: (+91) 9432149757 | G18: dbroy@cse.iitk.ac.in | H18: Assistant Professor | J18: Kanpur | K18: =VLOOKUP(G18,Dataset!F:H,2,0) -> IIT Madras | L18: IIT Madras | M18: =VLOOKUP(G18,Dataset!F:H,3,0) -> PIPETA: Post Quantum Cryptography | N18: PIPETA: Post Quantum Cryptography
A19: 46085.828 | B19: Ashish | C19: Arora | D19: Academician/Researcher | E19: IISER Pune | F19: (91) 9892294386 | G19: ashish.arora@iiserpune.ac.in | H19: Assistant Professor | J19: Pune | K19: =VLOOKUP(G19,Dataset!F:H,2,0) -> IIT Delhi | L19: IIT Delhi | M19: =VLOOKUP(G19,Dataset!F:H,3,0) -> TG2: Wafer-scale Emitter and Detector Arrays for Multi-wavelength RoomTemperature Photonic Quantum Technologies | N19: TG2: Wafer-scale Emitter and Detector Arrays for Multi-wavelength RoomTemperature Photonic Quantum Technologies
A20: 46085.876 | B20: Saikat | C20: Ghosh | D20: Academician/Researcher | E20: IIT-Kanpur | F20: (+91) 8545043528 | G20: gsaikat@iitk.ac.in | H20: Associate Professor | J20: Kanpur | K20: =VLOOKUP(G20,Dataset!F:H,2,0) -> IIT Bombay | L20: IIT Bombay | M20: =VLOOKUP(G20,Dataset!F:H,3,0) -> TG 2 Saikat Ghosh | N20: TG 2 Saikat Ghosh
... A33: 46091.359 | B33: Varun | C33: Raghunathan | D33: Academician/Researcher | E33: Indian Institute of Science | F33: (+91) 8939619026 | G33: varunr@iisc.ac.in | H33: Associate professor | J33: Bangalore | K33: =VLOOKUP(G33,Dataset!F:H,2,0) -> IIT Madras | L33: IIT Madras | M33: =VLOOKUP(G33,Dataset!F:H,3,0) -> QuILA | N33: QuILA
A34: 46091.385 | B34: Deepak | C34: Gaur | D34: Govt | F34: (+91) 9873209432 | G34: dgaur@cdot.in | H34: Scientist-F | I34: Centre for Development of Telematics | J34: New Delhi | K34: =VLOOKUP(G34,Dataset!F:H,2,0) -> IIT Madras | L34: IIT Madras | M34: =VLOOKUP(G34,Dataset!F:H,3,0) -> PIPETA: Post Quantum Cryptography | N34: PIPETA: Post Quantum Cryptography
A35: 46091.39 | B35: Sarani | C35: Bhattacharya | D35: Academician/Researcher | E35: MPI: IIT Kharagpur, TG: PIPETA | F35: (+91) 9477063861 | G35: bhattacharya.sarani.iitkgp@gmail.com | H35: Assistant Professor | J35: Kharagpur | K35: =VLOOKUP(G35,Dataset!F:H,2,0) -> #N/A | L35: IIT Madras | M35: =VLOOKUP(G35,Dataset!F:H,3,0) -> #N/A | N35: PIPETA: Post Quantum Cryptography
A36: 46091.412 | B36: Rajalakshmi | C36: Gurumurthy | D36: Academician/Researcher | E36: Rajalakshmi Gurumurthy | F36: (+91) 9963071783 | G36: raji@tifrh.res.in | H36: Scientific Officer (F) | J36: Hyderabad | K36: =VLOOKUP(G36,Dataset!F:H,2,0) -> IIT Bombay | L36: IIT Bombay | M36: =VLOOKUP(G36,Dataset!F:H,3,0) -> TG 2 Saikat Ghosh | N36: TG 2 Saikat Ghosh
A37: 46091.416 | B37: Saurabh | C37: Lodha | D37: Academician/Researcher | E37: IIT Bombay | F37: (+91) 9819927460 | G37: saurabh.lodha@gmail.com | H37: Professor | J37: Mumbai | K37: =VLOOKUP(G37,Dataset!F:H,2,0) -> #N/A | L37: IIT Delhi | M37: =VLOOKUP(G37,Dataset!F:H,3,0) -> #N/A | N37: TG2: Wafer-scale Emitter and Detector Arrays for Multi-wavelength RoomTemperature Photonic Quantum Technologies
A38: 46091.417 | B38: Prabha | C38: Mandayam | D38: Academician/Researcher | E38: FQCI/IIT Madras | F38: (+91) 9445992785 | G38: prabhamd@physics.iitm.ac.in | H38: Professor | J38: Chennai | K38: =VLOOKUP(G38,Dataset!F:H,2,0) -> IISc Bangalore | L38: IISc Bangalore | M38: =VLOOKUP(G38,Dataset!F:H,3,0) -> TG 5 Quantum computers with Superconducting Qubits | N38: TG 5 Quantum computers with Superconducting Qubits
A39: 46091.444 | B39: Shailendra K. | C39: Varshney | D39: Academician/Researcher | E39: IIT Kharagpur (QMD Hub) | F39: (+91) 9732926003 | G39: skvarshney@ece.iitkgp.ac.in | H39: Professor | J39: Kharagpur | K39: =VLOOKUP(G39,Dataset!F:H,2,0) -> IIT Delhi | L39: IIT Delhi | M39: =VLOOKUP(G39,Dataset!F:H,3,0) -> TG3:WaveguideandIntegratedQuantumPhotonics | N39: TG3:WaveguideandIntegratedQuantumPhotonics
A40: 46091.447 | B40: Akshay | C40: Naik | D40: Academician/Researcher | E40: IISc | F40: (+91) 9611396194 | G40: anaik@iisc.ac.in | H40: Professor | J40: Bangalore | K40: =VLOOKUP(G40,Dataset!F:H,2,0) -> IIT Bombay | L40: IIT Bombay | M40: =VLOOKUP(G40,Dataset!F:H,3,0) -> TG 2 Saikat Ghosh | N40: TG 2 Saikat Ghosh
A41: 46091.454 | B41: Rahul | C41: Singh | D41: Academician/Researcher | E41: Indian Institute of Technology, Bombay | F41: (91) 9004059586 | G41: rahuls_ee@iitb.ac.in | H41: Assistant Professor | J41: Mumbai | K41: =VLOOKUP(G41,Dataset!F:H,2,0) -> IISc Bangalore | L41: IISc Bangalore | M41: =VLOOKUP(G41,Dataset!F:H,3,0) -> TG 4 Development of a 50-qubit quantum information processor with electron spins in silicon | N41: TG 4 Development of a 50-qubit quantum information processor with electron spins in silicon
A42: 46091.493 | B42: Prosenjit | C42: Sen | D42: Academician/Researcher | E42: IISc | F42: (+91) 7406890351 | G42: prosenjits@iisc.ac.in | H42: Professor | J42: Bangalore | K42: =VLOOKUP(G42,Dataset!F:H,2,0) -> IIT Bombay | L42: IIT Bombay | M42: =VLOOKUP(G42,Dataset!F:H,3,0) -> TG 2 Saikat Ghosh | N42: TG 2 Saikat Ghosh
A43: 46091.587 | B43: SAMARESH | C43: DAS | D43: Academician/Researcher | E43: IIT DELHI | F43: (91) 9899130814 | G43: samareshdas@care.iitd.ac.in | H43: Professor | J43: Delhi | K43: =VLOOKUP(G43,Dataset!F:H,2,0) -> #N/A | L43: IISc Banglore | M43: =VLOOKUP(G43,Dataset!F:H,3,0) -> #N/A | N43: TG 4 Development of a 50-qubit quantum information processor with electron spins in silicon
A44: 46091.66 | B44: Madhu | C44: Thalakulam | D44: Academician/Researcher | E44: FQCI/IISER Thiruvananthapuram | F44: (91) 9497785983 | G44: madhu@iisertvm.ac.in | H44: Associate Professor | J44: Thiruvananthapuram | K44: =VLOOKUP(G44,Dataset!F:H,2,0) -> IISc Bangalore | L44: =K44 -> IISc Bangalore | M44: =VLOOKUP(G44,Dataset!F:H,3,0) -> TG 4 Development of a 50-qubit quantum information processor with electron spins in silicon | N44: =M44 -> TG 4 Development of a 50-qubit quantum information processor with electron spins in silicon
A45: 46091.662 | B45: Senthil Kumar | C45: M | D45: Govt | F45: (+91) 9427048883 | G45: senthiliist@gmail.com | H45: LPI NQM | I45: SAC, ISRO | J45: Ahmedabad | K45: =VLOOKUP(G45,Dataset!F:H,2,0) -> #N/A | L45: IIT Madras | M45: =VLOOKUP(G45,Dataset!F:H,3,0) -> #N/A | N45: SBQKD - ISRO
A46: 46091.702 | B46: Dr. Avinash | C46: Lahgere | D46: Academician/Researcher | E46: IIT Kanpur | F46: (91) 9711611954 | G46: alahgere@iitk.ac.in | H46: Assistant Professor | J46: Kanpur | K46: =VLOOKUP(G46,Dataset!F:H,2,0) -> IISc Bangalore | L46: =K46 -> IISc Bangalore | M46: =VLOOKUP(G46,Dataset!F:H,3,0) -> TG 3 Design and Demonstration of a Highly Scalable Quantum Computer using Semiconducting Qubits | N46: =M46 -> TG 3 Design and Demonstration of a Highly Scalable Quantum Computer using Semiconducting Qubits
A47: 46091.769 | B47: Anil | C47: Shaji | D47: Academician/Researcher | E47: Quantum Computing Hub - TG4 - IISER TVM (Member Institute) | F47: (+91) 9446460011 | G47: shaji@iisertvm.ac.in | H47: Professor | J47: Thiruvananthapuram | K47: =VLOOKUP(G47,Dataset!F:H,2,0) -> #N/A | L47: IISc Banglore | M47: =VLOOKUP(G47,Dataset!F:H,3,0) -> #N/A | N47: TG 4 Development of a 50-qubit quantum information processor with electron spins in silicon
A48: 46091.787 | B48: Shankar Kumar | C48: Selvaraja | D48: Academician/Researcher | E48: Indian Institute of Science | F48: (91) 9481283513 | G48: shankarks@iisc.ac.in | H48: Professor | J48: Bangalore | K48: =VLOOKUP(G48,Dataset!F:H,2,0) -> IISc Bangalore | L48: =K48 -> IISc Bangalore | M48: =VLOOKUP(G48,Dataset!F:H,3,0) -> TG 1 Photonics quantum processor development | N48: =M48 -> TG 1 Photonics quantum processor development
A49: 46091.871 | B49: Abhisek | C49: Dixit | D49: Academician/Researcher | E49: Quantum Computing/IIT Delhi | F49: (+91) 8373905693 | G49: adixit@ee.iitd.ac.in | H49: Professor | J49: New Delhi | K49: =VLOOKUP(G49,Dataset!F:H,2,0) -> #N/A | L49: IISc Banglore | M49: =VLOOKUP(G49,Dataset!F:H,3,0) -> #N/A | N49: TG 3 Design and Demonstration of a Highly Scalable Quantum Computer using Semiconducting Qubits
A50: 46091.9 | B50: Parvendra | C50: Kumar | D50: Academician/Researcher | E50: IITM CDOT Samgnya Technologies Foundation/IIT Delhi | F50: (+91) 7505086612 | G50: parvendra@iitd.ac.in | H50: Assistant Professor | J50: New Delhi | K50: =VLOOKUP(G50,Dataset!F:H,2,0) -> #N/A | L50: IIT Madras | M50: =VLOOKUP(G50,Dataset!F:H,3,0) -> #N/A | N50: TAHQEECAT
A51: 46092.29 | B51: Saptarishi | C51: Chaudhuri | D51: Academician/Researcher | E51: FQCI / RRI | F51: (91) 7259899430 | G51: srishic@rri.res.in | H51: Professor | J51: Bengaluru | K51: =VLOOKUP(G51,Dataset!F:H,2,0) -> IISc Bangalore | L51: =K51 -> IISc Bangalore | M51: =VLOOKUP(G51,Dataset!F:H,3,0) -> TG 6 Quantum Computing with Neutral Atoms, Trapped Ions and Related Hybrid Systems | N51: =M51 -> TG 6 Quantum Computing with Neutral Atoms, Trapped Ions and Related Hybrid Systems
A52: 46092.366 | B52: Anand | C52: Jha | D52: Academician/Researcher | E52: IIT Kanpur | F52: (+91) 9621423993 | G52: akjha@iitk.ac.in | H52: Professor | J52: Kanpur | K52: =VLOOKUP(G52,Dataset!F:H,2,0) -> IIT Bombay | L52: =K52 -> IIT Bombay | M52: =VLOOKUP(G52,Dataset!F:H,3,0) -> TG 1 Anand Jha | N52: =M52 -> TG 1 Anand Jha
A53: 46092.448 | B53: Kolin | C53: Paul | D53: Academician/Researcher | E53: IIT Delhi | F53: (+91) 9891942310 | G53: kolin.paul@gmail.com | H53: Professor | J53: New Delhi | K53: =VLOOKUP(G53,Dataset!F:H,2,0) -> IISc Bangalore | L53: =K53 -> IISc Bangalore | M53: =VLOOKUP(G53,Dataset!F:H,3,0) -> TG 3 Design and Demonstration of a Highly Scalable Quantum Computer using Semiconducting Qubits | N53: =M53 -> TG 3 Design and Demonstration of a Highly Scalable Quantum Computer using Semiconducting Qubits
A54: 46092.471 | B54: Henry | C54: Sukumar | D54: Govt | F54: (+91) 9886660658 | G54: henrys@cdac.in | H54: Scientist F | I54: C-DAC | J54: Bengaluru | K54: =VLOOKUP(G54,Dataset!F:H,2,0) -> IISc Bangalore | L54: =K54 -> IISc Bangalore | M54: =VLOOKUP(G54,Dataset!F:H,3,0) -> TG 2 Programmable photonic quantum computing using qubits encoded in different degrees of freedom of a photon | N54: =M54 -> TG 2 Programmable photonic quantum computing using qubits encoded in different degrees of freedom of a photon
A55: 46092.622 | B55: Uditendu | C55: Mukhopadhyay | D55: Academician/Researcher | E55: Computing Hub | F55: (+91) 9163063487 | G55: uditendu@iitb.ac.in | H55: Assistant Professor (MPI in TG4) | J55: Mumbai | K55: =VLOOKUP(G55,Dataset!F:H,2,0) -> #N/A | L55: IISc Banglore | M55: =VLOOKUP(G55,Dataset!F:H,3,0) -> #N/A | N55: TG 4 Development of a 50-qubit quantum information processor with electron spins in silicon
A56: 46092.739 | B56: Sandeep Kumar | C56: Goyal | D56: Academician/Researcher | E56: Quantum Communication/ IISER Mohali | F56: (+91) 8572879340 | G56: skgoyal@iisermohali.ac.in | H56: Associate Professor | J56: Mohali | K56: =VLOOKUP(G56,Dataset!F:H,2,0) -> IIT Madras | L56: =K56 -> IIT Madras | M56: =VLOOKUP(G56,Dataset!F:H,3,0) -> QuePRAN | N56: =M56 -> QuePRAN
A57: 46093.461 | B57: Devarshi Mrinal | C57: Das | D57: Academician/Researcher | E57: FQCI T-Hub / IIT Ropar | F57: (+91) 7738221277 | G57: devarshi.das@iitrpr.ac.in | H57: Assistant Professor | J57: Rupnagar, Punjab | K57: =VLOOKUP(G57,Dataset!F:H,2,0) -> #N/A | L57: IISc Banglore | M57: =VLOOKUP(G57,Dataset!F:H,3,0) -> #N/A | N57: TG 3 Design and Demonstration of a Highly Scalable Quantum Computer using Semiconducting Qubits
A58: 46093.476 | B58: Vaibhav Pratap | C58: Singh | D58: Govt | F58: (91) 7829635748 | G58: svaibhav@cdac.in | H58: Scientist 'E' | I58: CDAC Bangalore | J58: Bengaluru | K58: =VLOOKUP(G58,Dataset!F:H,2,0) -> IISc Bangalore | L58: =K58 -> IISc Bangalore | M58: =VLOOKUP(G58,Dataset!F:H,3,0) -> TG 1 Photonics quantum processor development | N58: =M58 -> TG 1 Photonics quantum processor development
A59: 46093.544 | B59: Rajamani | C59: Vijayaraghavan | D59: Academician/Researcher | E59: FQCI, IISc Bengaluru | F59: (+91) 9967167467 | G59: r.vijay@tifr.res.in | H59: Associate Professor | J59: Mumbai | K59: =VLOOKUP(G59,Dataset!F:H,2,0) -> #N/A | L59: IISc Banglore | M59: =VLOOKUP(G59,Dataset!F:H,3,0) -> #N/A | N59: TG 5 Quantum computers with Superconducting Qubits
A60: 46093.659 | B60: Ravi | C60: Pant | D60: Academician/Researcher | E60: IISER Thiruvananthapuram | F60: (+91) 8136810732 | G60: rpant@iisertvm.ac.in | H60: Associate Professor | J60: Trivandrum | K60: =VLOOKUP(G60,Dataset!F:H,2,0) -> IISc Bangalore | L60: =K60 -> IISc Bangalore | M60: =VLOOKUP(G60,Dataset!F:H,3,0) -> TG 1 Photonics quantum processor development | N60: =M60 -> TG 1 Photonics quantum processor development
A61: 46093.699 | B61: Anirban | C61: Mitra | D61: Academician/Researcher | E61: TG3/I.I.T, Roorkee | F61: (91) 8927280951 | G61: anirban.mitra@ph.iitr.ac.in | H61: Professor | J61: Roorkee | K61: =VLOOKUP(G61,Dataset!F:H,2,0) -> IIT Delhi | L61: =K61 -> IIT Delhi | M61: =VLOOKUP(G61,Dataset!F:H,3,0) -> TG3:WaveguideandIntegratedQuantumPhotonics | N61: =M61 -> TG3:WaveguideandIntegratedQuantumPhotonics
A62: 46093.702 | B62: Dr Raghavan | C62: EASWARAN | D62: Academician/Researcher | E62: IITM C-DOT | F62: (+91) 7542957634 | G62: raghavanke@iitp.ac.in | H62: Associate Professor IIT Patna | J62: Patna | K62: =VLOOKUP(G62,Dataset!F:H,2,0) -> IIT Madras | L62: =K62 -> IIT Madras | M62: =VLOOKUP(G62,Dataset!F:H,3,0) -> QuePRAN | N62: =M62 -> QuePRAN
A63: 46094.599 | B63: Praveen | C63: Kumar | D63: Academician/Researcher | E63: IIT Delhi (TG 2) | F63: (+91) 6290260756 | G63: praiitr@gmail.com | H63: Associate Professor | J63: MOHALI | K63: =VLOOKUP(G63,Dataset!F:H,2,0) -> #N/A | L63: IIT Delhi | M63: =VLOOKUP(G63,Dataset!F:H,3,0) -> #N/A | N63: TG2: Wafer-scale Emitter and Detector Arrays for Multi-wavelength RoomTemperature Photonic Quantum Technologies
A64: 46094.736 | B64: Amitangshu | C64: Pal | D64: Academician/Researcher | E64: IIT Kanpur | F64: (+91) 7384523610 | G64: amitangshu@cse.iitk.ac.in | H64: Assistant Professor | J64: Kanpur | K64: =VLOOKUP(G64,Dataset!F:H,2,0) -> IIT Bombay | L64: =K64 -> IIT Bombay | M64: =VLOOKUP(G64,Dataset!F:H,3,0) -> TG 2 Saikat Ghosh | N64: =M64 -> TG 2 Saikat Ghosh
A65: 46079.797 | B65: Arijit | C65: Sharma | D65: Academician/Researcher | E65: IIT TIRUPATI | F65: (+91) 9810875287 | G65: arijit@iittp.ac.in | H65: ASSOCIATE PROFESSOR | J65: TIRUPATI | K65: =VLOOKUP(G65,Dataset!F:H,2,0) -> IIT Madras | L65: =K65 -> IIT Madras | M65: =VLOOKUP(G65,Dataset!F:H,3,0) -> QuePRAN | N65: =M65 -> QuePRAN
A66: 46095.553 | B66: Debdeep | C66: Mukhopadhyay | D66: Academician/Researcher | E66: IIT Kharagpur | F66: (+91) 7478792350 | G66: debdeep.mukhopadhyay@gmail.com | H66: Asso Dean R&D and Professor, CSE | J66: Kharagpur | K66: =VLOOKUP(G66,Dataset!F:H,2,0) -> #N/A | L66: IIT Madras | M66: =VLOOKUP(G66,Dataset!F:H,3,0) -> #N/A | N66: PIPETA: Post Quantum Cryptography
A67: 46095.775 | B67: Pratap | C67: Raychaudhuri | D67: Academician/Researcher | E67: TIFR mumbai | F67: (+91) 9869303774 | G67: pratap@tifr.res.in | H67: Sr. Professor | J67: Mumbai | K67: =VLOOKUP(G67,Dataset!F:H,2,0) -> #N/A | L67: IIT Bombay | M67: =VLOOKUP(G67,Dataset!F:H,3,0) -> #N/A | N67: TG 3 Kasturi Saha
A68: 46096.019 | B68: D S | C68: Rawal | D68: Govt | F68: (91) 9818013936 | G68: dsrawal15@gmail.com | H68: Outstanding Scientist | I68: SSPL DRDO | J68: Delhi | K68: =VLOOKUP(G68,Dataset!F:H,2,0) -> #N/A | L68: IIT Delhi | M68: =VLOOKUP(G68,Dataset!F:H,3,0) -> #N/A | N68: TG1: Development ofOn-DemandSinglePhotonEmitters, SinglePhotonAvalancheDetectors,High-FrequencyDevices andInP-BasedEpitaxialSemiconductors
A69: 46096.501 | B69: Kanhaiya | C69: Pandey | D69: Academician/Researcher | E69: Quantum Computing Hub, IITG | F69: (+91) 8761942326 | G69: kanhaiyapandey@iitg.ac.in | H69: Associate Professor | J69: Guwahati | K69: =VLOOKUP(G69,Dataset!F:H,2,0) -> IISc Bangalore | L69: =K69 -> IISc Bangalore | M69: =VLOOKUP(G69,Dataset!F:H,3,0) -> TG 6 Quantum Computing with Neutral Atoms, Trapped Ions and Related Hybrid Systems | N69: =M69 -> TG 6 Quantum Computing with Neutral Atoms, Trapped Ions and Related Hybrid Systems
A70: 46096.668 | B70: Jaydeep Kumar | C70: Basu | D70: Academician/Researcher | E70: Quantum Computing/ IISc | F70: (+91) 9886324567 | G70: basu@iisc.ac.in | H70: Professor, MPI | J70: Bangalore | K70: =VLOOKUP(G70,Dataset!F:H,2,0) -> IISc Bangalore | L70: =K70 -> IISc Bangalore | M70: =VLOOKUP(G70,Dataset!F:H,3,0) -> TG 1 Photonics quantum processor development | N70: =M70 -> TG 1 Photonics quantum processor development
A71: 46096.836 | B71: C M | C71: Chandrashekar | D71: Academician/Researcher | E71: Indian Institute of Science | F71: (+91) 9566000369 | G71: chandracm@iisc.ac.in | H71: Professor | J71: Bengaluru | K71: =VLOOKUP(G71,Dataset!F:H,2,0) -> IISc Bangalore | L71: =K71 -> IISc Bangalore | M71: =VLOOKUP(G71,Dataset!F:H,3,0) -> TG 2 Programmable photonic quantum computing using qubits encoded in different degrees of freedom of a photon | N71: =M71 -> TG 2 Programmable photonic quantum computing using qubits encoded in different degrees of freedom of a photon
A72: 46097.505 | B72: Apoorva | C72: Patel | D72: Academician/Researcher | F72: (+91) 9741294802 | G72: adpatel@iisc.ac.in | H72: Professor | J72: Bengaluru | K72: =VLOOKUP(G72,Dataset!F:H,2,0) -> IISc Bangalore | M72: =VLOOKUP(G72,Dataset!F:H,3,0) -> TG 1 Photonics quantum processor development
A73: 46097.528 | B73: Akshay | C73: Singh | D73: Academician/Researcher | F73: (+91) 9870127569 | G73: aksy@iisc.ac.in | H73: Assistant professor | J73: bengaluru | K73: =VLOOKUP(G73,Dataset!F:H,2,0) -> IISc Bangalore | L73: =K73 -> IISc Bangalore | M73: =VLOOKUP(G73,Dataset!F:H,3,0) -> TG 1 Photonics quantum processor development | N73: =M73 -> TG 1 Photonics quantum processor development
A74: 46097.605 | B74: Neeraj | C74: Goel | D74: Academician/Researcher | F74: (+91) 9818562842 | G74: neeraj@iitrpr.ac.in | H74: Associate Professor | J74: Ropar | K74: =VLOOKUP(G74,Dataset!F:H,2,0) -> #N/A | L74: IISc Bangalore | M74: =VLOOKUP(G74,Dataset!F:H,3,0) -> #N/A | N74: TG 3 Design and Demonstration of a Highly Scalable Quantum Computer using Semiconducting Qubits
A75: 46097.749 | B75: Ashok | C75: Mohapatra | D75: Academician/Researcher | F75: (+91) 8249520154 | G75: a.mohapatra@niser.ac.in | H75: Assoc. Prof. | J75: Bhubaneswar | K75: =VLOOKUP(G75,Dataset!F:H,2,0) -> IISc Bangalore | L75: =K75 -> IISc Bangalore | M75: =VLOOKUP(G75,Dataset!F:H,3,0) -> TG 6 Quantum Computing with Neutral Atoms, Trapped Ions and Related Hybrid Systems | N75: =M75 -> TG 6 Quantum Computing with Neutral Atoms, Trapped Ions and Related Hybrid Systems
A76: 46098.391 | B76: Awanish | C76: Pandey | D76: Academician/Researcher | F76: (+91) 8762262341 | G76: opcawanish@iitd.ac.in | H76: Assistant Professor | J76: New Delhi | K76: =VLOOKUP(G76,Dataset!F:H,2,0) -> #N/A | L76: IISc Bangalore | M76: =VLOOKUP(G76,Dataset!F:H,3,0) -> #N/A | N76: TG 1 Photonics quantum processor development
A77: 46098.423 | B77: Mukesh | C77: Kumar | D77: Academician/Researcher | E77: Foundation for QC Innovation IISc Bangalore | F77: (+91) 8437166802 | G77: mukesh.kr@iiti.ac.in | H77: Professor | J77: Indore | K77: =VLOOKUP(G77,Dataset!F:H,2,0) -> IISc Bangalore | L77: =K77 -> IISc Bangalore | M77: =VLOOKUP(G77,Dataset!F:H,3,0) -> TG 1 Photonics quantum processor development | N77: =M77 -> TG 1 Photonics quantum processor development
A78: 46098.466 | B78: Anirban | C78: Pathak | D78: Academician/Researcher | E78: Foundation for QC Innovation IISc Bangalore | F78: (+91) 9717066494 | G78: anirban.pathak@gmail.com | H78: Professor | J78: Noida | K78: =VLOOKUP(G78,Dataset!F:H,2,0) -> #N/A | L78: IISc Bangalore | M78: =VLOOKUP(G78,Dataset!F:H,3,0) -> #N/A | N78: TG 2 Programmable photonic quantum computing using qubits encoded in different degrees of freedom of a photon
A79: 46098.467 | B79: Prof. Rajendra | C79: Singh | D79: Academician/Researcher | E79: QMD Foundation at IIT Delhi | F79: (91) 95827 74442 | G79: rsingh@physics.iitd.ac.in | H79: Project Director | J79: New Delhi | K79: =VLOOKUP(G79,Dataset!F:H,2,0) -> #N/A | L79: IIT Delhi | M79: =VLOOKUP(G79,Dataset!F:H,3,0) -> #N/A | N79: TG 1 Development of on-demand single photon emitters, single photon avalanche detectors, high-frequency devices and InP based Epitaxial semiconductors
A80: 46098.519 | B80: Vishvendra Singh | C80: Poonia | D80: Academician/Researcher | E80: Foundation for QC Innovation IISc Bangalore | F80: (+91) 8097426535 | G80: vishvendra@ece.iitr.ac.in | H80: Associate Professor | J80: Roorkee | K80: =VLOOKUP(G80,Dataset!F:H,2,0) -> IISc Bangalore | L80: =K80 -> IISc Bangalore | M80: =VLOOKUP(G80,Dataset!F:H,3,0) -> TG 3 Design and Demonstration of a Highly Scalable Quantum Computer using Semiconducting Qubits | N80: =M80 -> TG 3 Design and Demonstration of a Highly Scalable Quantum Computer using Semiconducting Qubits
A81: 46098.531 | B81: Ajay | C81: Wasan | D81: Academician/Researcher | E81: Foundation for QC Innovation IISc Bangalore | F81: (097205) 43906 | G81: awasan@ph.iitr.ac.in | H81: Professor | J81: Roorkee | K81: =VLOOKUP(G81,Dataset!F:H,2,0) -> IISc Bangalore | L81: =K81 -> IISc Bangalore | M81: =VLOOKUP(G81,Dataset!F:H,3,0) -> TG 6 Quantum Computing with Neutral Atoms, Trapped Ions and Related Hybrid Systems | N81: =M81 -> TG 6 Quantum Computing with Neutral Atoms, Trapped Ions and Related Hybrid Systems
A82: 46098.565 | B82: Kausik | C82: Majumdar | D82: Academician/Researcher | E82: Foundation for QC Innovation IISc Bangalore | F82: (+91) 7022665421 | G82: kausikm@iisc.ac.in | H82: Associate Professor | J82: Bangalore | K82: =VLOOKUP(G82,Dataset!F:H,2,0) -> IISc Bangalore | L82: =K82 -> IISc Bangalore | M82: =VLOOKUP(G82,Dataset!F:H,3,0) -> TG 1 Photonics quantum processor development | N82: =M82 -> TG 1 Photonics quantum processor development
A83: 46098.597 | B83: Rakesh | C83: Palani | D83: Academician/Researcher | E83: Foundation for QC Innovation IISc Bangalore | F83: (+91) 9606310202 | G83: rakesh@ee.iitd.ac.in | H83: Associate Professor | J83: Delhi | K83: =VLOOKUP(G83,Dataset!F:H,2,0) -> #N/A | L83: IISc Bangalore | M83: =VLOOKUP(G83,Dataset!F:H,3,0) -> #N/A | N83: TG 3 Design and Demonstration of a Highly Scalable Quantum Computer using Semiconducting Qubits
A84: 46098.658 | B84: Darshak | C84: Bhatt | D84: Academician/Researcher | E84: Foundation for QC Innovation IISc Bangalore | F84: (+91) 8879179443 | G84: darshak.bhatt@ece.iitr.ac.in | H84: Associate Professor | J84: Roorkee | K84: =VLOOKUP(G84,Dataset!F:H,2,0) -> IISc Bangalore | L84: IISc Bangalore | M84: =VLOOKUP(G84,Dataset!F:H,3,0) -> TG 3 Design and Demonstration of a Highly Scalable Quantum Computer using Semiconducting Qubits | N84: TG 3 Design and Demonstration of a Highly Scalable Quantum Computer using Semiconducting Qubits
A85: 46098.705 | B85: Sai | C85: Vinjanampathy | D85: Academician/Researcher | E85: Qmet Tech Foundation at IIT Bombay | F85: (022) 25767592 | G85: sai.vinjanampathy@iitb.ac.in | H85: Associate Professor | J85: Mumbai | K85: =VLOOKUP(G85,Dataset!F:H,2,0) -> #N/A | L85: IISc Bangalore | IIT Bombay | M85: =VLOOKUP(G85,Dataset!F:H,3,0) -> #N/A | N85: TG 5 Quantum computers with Superconducting Qubits | TG 2 Saikat Ghosh
A86: 46098.789 | B86: Vibhor | C86: Singh | D86: Academician/Researcher | E86: Foundation for QC Innovation IISc Bangalore | F86: (+91) 9108157495 | G86: v.singh@iisc.ac.in | H86: Associate Professor | J86: Bangalore | K86: =VLOOKUP(G86,Dataset!F:H,2,0) -> IISc Bangalore | L86: =K86 -> IISc Bangalore | M86: =VLOOKUP(G86,Dataset!F:H,3,0) -> TG 5 Quantum computers with Superconducting Qubits | N86: =M86 -> TG 5 Quantum computers with Superconducting Qubits
A87: 46098.792 | B87: Chetan Singh | C87: Thakur | D87: Academician/Researcher | E87: Foundation for QC Innovation IISc Bangalore | F87: (+91) 9731680833 | G87: csthakur@iisc.ac.in | H87: Professor | J87: Bengaluru | K87: =VLOOKUP(G87,Dataset!F:H,2,0) -> IISc Bangalore | L87: =K87 -> IISc Bangalore | M87: =VLOOKUP(G87,Dataset!F:H,3,0) -> TG 5 Quantum computers with Superconducting Qubits | N87: =M87 -> TG 5 Quantum computers with Superconducting Qubits
A88: 46098.866 | B88: UTPAL | C88: ROY | D88: Academician/Researcher | E88: Foundation for QC Innovation IISc Bangalore | F88: (+91) 8102156405 | G88: uroy@iitp.ac.in | H88: Associate Professor | J88: Patna | K88: =VLOOKUP(G88,Dataset!F:H,2,0) -> IISc Bangalore | L88: =K88 -> IISc Bangalore | M88: =VLOOKUP(G88,Dataset!F:H,3,0) -> TG 6 Quantum Computing with Neutral Atoms, Trapped Ions and Related Hybrid Systems | N88: =M88 -> TG 6 Quantum Computing with Neutral Atoms, Trapped Ions and Related Hybrid Systems
A89: 46098.972 | B89: Baladitya | C89: Suri | D89: Academician/Researcher | E89: Foundation for QC Innovation IISc Bangalore | F89: (+91) 9481186223 | G89: surib@iisc.ac.in | H89: Associate Professor | J89: Bengaluru | K89: =VLOOKUP(G89,Dataset!F:H,2,0) -> IISc Bangalore | L89: =K89 -> IISc Bangalore | M89: =VLOOKUP(G89,Dataset!F:H,3,0) -> TG 5 Quantum computers with Superconducting Qubits | N89: =M89 -> TG 5 Quantum computers with Superconducting Qubits
A90: 46099.318 | B90: Rejish Nath | C90: Gopinathan Rejani | D90: Academician/Researcher | E90: Foundation for QC Innovation IISc Bangalore | F90: (020) 25908165 | G90: rejish@iiserpune.ac.in | H90: Professor | J90: Pune | K90: =VLOOKUP(G90,Dataset!F:H,2,0) -> #N/A | L90: IISc Bangalore | M90: =VLOOKUP(G90,Dataset!F:H,3,0) -> #N/A | N90: TG 6 Quantum Computing with Neutral Atoms, Trapped Ions and Related Hybrid Systems
A91: 46099.414 | B91: Kedar | C91: Khare | D91: Academician/Researcher | E91: Qmet Tech Foundation at IIT Bombay | F91: (91) 9868278691 | G91: kedark@opc.iitd.ac.in | H91: Professor | J91: New Delhi | K91: =VLOOKUP(G91,Dataset!F:H,2,0) -> IIT Bombay | L91: IIT Bombay | M91: =VLOOKUP(G91,Dataset!F:H,3,0) -> TG 1 Anand Jha | N91: =M91 -> TG 1 Anand Jha
A92: 46105.382 | B92: Saravana | C92: Kumar | D92: Academician/Researcher | F92: (+91) 6369385349 | G92: saravana.kumar@ece.iitr.ac.in | H92: Assistant Professor | I92: Foundation for QC Innovation IISc Bangalore | J92: Delhi | K92: =VLOOKUP(G92,Dataset!F:H,2,0) -> IISc Bangalore | L92: IISc Bangalore
A93: 46105.641 | B93: Suraj | C93: Mandal | D93: Student | F93: (+91) 8617844701 | G93: surajm22@iitk.ac.in | H93: PhD Scholar | I93: INDIAN INSTITUTE OF TECHNOLOGY KANPUR | J93: KANPUR | K93: =VLOOKUP(G93,Dataset!F:H,2,0) -> #N/A | L93: IITM CDOT Samgnya Technologies Foundation at IIT Madras | O93: Debapriya Das
A94: 46105.747 | B94: Anirudh | C94: Jaiswal | D94: Student | F94: (+91) 7439215216 | G94: anirudh_202200138@smit.smu.edu.in | H94: Project Intern | I94: Indian Institute of Technology Bhilai (IITBH) | J94: Chattisgarh, Durg | K94: =VLOOKUP(G94,Dataset!F:H,2,0) -> #N/A | L94: IITM CDOT Samgnya Technologies Foundation at IIT Madras | O94: Dhiman Saha
A95: 46105.923 | B95: Anshuman | C95: Kumar | D95: Academician/Researcher | F95: (099587) 13346 | G95: anshuman.kumar@iitb.ac.in | H95: Associate Professor | J95: Mumbai | K95: =VLOOKUP(G95,Dataset!F:H,2,0) -> #N/A | L95: QMD Foundation | N95: TG2: Wafer-scale Emitter and Detector Arrays for Multi-wavelength RoomTemperature Photonic Quantum Technologie
A96: 46105.964 | B96: Sai Tarun | C96: Baratam | D96: Student | F96: (+91) 9560241708 | G96: saitarun.baratam25@kgpian.iitkgp.ac.in | H96: MS student at Computer science and engineering department | I96: IIT Kharagpur | J96: Kharagpur, Paschim Medinipur | K96: =VLOOKUP(G96,Dataset!F:H,2,0) -> #N/A | L96: IITM CDOT Samgnya Technologies Foundation at IIT Madras | O96: Debdeep Mukopadhyay
A97: 46106.719 | B97: Amrita | C97: Bhattacharya | D97: Academician/Researcher | F97: (091) 9930557620 | G97: b.amrita10@gmail.com | H97: Associate Professor | J97: Mumbai | K97: =VLOOKUP(G97,Dataset!F:H,2,0) -> #N/A | L97: QMD Foundation | N97: TG2: Wafer-scale Emitter and Detector Arrays for Multi-wavelength RoomTemperature Photonic Quantum Technologie
A98: 46106.723 | B98: Swaroop | C98: Ganguly | D98: Academician/Researcher | F98: (+91) 9867759249 | G98: swaroop.ganguly@iitb.ac.in | H98: Professor | J98: Mumbai | K98: =VLOOKUP(G98,Dataset!F:H,2,0) -> #N/A | L98: QMD Foundation | N98: TG 1 Development ofOn-DemandSinglePhotonEmitters, SinglePhotonAvalancheDetectors,High-FrequencyDevices andInP-BasedEpitaxialSemiconductors
A99: 46106.724 | B99: Dibyajyoti | C99: Ghosh | D99: Academician/Researcher | F99: (+91) 9289013008 | G99: dibyajyoti@iitd.ac.in | H99: Assistant Professor | J99: New Delhi | K99: =VLOOKUP(G99,Dataset!F:H,2,0) -> #N/A | L99: QMD Foundation | N99: TG 1 Development ofOn-DemandSinglePhotonEmitters, SinglePhotonAvalancheDetectors,High-FrequencyDevices andInP-BasedEpitaxialSemiconductors
A100: 46106.73 | B100: Maniraj | C100: Mahalingam | D100: Academician/Researcher | F100: (+91) 9039493225 | G100: maniraj@iitb.ac.in | H100: Professor | J100: Mumbai | K100: =VLOOKUP(G100,Dataset!F:H,2,0) -> IIT Delhi | L100: QMD Foundation
A101: 46106.74 | B101: Rajaraman | C101: Gopalan | D101: Academician/Researcher | F101: (+91) 9833607183 | G101: rajaraman@chem.iitb.ac.in | H101: Professor | J101: Mumbai | K101: =VLOOKUP(G101,Dataset!F:H,2,0) -> IIT Delhi | L101: QMD Foundation
A102: 46106.744 | B102: Karun | C102: Rawat | D102: Academician/Researcher | F102: (+91) 8585992445 | G102: karun.rawat@ece.iitr.ac.in | H102: Professor | J102: Roorkee | K102: =VLOOKUP(G102,Dataset!F:H,2,0) -> IIT Delhi | L102: QMD Foundation
A103: 46107.74 | B103: Santanu | C103: Manna | D103: Academician/Researcher | F103: (+91) 9775577930 | G103: mannasan@ee.iitd.ac.in | H103: Assistant Professor | J103: New Delhi | K103: =VLOOKUP(G103,Dataset!F:H,2,0) -> IIT Delhi | L103: QMD Foundation
A104: 46107.924 | B104: Siddhartha | C104: Chowdhury | D104: Student | F104: (+91) 9038043198 | G104: siddhartha.chowdhury92@gmail.com | H104: PhD Student | I104: Indian Institute of Technology Kharagpur | J104: Kharagpur | K104: =VLOOKUP(G104,Dataset!F:H,2,0) -> #N/A | L104: IITM CDOT Samgnya Technologies Foundation at IIT Madras | O104: Debdeep Mukopadhyay
A105: 46108.559 | B105: Rohit | C105: Chaurasiya | D105: Academician/Researcher | F105: (+91) 9049582034 | G105: rohit.chaurasiya@iitjammu.ac.in | H105: Assistant Professor | J105: Jammu | K105: IITM CDOT Samgnya Technologies Foundation at IIT Madras
A106: 46108.626 | B106: Sudipta | C106: Dubey | D106: Academician/Researcher | F106: (+91) 8604933508 | G106: sudiptad@iitk.ac.in | H106: Assistant Professor | J106: Kanpur | K106: QMD Foundation at IIT Delhi
A107: 46080.48 | B107: Gayathri | C107: Raman | D107: Academician/Researcher | E107: IIT Bombay | F107: (+91) 8095096873 | G107: g3raman@iitb.ac.in | H107: Program Manager | J107: Mumbai | K107: =VLOOKUP(G107,Dataset!F:H,2,0) -> #N/A | L107: IIT Delhi | M107: =VLOOKUP(G107,Dataset!F:H,3,0) -> #N/A
A108: 46079.797 | B108: Ravindra | C108: Barlingay | D108: Industry | F108: (+91) 9820776114 | G108: ceo@samgnya.in | H108: CEO | I108: IITM CDOT Samgnya Technologies Foundation | J108: Chennai | K108: =VLOOKUP(G108,Dataset!F:H,2,0) -> #N/A | L108: IIT Madras | M108: =VLOOKUP(G108,Dataset!F:H,3,0) -> #N/A | N108: CEO
A109: 46079.807 | B109: Kiran | C109: Shesh | D109: Industry | F109: (+91) 9820007330 | G109: ceo@qmettech.com | H109: CEO | I109: Qmet Tech Foundation | J109: Mumbai | K109: =VLOOKUP(G109,Dataset!F:H,2,0) -> #N/A | L109: IIT Bombay | M109: =VLOOKUP(G109,Dataset!F:H,3,0) -> #N/A | N109: CEO
A110: 46080.391 | B110: Dr. Venkateswaran | C110: PS | D110: Industry | F110: (+91) 7895734999 | G110: venkatps@qcinnovation.co.in | H110: Chief Operating Officer (COO) | I110: FQCI, DST-NQM, IISC | J110: Bengaluru | K110: =VLOOKUP(G110,Dataset!F:H,2,0) -> #N/A | L110: IISc Bangalore | M110: =VLOOKUP(G110,Dataset!F:H,3,0) -> #N/A | N110: COO
A111: 46080.394 | B111: Kunj | C111: Tandon | D111: Govt | F111: (+91) 9731562513 | G111: kunjtandon@quantech.org.in | H111: CEO | I111: I-Hub Quantum Technology Foundation | J111: Pune | K111: =VLOOKUP(G111,Dataset!F:H,2,0) -> #N/A | L111: I-Hub Quantum Technology Foundation | M111: =VLOOKUP(G111,Dataset!F:H,3,0) -> #N/A | N111: COO
A112: 46084.518 | B112: Aditya SG | C112: Vyas | D112: Academician/Researcher | E112: QMD Foundation | F112: (+91) 9214094775 | G112: ceo@qmdhub.co.in | H112: CEO | J112: Delhi | K112: =VLOOKUP(G112,Dataset!F:H,2,0) -> #N/A | L112: IIT Delhi | M112: =VLOOKUP(G112,Dataset!F:H,3,0) -> #N/A | N112: CEO
...

Sheet Registrations (2)
A1: Submission Date | B1: Name - First Name | C1: Name - Last Name | D1: Category | E1: Name of the Hub/Institution | F1: Contact Number | G1: E-mail | H1: Designation | I1: Your Company/Institution | J1: City/Town | K1: Hub | L1: Corrected Hub values | M1: TG | N1: Correct TG Names | P1: PI Name
A2: 46079.852 | B2: Ankur | C2: Raina | D2: Academician/Researcher | E2: IISER BHOPAL | F2: (+91) 9900495182 | G2: ankur@iiserb.ac.in | H2: Assistant Professor | J2: Bhopal | K2: =VLOOKUP(G2,Dataset!F:H,2,0) -> IIT Madras | L2: IIT Madras | M2: =VLOOKUP(G2,Dataset!F:H,3,0) -> TAHQEECAT
A3: 46079.9 | B3: Neel Kanth | C3: Kundu | D3: Academician/Researcher | E3: Quantum Communications | F3: (+91) 9891901100 | G3: neelkanth@iitd.ac.in | H3: Assistant Professor | J3: New Delhi | K3: =VLOOKUP(G3,Dataset!F:H,2,0) -> IIT Madras | L3: IIT Madras | M3: =VLOOKUP(G3,Dataset!F:H,3,0) -> TAHQEECAT
A4: 46079.905 | B4: Veeresh Vidyadhar | C4: Deshpande | D4: Academician/Researcher | E4: Indian Institute of Technology Bombay | F4: (91) 9108878742 | G4: veeresh@gmail.com | H4: Associate Professor | J4: Mumbai | K4: =VLOOKUP(G4,Dataset!F:H,2,0) -> #N/A | L4: IIT Bombay|IISc Banglore | M4: =VLOOKUP(G4,Dataset!F:H,3,0) -> #N/A | N4: TG 1 Kasturi Saha | TG 5 Quantum Computers with superconducting qubits
A5: 46080.655 | B5: Ravikiran | C5: Yeleswarapu | D5: Academician/Researcher | E5: BITS-Pilani Hyderabad, HUB: Quantum Computing HUB,IISC | F5: (+91) 8008547840 | G5: ravikiran.y@hyderabad.bits-pilani.ac.in | H5: Asst Professor | J5: Hyderabad | K5: =VLOOKUP(G5,Dataset!F:H,2,0) -> IISc Bangalore | L5: IISc Bangalore | M5: =VLOOKUP(G5,Dataset!F:H,3,0) -> TG 3 Design and Demonstration of a Highly Scalable Quantum Computer using Semiconducting Qubits | N5: TG 3 Design and Demonstration of a Highly Scalable Quantum Computer using Semiconducting Qubits
A6: 46082.977 | B6: Prasana | C6: Sahoo | D6: Academician/Researcher | E6: QMD/IIT Delhi Hub | F6: (+91) 7894525638 | G6: prasanasahoo@gmail.com | H6: Assistant Professor | J6: Kharagpur | K6: =VLOOKUP(G6,Dataset!F:H,2,0) -> #N/A | L6: IIT Delhi | M6: =VLOOKUP(G6,Dataset!F:H,3,0) -> #N/A | N6: TG2: Wafer-scale Emitter and Detector Arrays for Multi-wavelength RoomTemperature Photonic Quantum Technologie
A7: 46083.48 | B7: Prof. Rajesh | C7: Kumar | D7: Academician/Researcher | E7: QMD/ IITR | F7: (+91) 9643028327 | G7: rajesh.kumar@ph.iitr.ac.in | H7: Associate Professor | J7: Roorkee | K7: =VLOOKUP(G7,Dataset!F:H,2,0) -> #N/A | L7: IIT Delhi | M7: =VLOOKUP(G7,Dataset!F:H,3,0) -> #N/A | N7: TG3:WaveguideandIntegratedQuantumPhotonics
A8: 46084.82 | B8: Natarajan | C8: Venkatachalam | D8: Govt | F8: (+91) 9943195161 | G8: natarajan@setsindia.net | H8: Scientist E | I8: SETS | J8: Chennai | K8: =VLOOKUP(G8,Dataset!F:H,2,0) -> IISc Bangalore | L8: IISc Bangalore | M8: =VLOOKUP(G8,Dataset!F:H,3,0) -> QuILA | N8: QuILA
A9: 46085.454 | B9: Siddharth | C9: Tallur | D9: Academician/Researcher | E9: Qmet/IIT Bombay | F9: (+91) 8291020571 | G9: stallur@ee.iitb.ac.in | H9: Associate Professor | J9: Mumbai | K9: =VLOOKUP(G9,Dataset!F:H,2,0) -> IIT Bombay | L9: IIT Bombay | M9: =VLOOKUP(G9,Dataset!F:H,3,0) -> TG 3 Kasturi Saha | N9: TG 3 Kasturi Saha
A10: 46085.454 | B10: Phani | C10: Peddibhotla | D10: Academician/Researcher | E10: Qmet | F10: (+91) 8978535980 | G10: phani@iiserb.ac.in | H10: Asst. Prof. | J10: Bhopal | K10: =VLOOKUP(G10,Dataset!F:H,2,0) -> IIT Bombay | L10: IIT Bombay | M10: =VLOOKUP(G10,Dataset!F:H,3,0) -> TG 2 Saikat Ghosh | N10: TG 2 Saikat Ghosh
A11: 46085.455 | B11: Tanmoy | C11: Basu | D11: Academician/Researcher | E11: Quantum Sensing/TCG CREST | F11: (+91) 9040227037 | G11: tanmoy.basu@tcgcrest.org | H11: Assistant Professor | J11: Kolkata | K11: =VLOOKUP(G11,Dataset!F:H,2,0) -> IIT Bombay | L11: IIT Bombay | M11: =VLOOKUP(G11,Dataset!F:H,3,0) -> TG 3 Kasturi Saha | N11: TG 3 Kasturi Saha
A12: 46085.469 | B12: Santanu | C12: Talukder | D12: Academician/Researcher | E12: QMet | F12: (+91) 9632716218 | G12: santanu@iiserb.ac.in | H12: Associate Professor | J12: Bhopal | K12: =VLOOKUP(G12,Dataset!F:H,2,0) -> IIT Bombay | L12: IIT Bombay | M12: =VLOOKUP(G12,Dataset!F:H,3,0) -> TG 3 Kasturi Saha | N12: TG 3 Kasturi Saha
A13: 46085.471 | B13: Ambarish | C13: Ghosh | D13: Academician/Researcher | E13: IISc | F13: (95350) 22265 | G13: ambarish@iisc.ac.in | H13: Professor | J13: Bangalore | K13: =VLOOKUP(G13,Dataset!F:H,2,0) -> IIT Bombay | L13: IIT Bombay | M13: =VLOOKUP(G13,Dataset!F:H,3,0) -> TG 3 Kasturi Saha | N13: TG 3 Kasturi Saha
A14: 46085.491 | B14: Venkata Jayasurya | C14: Yallapragada | D14: Academician/Researcher | E14: IIT Kanpur | F14: (+91) 9441885075 | G14: jayasurya@iitk.ac.in | H14: Assistant Professor | J14: Kanpur | K14: =VLOOKUP(G14,Dataset!F:H,2,0) -> IIT Bombay | L14: IIT Bombay | M14: =VLOOKUP(G14,Dataset!F:H,3,0) -> TG 1 Anand Jha | N14: TG 1 Anand Jha
A15: 46085.502 | B15: Kasturi | C15: Saha | D15: Academician/Researcher | E15: Qmet Tech Foundation | F15: (+91) 8291020871 | G15: pic@qmettech.com | H15: Project Director | J15: Mumbai | K15: =VLOOKUP(G15,Dataset!F:H,2,0) -> IIT Bombay | L15: IIT Bombay | M15: =VLOOKUP(G15,Dataset!F:H,3,0) -> TG 3 Kasturi Saha | N15: TG 3 Kasturi Saha
A16: 46085.536 | B16: Bimalendu | C16: Deb | D16: Academician/Researcher | E16: Quantum sesing | F16: (91) 8420265902 | G16: msbd@iacs.res.in | H16: Professor | J16: Kolkata | K16: =VLOOKUP(G16,Dataset!F:H,2,0) -> IIT Bombay | L16: IIT Bombay | M16: =VLOOKUP(G16,Dataset!F:H,3,0) -> TG 2 Saikat Ghosh | N16: TG 2 Saikat Ghosh
A17: 46085.623 | B17: Sanjib | C17: Dey | D17: Academician/Researcher | E17: Quantum Sensing and Metrology/IIT Bombay | F17: (+91) 8617433466 | G17: sanjibd@goa.bits-pilani.ac.in | H17: Assistant Professor | J17: Goa | K17: =VLOOKUP(G17,Dataset!F:H,2,0) -> IIT Bombay | L17: IIT Bombay | M17: =VLOOKUP(G17,Dataset!F:H,3,0) -> TG 2 Saikat Ghosh | N17: TG 2 Saikat Ghosh
A18: 46085.828 | B18: Debapriya | C18: Basu Roy | D18: Academician/Researcher | E18: IIT Kanpur | F18: (+91) 9432149757 | G18: dbroy@cse.iitk.ac.in | H18: Assistant Professor | J18: Kanpur | K18: =VLOOKUP(G18,Dataset!F:H,2,0) -> IIT Madras | L18: IIT Madras | M18: =VLOOKUP(G18,Dataset!F:H,3,0) -> PIPETA: Post Quantum Cryptography | N18: PIPETA: Post Quantum Cryptography
A19: 46085.828 | B19: Ashish | C19: Arora | D19: Academician/Researcher | E19: IISER Pune | F19: (91) 9892294386 | G19: ashish.arora@iiserpune.ac.in | H19: Assistant Professor | J19: Pune | K19: =VLOOKUP(G19,Dataset!F:H,2,0) -> IIT Delhi | L19: IIT Delhi | M19: =VLOOKUP(G19,Dataset!F:H,3,0) -> TG2: Wafer-scale Emitter and Detector Arrays for Multi-wavelength RoomTemperature Photonic Quantum Technologies | N19: TG2: Wafer-scale Emitter and Detector Arrays for Multi-wavelength RoomTemperature Photonic Quantum Technologies
A20: 46085.876 | B20: Saikat | C20: Ghosh | D20: Academician/Researcher | E20: IIT-Kanpur | F20: (+91) 8545043528 | G20: gsaikat@iitk.ac.in | H20: Associate Professor | J20: Kanpur | K20: =VLOOKUP(G20,Dataset!F:H,2,0) -> IIT Bombay | L20: IIT Bombay | M20: =VLOOKUP(G20,Dataset!F:H,3,0) -> TG 2 Saikat Ghosh | N20: TG 2 Saikat Ghosh
... A33: 46091.359 | B33: Varun | C33: Raghunathan | D33: Academician/Researcher | E33: Indian Institute of Science | F33: (+91) 8939619026 | G33: varunr@iisc.ac.in | H33: Associate professor | J33: Bangalore | K33: =VLOOKUP(G33,Dataset!F:H,2,0) -> IIT Madras | L33: IIT Madras | M33: =VLOOKUP(G33,Dataset!F:H,3,0) -> QuILA | N33: QuILA
A34: 46091.385 | B34: Deepak | C34: Gaur | D34: Govt | F34: (+91) 9873209432 | G34: dgaur@cdot.in | H34: Scientist-F | I34: Centre for Development of Telematics | J34: New Delhi | K34: =VLOOKUP(G34,Dataset!F:H,2,0) -> IIT Madras | L34: IIT Madras | M34: =VLOOKUP(G34,Dataset!F:H,3,0) -> PIPETA: Post Quantum Cryptography | N34: PIPETA: Post Quantum Cryptography
A35: 46091.39 | B35: Sarani | C35: Bhattacharya | D35: Academician/Researcher | E35: MPI: IIT Kharagpur, TG: PIPETA | F35: (+91) 9477063861 | G35: bhattacharya.sarani.iitkgp@gmail.com | H35: Assistant Professor | J35: Kharagpur | K35: =VLOOKUP(G35,Dataset!F:H,2,0) -> #N/A | L35: IIT Madras | M35: =VLOOKUP(G35,Dataset!F:H,3,0) -> #N/A | N35: PIPETA: Post Quantum Cryptography
A36: 46091.412 | B36: Rajalakshmi | C36: Gurumurthy | D36: Academician/Researcher | E36: Rajalakshmi Gurumurthy | F36: (+91) 9963071783 | G36: raji@tifrh.res.in | H36: Scientific Officer (F) | J36: Hyderabad | K36: =VLOOKUP(G36,Dataset!F:H,2,0) -> IIT Bombay | L36: IIT Bombay | M36: =VLOOKUP(G36,Dataset!F:H,3,0) -> TG 2 Saikat Ghosh | N36: TG 2 Saikat Ghosh
A37: 46091.416 | B37: Saurabh | C37: Lodha | D37: Academician/Researcher | E37: IIT Bombay | F37: (+91) 9819927460 | G37: saurabh.lodha@gmail.com | H37: Professor | J37: Mumbai | K37: =VLOOKUP(G37,Dataset!F:H,2,0) -> #N/A | L37: IIT Delhi | M37: =VLOOKUP(G37,Dataset!F:H,3,0) -> #N/A | N37: TG2: Wafer-scale Emitter and Detector Arrays for Multi-wavelength RoomTemperature Photonic Quantum Technologies
A38: 46091.417 | B38: Prabha | C38: Mandayam | D38: Academician/Researcher | E38: FQCI/IIT Madras | F38: (+91) 9445992785 | G38: prabhamd@physics.iitm.ac.in | H38: Professor | J38: Chennai | K38: =VLOOKUP(G38,Dataset!F:H,2,0) -> IISc Bangalore | L38: IISc Bangalore | M38: =VLOOKUP(G38,Dataset!F:H,3,0) -> TG 5 Quantum computers with Superconducting Qubits | N38: TG 5 Quantum computers with Superconducting Qubits
A39: 46091.444 | B39: Shailendra K. | C39: Varshney | D39: Academician/Researcher | E39: IIT Kharagpur (QMD Hub) | F39: (+91) 9732926003 | G39: skvarshney@ece.iitkgp.ac.in | H39: Professor | J39: Kharagpur | K39: =VLOOKUP(G39,Dataset!F:H,2,0) -> IIT Delhi | L39: IIT Delhi | M39: =VLOOKUP(G39,Dataset!F:H,3,0) -> TG3:WaveguideandIntegratedQuantumPhotonics | N39: TG3:WaveguideandIntegratedQuantumPhotonics
A40: 46091.447 | B40: Akshay | C40: Naik | D40: Academician/Researcher | E40: IISc | F40: (+91) 9611396194 | G40: anaik@iisc.ac.in | H40: Professor | J40: Bangalore | K40: =VLOOKUP(G40,Dataset!F:H,2,0) -> IIT Bombay | L40: IIT Bombay | M40: =VLOOKUP(G40,Dataset!F:H,3,0) -> TG 2 Saikat Ghosh | N40: TG 2 Saikat Ghosh
A41: 46091.454 | B41: Rahul | C41: Singh | D41: Academician/Researcher | E41: Indian Institute of Technology, Bombay | F41: (91) 9004059586 | G41: rahuls_ee@iitb.ac.in | H41: Assistant Professor | J41: Mumbai | K41: =VLOOKUP(G41,Dataset!F:H,2,0) -> IISc Bangalore | L41: IISc Bangalore | M41: =VLOOKUP(G41,Dataset!F:H,3,0) -> TG 4 Development of a 50-qubit quantum information processor with electron spins in silicon | N41: TG 4 Development of a 50-qubit quantum information processor with electron spins in silicon
A42: 46091.493 | B42: Prosenjit | C42: Sen | D42: Academician/Researcher | E42: IISc | F42: (+91) 7406890351 | G42: prosenjits@iisc.ac.in | H42: Professor | J42: Bangalore | K42: =VLOOKUP(G42,Dataset!F:H,2,0) -> IIT Bombay | L42: IIT Bombay | M42: =VLOOKUP(G42,Dataset!F:H,3,0) -> TG 2 Saikat Ghosh | N42: TG 2 Saikat Ghosh
A43: 46091.587 | B43: SAMARESH | C43: DAS | D43: Academician/Researcher | E43: IIT DELHI | F43: (91) 9899130814 | G43: samareshdas@care.iitd.ac.in | H43: Professor | J43: Delhi | K43: =VLOOKUP(G43,Dataset!F:H,2,0) -> #N/A | L43: IISc Banglore | M43: =VLOOKUP(G43,Dataset!F:H,3,0) -> #N/A | N43: TG 4 Development of a 50-qubit quantum information processor with electron spins in silicon
A44: 46091.66 | B44: Madhu | C44: Thalakulam | D44: Academician/Researcher | E44: FQCI/IISER Thiruvananthapuram | F44: (91) 9497785983 | G44: madhu@iisertvm.ac.in | H44: Associate Professor | J44: Thiruvananthapuram | K44: =VLOOKUP(G44,Dataset!F:H,2,0) -> IISc Bangalore | L44: =K44 -> IISc Bangalore | M44: =VLOOKUP(G44,Dataset!F:H,3,0) -> TG 4 Development of a 50-qubit quantum information processor with electron spins in silicon | N44: =M44 -> TG 4 Development of a 50-qubit quantum information processor with electron spins in silicon
A45: 46091.662 | B45: Senthil Kumar | C45: M | D45: Govt | F45: (+91) 9427048883 | G45: senthiliist@gmail.com | H45: LPI NQM | I45: SAC, ISRO | J45: Ahmedabad | K45: =VLOOKUP(G45,Dataset!F:H,2,0) -> #N/A | L45: IIT Madras | M45: =VLOOKUP(G45,Dataset!F:H,3,0) -> #N/A | N45: SBQKD - ISRO
A46: 46091.702 | B46: Dr. Avinash | C46: Lahgere | D46: Academician/Researcher | E46: IIT Kanpur | F46: (91) 9711611954 | G46: alahgere@iitk.ac.in | H46: Assistant Professor | J46: Kanpur | K46: =VLOOKUP(G46,Dataset!F:H,2,0) -> IISc Bangalore | L46: =K46 -> IISc Bangalore | M46: =VLOOKUP(G46,Dataset!F:H,3,0) -> TG 3 Design and Demonstration of a Highly Scalable Quantum Computer using Semiconducting Qubits | N46: =M46 -> TG 3 Design and Demonstration of a Highly Scalable Quantum Computer using Semiconducting Qubits
A47: 46091.769 | B47: Anil | C47: Shaji | D47: Academician/Researcher | E47: Quantum Computing Hub - TG4 - IISER TVM (Member Institute) | F47: (+91) 9446460011 | G47: shaji@iisertvm.ac.in | H47: Professor | J47: Thiruvananthapuram | K47: =VLOOKUP(G47,Dataset!F:H,2,0) -> #N/A | L47: IISc Banglore | M47: =VLOOKUP(G47,Dataset!F:H,3,0) -> #N/A | N47: TG 4 Development of a 50-qubit quantum information processor with electron spins in silicon
A48: 46091.787 | B48: Shankar Kumar | C48: Selvaraja | D48: Academician/Researcher | E48: Indian Institute of Science | F48: (91) 9481283513 | G48: shankarks@iisc.ac.in | H48: Professor | J48: Bangalore | K48: =VLOOKUP(G48,Dataset!F:H,2,0) -> IISc Bangalore | L48: =K48 -> IISc Bangalore | M48: =VLOOKUP(G48,Dataset!F:H,3,0) -> TG 1 Photonics quantum processor development | N48: =M48 -> TG 1 Photonics quantum processor development
A49: 46091.871 | B49: Abhisek | C49: Dixit | D49: Academician/Researcher | E49: Quantum Computing/IIT Delhi | F49: (+91) 8373905693 | G49: adixit@ee.iitd.ac.in | H49: Professor | J49: New Delhi | K49: =VLOOKUP(G49,Dataset!F:H,2,0) -> #N/A | L49: IISc Banglore | M49: =VLOOKUP(G49,Dataset!F:H,3,0) -> #N/A | N49: TG 3 Design and Demonstration of a Highly Scalable Quantum Computer using Semiconducting Qubits
A50: 46091.9 | B50: Parvendra | C50: Kumar | D50: Academician/Researcher | E50: IITM CDOT Samgnya Technologies Foundation/IIT Delhi | F50: (+91) 7505086612 | G50: parvendra@iitd.ac.in | H50: Assistant Professor | J50: New Delhi | K50: =VLOOKUP(G50,Dataset!F:H,2,0) -> #N/A | L50: IIT Madras | M50: =VLOOKUP(G50,Dataset!F:H,3,0) -> #N/A | N50: TAHQEECAT
A51: 46092.29 | B51: Saptarishi | C51: Chaudhuri | D51: Academician/Researcher | E51: FQCI / RRI | F51: (91) 7259899430 | G51: srishic@rri.res.in | H51: Professor | J51: Bengaluru | K51: =VLOOKUP(G51,Dataset!F:H,2,0) -> IISc Bangalore | L51: =K51 -> IISc Bangalore | M51: =VLOOKUP(G51,Dataset!F:H,3,0) -> TG 6 Quantum Computing with Neutral Atoms, Trapped Ions and Related Hybrid Systems | N51: =M51 -> TG 6 Quantum Computing with Neutral Atoms, Trapped Ions and Related Hybrid Systems
A52: 46092.366 | B52: Anand | C52: Jha | D52: Academician/Researcher | E52: IIT Kanpur | F52: (+91) 9621423993 | G52: akjha@iitk.ac.in | H52: Professor | J52: Kanpur | K52: =VLOOKUP(G52,Dataset!F:H,2,0) -> IIT Bombay | L52: =K52 -> IIT Bombay | M52: =VLOOKUP(G52,Dataset!F:H,3,0) -> TG 1 Anand Jha | N52: =M52 -> TG 1 Anand Jha
A53: 46092.448 | B53: Kolin | C53: Paul | D53: Academician/Researcher | E53: IIT Delhi | F53: (+91) 9891942310 | G53: kolin.paul@gmail.com | H53: Professor | J53: New Delhi | K53: =VLOOKUP(G53,Dataset!F:H,2,0) -> IISc Bangalore | L53: =K53 -> IISc Bangalore | M53: =VLOOKUP(G53,Dataset!F:H,3,0) -> TG 3 Design and Demonstration of a Highly Scalable Quantum Computer using Semiconducting Qubits | N53: =M53 -> TG 3 Design and Demonstration of a Highly Scalable Quantum Computer using Semiconducting Qubits
A54: 46092.471 | B54: Henry | C54: Sukumar | D54: Govt | F54: (+91) 9886660658 | G54: henrys@cdac.in | H54: Scientist F | I54: C-DAC | J54: Bengaluru | K54: =VLOOKUP(G54,Dataset!F:H,2,0) -> IISc Bangalore | L54: =K54 -> IISc Bangalore | M54: =VLOOKUP(G54,Dataset!F:H,3,0) -> TG 2 Programmable photonic quantum computing using qubits encoded in different degrees of freedom of a photon | N54: =M54 -> TG 2 Programmable photonic quantum computing using qubits encoded in different degrees of freedom of a photon
A55: 46092.622 | B55: Uditendu | C55: Mukhopadhyay | D55: Academician/Researcher | E55: Computing Hub | F55: (+91) 9163063487 | G55: uditendu@iitb.ac.in | H55: Assistant Professor (MPI in TG4) | J55: Mumbai | K55: =VLOOKUP(G55,Dataset!F:H,2,0) -> #N/A | L55: IISc Banglore | M55: =VLOOKUP(G55,Dataset!F:H,3,0) -> #N/A | N55: TG 4 Development of a 50-qubit quantum information processor with electron spins in silicon
A56: 46092.739 | B56: Sandeep Kumar | C56: Goyal | D56: Academician/Researcher | E56: Quantum Communication/ IISER Mohali | F56: (+91) 8572879340 | G56: skgoyal@iisermohali.ac.in | H56: Associate Professor | J56: Mohali | K56: =VLOOKUP(G56,Dataset!F:H,2,0) -> IIT Madras | L56: =K56 -> IIT Madras | M56: =VLOOKUP(G56,Dataset!F:H,3,0) -> QuePRAN | N56: =M56 -> QuePRAN
A57: 46093.461 | B57: Devarshi Mrinal | C57: Das | D57: Academician/Researcher | E57: FQCI T-Hub / IIT Ropar | F57: (+91) 7738221277 | G57: devarshi.das@iitrpr.ac.in | H57: Assistant Professor | J57: Rupnagar, Punjab | K57: =VLOOKUP(G57,Dataset!F:H,2,0) -> #N/A | L57: IISc Banglore | M57: =VLOOKUP(G57,Dataset!F:H,3,0) -> #N/A | N57: TG 3 Design and Demonstration of a Highly Scalable Quantum Computer using Semiconducting Qubits
A58: 46093.476 | B58: Vaibhav Pratap | C58: Singh | D58: Govt | F58: (91) 7829635748 | G58: svaibhav@cdac.in | H58: Scientist 'E' | I58: CDAC Bangalore | J58: Bengaluru | K58: =VLOOKUP(G58,Dataset!F:H,2,0) -> IISc Bangalore | L58: =K58 -> IISc Bangalore | M58: =VLOOKUP(G58,Dataset!F:H,3,0) -> TG 1 Photonics quantum processor development | N58: =M58 -> TG 1 Photonics quantum processor development
A59: 46093.544 | B59: Rajamani | C59: Vijayaraghavan | D59: Academician/Researcher | E59: FQCI, IISc Bengaluru | F59: (+91) 9967167467 | G59: r.vijay@tifr.res.in | H59: Associate Professor | J59: Mumbai | K59: =VLOOKUP(G59,Dataset!F:H,2,0) -> #N/A | L59: IISc Banglore | M59: =VLOOKUP(G59,Dataset!F:H,3,0) -> #N/A | N59: TG 5 Quantum computers with Superconducting Qubits
A60: 46093.659 | B60: Ravi | C60: Pant | D60: Academician/Researcher | E60: IISER Thiruvananthapuram | F60: (+91) 8136810732 | G60: rpant@iisertvm.ac.in | H60: Associate Professor | J60: Trivandrum | K60: =VLOOKUP(G60,Dataset!F:H,2,0) -> IISc Bangalore | L60: =K60 -> IISc Bangalore | M60: =VLOOKUP(G60,Dataset!F:H,3,0) -> TG 1 Photonics quantum processor development | N60: =M60 -> TG 1 Photonics quantum processor development
A61: 46093.699 | B61: Anirban | C61: Mitra | D61: Academician/Researcher | E61: TG3/I.I.T, Roorkee | F61: (91) 8927280951 | G61: anirban.mitra@ph.iitr.ac.in | H61: Professor | J61: Roorkee | K61: =VLOOKUP(G61,Dataset!F:H,2,0) -> IIT Delhi | L61: =K61 -> IIT Delhi | M61: =VLOOKUP(G61,Dataset!F:H,3,0) -> TG3:WaveguideandIntegratedQuantumPhotonics | N61: =M61 -> TG3:WaveguideandIntegratedQuantumPhotonics
A62: 46093.702 | B62: Dr Raghavan | C62: EASWARAN | D62: Academician/Researcher | E62: IITM C-DOT | F62: (+91) 7542957634 | G62: raghavanke@iitp.ac.in | H62: Associate Professor IIT Patna | J62: Patna | K62: =VLOOKUP(G62,Dataset!F:H,2,0) -> IIT Madras | L62: =K62 -> IIT Madras | M62: =VLOOKUP(G62,Dataset!F:H,3,0) -> QuePRAN | N62: =M62 -> QuePRAN
A63: 46094.599 | B63: Praveen | C63: Kumar | D63: Academician/Researcher | E63: IIT Delhi (TG 2) | F63: (+91) 6290260756 | G63: praiitr@gmail.com | H63: Associate Professor | J63: MOHALI | K63: =VLOOKUP(G63,Dataset!F:H,2,0) -> #N/A | L63: IIT Delhi | M63: =VLOOKUP(G63,Dataset!F:H,3,0) -> #N/A | N63: TG2: Wafer-scale Emitter and Detector Arrays for Multi-wavelength RoomTemperature Photonic Quantum Technologies
A64: 46094.736 | B64: Amitangshu | C64: Pal | D64: Academician/Researcher | E64: IIT Kanpur | F64: (+91) 7384523610 | G64: amitangshu@cse.iitk.ac.in | H64: Assistant Professor | J64: Kanpur | K64: =VLOOKUP(G64,Dataset!F:H,2,0) -> IIT Bombay | L64: =K64 -> IIT Bombay | M64: =VLOOKUP(G64,Dataset!F:H,3,0) -> TG 2 Saikat Ghosh | N64: =M64 -> TG 2 Saikat Ghosh
A65: 46079.797 | B65: Arijit | C65: Sharma | D65: Academician/Researcher | E65: IIT TIRUPATI | F65: (+91) 9810875287 | G65: arijit@iittp.ac.in | H65: ASSOCIATE PROFESSOR | J65: TIRUPATI | K65: =VLOOKUP(G65,Dataset!F:H,2,0) -> IIT Madras | L65: =K65 -> IIT Madras | M65: =VLOOKUP(G65,Dataset!F:H,3,0) -> QuePRAN | N65: =M65 -> QuePRAN
A66: 46095.553 | B66: Debdeep | C66: Mukhopadhyay | D66: Academician/Researcher | E66: IIT Kharagpur | F66: (+91) 7478792350 | G66: debdeep.mukhopadhyay@gmail.com | H66: Asso Dean R&D and Professor, CSE | J66: Kharagpur | K66: =VLOOKUP(G66,Dataset!F:H,2,0) -> #N/A | L66: IIT Madras | M66: =VLOOKUP(G66,Dataset!F:H,3,0) -> #N/A | N66: PIPETA: Post Quantum Cryptography
A67: 46095.775 | B67: Pratap | C67: Raychaudhuri | D67: Academician/Researcher | E67: TIFR mumbai | F67: (+91) 9869303774 | G67: pratap@tifr.res.in | H67: Sr. Professor | J67: Mumbai | K67: =VLOOKUP(G67,Dataset!F:H,2,0) -> #N/A | L67: IIT Bombay | M67: =VLOOKUP(G67,Dataset!F:H,3,0) -> #N/A | N67: TG 3 Kasturi Saha
A68: 46096.019 | B68: D S | C68: Rawal | D68: Govt | F68: (91) 9818013936 | G68: dsrawal15@gmail.com | H68: Outstanding Scientist | I68: SSPL DRDO | J68: Delhi | K68: =VLOOKUP(G68,Dataset!F:H,2,0) -> #N/A | L68: IIT Delhi | M68: =VLOOKUP(G68,Dataset!F:H,3,0) -> #N/A | N68: TG1: Development ofOn-DemandSinglePhotonEmitters, SinglePhotonAvalancheDetectors,High-FrequencyDevices andInP-BasedEpitaxialSemiconductors
A69: 46096.501 | B69: Kanhaiya | C69: Pandey | D69: Academician/Researcher | E69: Quantum Computing Hub, IITG | F69: (+91) 8761942326 | G69: kanhaiyapandey@iitg.ac.in | H69: Associate Professor | J69: Guwahati | K69: =VLOOKUP(G69,Dataset!F:H,2,0) -> IISc Bangalore | L69: =K69 -> IISc Bangalore | M69: =VLOOKUP(G69,Dataset!F:H,3,0) -> TG 6 Quantum Computing with Neutral Atoms, Trapped Ions and Related Hybrid Systems | N69: =M69 -> TG 6 Quantum Computing with Neutral Atoms, Trapped Ions and Related Hybrid Systems
A70: 46096.668 | B70: Jaydeep Kumar | C70: Basu | D70: Academician/Researcher | E70: Quantum Computing/ IISc | F70: (+91) 9886324567 | G70: basu@iisc.ac.in | H70: Professor, MPI | J70: Bangalore | K70: =VLOOKUP(G70,Dataset!F:H,2,0) -> IISc Bangalore | L70: =K70 -> IISc Bangalore | M70: =VLOOKUP(G70,Dataset!F:H,3,0) -> TG 1 Photonics quantum processor development | N70: =M70 -> TG 1 Photonics quantum processor development
A71: 46096.836 | B71: C M | C71: Chandrashekar | D71: Academician/Researcher | E71: Indian Institute of Science | F71: (+91) 9566000369 | G71: chandracm@iisc.ac.in | H71: Professor | J71: Bengaluru | K71: =VLOOKUP(G71,Dataset!F:H,2,0) -> IISc Bangalore | L71: =K71 -> IISc Bangalore | M71: =VLOOKUP(G71,Dataset!F:H,3,0) -> TG 2 Programmable photonic quantum computing using qubits encoded in different degrees of freedom of a photon | N71: =M71 -> TG 2 Programmable photonic quantum computing using qubits encoded in different degrees of freedom of a photon
A72: 46097.505 | B72: Apoorva | C72: Patel | D72: Academician/Researcher | F72: (+91) 9741294802 | G72: adpatel@iisc.ac.in | H72: Professor | J72: Bengaluru | K72: =VLOOKUP(G72,Dataset!F:H,2,0) -> IISc Bangalore | M72: =VLOOKUP(G72,Dataset!F:H,3,0) -> TG 1 Photonics quantum processor development
A73: 46097.528 | B73: Akshay | C73: Singh | D73: Academician/Researcher | F73: (+91) 9870127569 | G73: aksy@iisc.ac.in | H73: Assistant professor | J73: bengaluru | K73: =VLOOKUP(G73,Dataset!F:H,2,0) -> IISc Bangalore | L73: =K73 -> IISc Bangalore | M73: =VLOOKUP(G73,Dataset!F:H,3,0) -> TG 1 Photonics quantum processor development | N73: =M73 -> TG 1 Photonics quantum processor development
A74: 46097.605 | B74: Neeraj | C74: Goel | D74: Academician/Researcher | F74: (+91) 9818562842 | G74: neeraj@iitrpr.ac.in | H74: Associate Professor | J74: Ropar | K74: =VLOOKUP(G74,Dataset!F:H,2,0) -> #N/A | L74: IISc Bangalore | M74: =VLOOKUP(G74,Dataset!F:H,3,0) -> #N/A | N74: TG 3 Design and Demonstration of a Highly Scalable Quantum Computer using Semiconducting Qubits
A75: 46097.749 | B75: Ashok | C75: Mohapatra | D75: Academician/Researcher | F75: (+91) 8249520154 | G75: a.mohapatra@niser.ac.in | H75: Assoc. Prof. | J75: Bhubaneswar | K75: =VLOOKUP(G75,Dataset!F:H,2,0) -> IISc Bangalore | L75: =K75 -> IISc Bangalore | M75: =VLOOKUP(G75,Dataset!F:H,3,0) -> TG 6 Quantum Computing with Neutral Atoms, Trapped Ions and Related Hybrid Systems | N75: =M75 -> TG 6 Quantum Computing with Neutral Atoms, Trapped Ions and Related Hybrid Systems
A76: 46098.391 | B76: Awanish | C76: Pandey | D76: Academician/Researcher | F76: (+91) 8762262341 | G76: opcawanish@iitd.ac.in | H76: Assistant Professor | J76: New Delhi | K76: =VLOOKUP(G76,Dataset!F:H,2,0) -> #N/A | L76: IISc Bangalore | M76: =VLOOKUP(G76,Dataset!F:H,3,0) -> #N/A | N76: TG 1 Photonics quantum processor development
A77: 46098.423 | B77: Mukesh | C77: Kumar | D77: Academician/Researcher | E77: Foundation for QC Innovation IISc Bangalore | F77: (+91) 8437166802 | G77: mukesh.kr@iiti.ac.in | H77: Professor | J77: Indore | K77: =VLOOKUP(G77,Dataset!F:H,2,0) -> IISc Bangalore | L77: =K77 -> IISc Bangalore | M77: =VLOOKUP(G77,Dataset!F:H,3,0) -> TG 1 Photonics quantum processor development | N77: =M77 -> TG 1 Photonics quantum processor development
A78: 46098.466 | B78: Anirban | C78: Pathak | D78: Academician/Researcher | E78: Foundation for QC Innovation IISc Bangalore | F78: (+91) 9717066494 | G78: anirban.pathak@gmail.com | H78: Professor | J78: Noida | K78: =VLOOKUP(G78,Dataset!F:H,2,0) -> #N/A | L78: IISc Bangalore | M78: =VLOOKUP(G78,Dataset!F:H,3,0) -> #N/A | N78: TG 2 Programmable photonic quantum computing using qubits encoded in different degrees of freedom of a photon
A79: 46098.467 | B79: Prof. Rajendra | C79: Singh | D79: Academician/Researcher | E79: QMD Foundation at IIT Delhi | F79: (91) 95827 74442 | G79: rsingh@physics.iitd.ac.in | H79: Project Director | J79: New Delhi | K79: =VLOOKUP(G79,Dataset!F:H,2,0) -> #N/A | L79: IIT Delhi | M79: =VLOOKUP(G79,Dataset!F:H,3,0) -> #N/A | N79: TG 1 Development of on-demand single photon emitters, single photon avalanche detectors, high-frequency devices and InP based Epitaxial semiconductors
A80: 46098.519 | B80: Vishvendra Singh | C80: Poonia | D80: Academician/Researcher | E80: Foundation for QC Innovation IISc Bangalore | F80: (+91) 8097426535 | G80: vishvendra@ece.iitr.ac.in | H80: Associate Professor | J80: Roorkee | K80: =VLOOKUP(G80,Dataset!F:H,2,0) -> IISc Bangalore | L80: =K80 -> IISc Bangalore | M80: =VLOOKUP(G80,Dataset!F:H,3,0) -> TG 3 Design and Demonstration of a Highly Scalable Quantum Computer using Semiconducting Qubits | N80: =M80 -> TG 3 Design and Demonstration of a Highly Scalable Quantum Computer using Semiconducting Qubits
A81: 46098.531 | B81: Ajay | C81: Wasan | D81: Academician/Researcher | E81: Foundation for QC Innovation IISc Bangalore | F81: (097205) 43906 | G81: awasan@ph.iitr.ac.in | H81: Professor | J81: Roorkee | K81: =VLOOKUP(G81,Dataset!F:H,2,0) -> IISc Bangalore | L81: =K81 -> IISc Bangalore | M81: =VLOOKUP(G81,Dataset!F:H,3,0) -> TG 6 Quantum Computing with Neutral Atoms, Trapped Ions and Related Hybrid Systems | N81: =M81 -> TG 6 Quantum Computing with Neutral Atoms, Trapped Ions and Related Hybrid Systems
A82: 46098.565 | B82: Kausik | C82: Majumdar | D82: Academician/Researcher | E82: Foundation for QC Innovation IISc Bangalore | F82: (+91) 7022665421 | G82: kausikm@iisc.ac.in | H82: Associate Professor | J82: Bangalore | K82: =VLOOKUP(G82,Dataset!F:H,2,0) -> IISc Bangalore | L82: =K82 -> IISc Bangalore | M82: =VLOOKUP(G82,Dataset!F:H,3,0) -> TG 1 Photonics quantum processor development | N82: =M82 -> TG 1 Photonics quantum processor development
A83: 46098.597 | B83: Rakesh | C83: Palani | D83: Academician/Researcher | E83: Foundation for QC Innovation IISc Bangalore | F83: (+91) 9606310202 | G83: rakesh@ee.iitd.ac.in | H83: Associate Professor | J83: Delhi | K83: =VLOOKUP(G83,Dataset!F:H,2,0) -> #N/A | L83: IISc Bangalore | M83: =VLOOKUP(G83,Dataset!F:H,3,0) -> #N/A | N83: TG 3 Design and Demonstration of a Highly Scalable Quantum Computer using Semiconducting Qubits
A84: 46098.658 | B84: Darshak | C84: Bhatt | D84: Academician/Researcher | E84: Foundation for QC Innovation IISc Bangalore | F84: (+91) 8879179443 | G84: darshak.bhatt@ece.iitr.ac.in | H84: Associate Professor | J84: Roorkee | K84: =VLOOKUP(G84,Dataset!F:H,2,0) -> IISc Bangalore | L84: IISc Bangalore | M84: =VLOOKUP(G84,Dataset!F:H,3,0) -> TG 3 Design and Demonstration of a Highly Scalable Quantum Computer using Semiconducting Qubits | N84: TG 3 Design and Demonstration of a Highly Scalable Quantum Computer using Semiconducting Qubits
A85: 46098.705 | B85: Sai | C85: Vinjanampathy | D85: Academician/Researcher | E85: Qmet Tech Foundation at IIT Bombay | F85: (022) 25767592 | G85: sai.vinjanampathy@iitb.ac.in | H85: Associate Professor | J85: Mumbai | K85: =VLOOKUP(G85,Dataset!F:H,2,0) -> #N/A | L85: IISc Bangalore | IIT Bombay | M85: =VLOOKUP(G85,Dataset!F:H,3,0) -> #N/A | N85: TG 5 Quantum computers with Superconducting Qubits | TG 2 Saikat Ghosh
A86: 46098.789 | B86: Vibhor | C86: Singh | D86: Academician/Researcher | E86: Foundation for QC Innovation IISc Bangalore | F86: (+91) 9108157495 | G86: v.singh@iisc.ac.in | H86: Associate Professor | J86: Bangalore | K86: =VLOOKUP(G86,Dataset!F:H,2,0) -> IISc Bangalore | L86: =K86 -> IISc Bangalore | M86: =VLOOKUP(G86,Dataset!F:H,3,0) -> TG 5 Quantum computers with Superconducting Qubits | N86: =M86 -> TG 5 Quantum computers with Superconducting Qubits
A87: 46098.792 | B87: Chetan Singh | C87: Thakur | D87: Academician/Researcher | E87: Foundation for QC Innovation IISc Bangalore | F87: (+91) 9731680833 | G87: csthakur@iisc.ac.in | H87: Professor | J87: Bengaluru | K87: =VLOOKUP(G87,Dataset!F:H,2,0) -> IISc Bangalore | L87: =K87 -> IISc Bangalore | M87: =VLOOKUP(G87,Dataset!F:H,3,0) -> TG 5 Quantum computers with Superconducting Qubits | N87: =M87 -> TG 5 Quantum computers with Superconducting Qubits
A88: 46098.866 | B88: UTPAL | C88: ROY | D88: Academician/Researcher | E88: Foundation for QC Innovation IISc Bangalore | F88: (+91) 8102156405 | G88: uroy@iitp.ac.in | H88: Associate Professor | J88: Patna | K88: =VLOOKUP(G88,Dataset!F:H,2,0) -> IISc Bangalore | L88: =K88 -> IISc Bangalore | M88: =VLOOKUP(G88,Dataset!F:H,3,0) -> TG 6 Quantum Computing with Neutral Atoms, Trapped Ions and Related Hybrid Systems | N88: =M88 -> TG 6 Quantum Computing with Neutral Atoms, Trapped Ions and Related Hybrid Systems
A89: 46098.972 | B89: Baladitya | C89: Suri | D89: Academician/Researcher | E89: Foundation for QC Innovation IISc Bangalore | F89: (+91) 9481186223 | G89: surib@iisc.ac.in | H89: Associate Professor | J89: Bengaluru | K89: =VLOOKUP(G89,Dataset!F:H,2,0) -> IISc Bangalore | L89: =K89 -> IISc Bangalore | M89: =VLOOKUP(G89,Dataset!F:H,3,0) -> TG 5 Quantum computers with Superconducting Qubits | N89: =M89 -> TG 5 Quantum computers with Superconducting Qubits
A90: 46099.318 | B90: Rejish Nath | C90: Gopinathan Rejani | D90: Academician/Researcher | E90: Foundation for QC Innovation IISc Bangalore | F90: (020) 25908165 | G90: rejish@iiserpune.ac.in | H90: Professor | J90: Pune | K90: =VLOOKUP(G90,Dataset!F:H,2,0) -> #N/A | L90: IISc Bangalore | M90: =VLOOKUP(G90,Dataset!F:H,3,0) -> #N/A | N90: TG 6 Quantum Computing with Neutral Atoms, Trapped Ions and Related Hybrid Systems
A91: 46099.414 | B91: Kedar | C91: Khare | D91: Academician/Researcher | E91: Qmet Tech Foundation at IIT Bombay | F91: (91) 9868278691 | G91: kedark@opc.iitd.ac.in | H91: Professor | J91: New Delhi | K91: =VLOOKUP(G91,Dataset!F:H,2,0) -> IIT Bombay | L91: IIT Bombay | M91: =VLOOKUP(G91,Dataset!F:H,3,0) -> TG 1 Anand Jha | N91: =M91 -> TG 1 Anand Jha
A92: 46105.382 | B92: Saravana | C92: Kumar | D92: Academician/Researcher | F92: (+91) 6369385349 | G92: saravana.kumar@ece.iitr.ac.in | H92: Assistant Professor | I92: Foundation for QC Innovation IISc Bangalore | J92: Delhi | K92: =VLOOKUP(G92,Dataset!F:H,2,0) -> IISc Bangalore | L92: IISc Bangalore
A93: 46105.641 | B93: Suraj | C93: Mandal | D93: Student | F93: (+91) 8617844701 | G93: surajm22@iitk.ac.in | H93: PhD Scholar | I93: INDIAN INSTITUTE OF TECHNOLOGY KANPUR | J93: KANPUR | K93: =VLOOKUP(G93,Dataset!F:H,2,0) -> #N/A | L93: IITM CDOT Samgnya Technologies Foundation at IIT Madras | O93: Debapriya Das
A94: 46105.747 | B94: Anirudh | C94: Jaiswal | D94: Student | F94: (+91) 7439215216 | G94: anirudh_202200138@smit.smu.edu.in | H94: Project Intern | I94: Indian Institute of Technology Bhilai (IITBH) | J94: Chattisgarh, Durg | K94: =VLOOKUP(G94,Dataset!F:H,2,0) -> #N/A | L94: IITM CDOT Samgnya Technologies Foundation at IIT Madras | O94: Dhiman Saha
A95: 46105.923 | B95: Anshuman | C95: Kumar | D95: Academician/Researcher | F95: (099587) 13346 | G95: anshuman.kumar@iitb.ac.in | H95: Associate Professor | J95: Mumbai | K95: =VLOOKUP(G95,Dataset!F:H,2,0) -> #N/A | L95: QMD Foundation | N95: TG2: Wafer-scale Emitter and Detector Arrays for Multi-wavelength RoomTemperature Photonic Quantum Technologie
A96: 46105.964 | B96: Sai Tarun | C96: Baratam | D96: Student | F96: (+91) 9560241708 | G96: saitarun.baratam25@kgpian.iitkgp.ac.in | H96: MS student at Computer science and engineering department | I96: IIT Kharagpur | J96: Kharagpur, Paschim Medinipur | K96: =VLOOKUP(G96,Dataset!F:H,2,0) -> #N/A | L96: IITM CDOT Samgnya Technologies Foundation at IIT Madras | O96: Debdeep Mukopadhyay
A97: 46106.719 | B97: Amrita | C97: Bhattacharya | D97: Academician/Researcher | F97: (091) 9930557620 | G97: b.amrita10@gmail.com | H97: Associate Professor | J97: Mumbai | K97: =VLOOKUP(G97,Dataset!F:H,2,0) -> #N/A | L97: QMD Foundation | N97: TG2: Wafer-scale Emitter and Detector Arrays for Multi-wavelength RoomTemperature Photonic Quantum Technologie
A98: 46106.723 | B98: Swaroop | C98: Ganguly | D98: Academician/Researcher | F98: (+91) 9867759249 | G98: swaroop.ganguly@iitb.ac.in | H98: Professor | J98: Mumbai | K98: =VLOOKUP(G98,Dataset!F:H,2,0) -> #N/A | L98: QMD Foundation | N98: TG 1 Development ofOn-DemandSinglePhotonEmitters, SinglePhotonAvalancheDetectors,High-FrequencyDevices andInP-BasedEpitaxialSemiconductors
A99: 46106.724 | B99: Dibyajyoti | C99: Ghosh | D99: Academician/Researcher | F99: (+91) 9289013008 | G99: dibyajyoti@iitd.ac.in | H99: Assistant Professor | J99: New Delhi | K99: =VLOOKUP(G99,Dataset!F:H,2,0) -> #N/A | L99: QMD Foundation | N99: TG 1 Development ofOn-DemandSinglePhotonEmitters, SinglePhotonAvalancheDetectors,High-FrequencyDevices andInP-BasedEpitaxialSemiconductors
A100: 46106.73 | B100: Maniraj | C100: Mahalingam | D100: Academician/Researcher | F100: (+91) 9039493225 | G100: maniraj@iitb.ac.in | H100: Professor | J100: Mumbai | K100: =VLOOKUP(G100,Dataset!F:H,2,0) -> IIT Delhi | L100: QMD Foundation
A101: 46106.74 | B101: Rajaraman | C101: Gopalan | D101: Academician/Researcher | F101: (+91) 9833607183 | G101: rajaraman@chem.iitb.ac.in | H101: Professor | J101: Mumbai | K101: =VLOOKUP(G101,Dataset!F:H,2,0) -> IIT Delhi | L101: QMD Foundation
A102: 46106.744 | B102: Karun | C102: Rawat | D102: Academician/Researcher | F102: (+91) 8585992445 | G102: karun.rawat@ece.iitr.ac.in | H102: Professor | J102: Roorkee | K102: =VLOOKUP(G102,Dataset!F:H,2,0) -> IIT Delhi | L102: QMD Foundation
A103: 46107.74 | B103: Santanu | C103: Manna | D103: Academician/Researcher | F103: (+91) 9775577930 | G103: mannasan@ee.iitd.ac.in | H103: Assistant Professor | J103: New Delhi | K103: =VLOOKUP(G103,Dataset!F:H,2,0) -> IIT Delhi | L103: QMD Foundation
A104: 46107.924 | B104: Siddhartha | C104: Chowdhury | D104: Student | F104: (+91) 9038043198 | G104: siddhartha.chowdhury92@gmail.com | H104: PhD Student | I104: Indian Institute of Technology Kharagpur | J104: Kharagpur | K104: =VLOOKUP(G104,Dataset!F:H,2,0) -> #N/A | L104: IITM CDOT Samgnya Technologies Foundation at IIT Madras | O104: Debdeep Mukopadhyay
A105: 46108.559 | B105: Rohit | C105: Chaurasiya | D105: Academician/Researcher | F105: (+91) 9049582034 | G105: rohit.chaurasiya@iitjammu.ac.in | H105: Assistant Professor | J105: Jammu | K105: IITM CDOT Samgnya Technologies Foundation at IIT Madras
A106: 46108.626 | B106: Sudipta | C106: Dubey | D106: Academician/Researcher | F106: (+91) 8604933508 | G106: sudiptad@iitk.ac.in | H106: Assistant Professor | J106: Kanpur | K106: QMD Foundation at IIT Delhi
A107: 46080.48 | B107: Gayathri | C107: Raman | D107: Academician/Researcher | E107: IIT Bombay | F107: (+91) 8095096873 | G107: g3raman@iitb.ac.in | H107: Program Manager | J107: Mumbai | K107: =VLOOKUP(G107,Dataset!F:H,2,0) -> #N/A | L107: IIT Delhi | M107: =VLOOKUP(G107,Dataset!F:H,3,0) -> #N/A
A108: 46079.797 | B108: Ravindra | C108: Barlingay | D108: Industry | F108: (+91) 9820776114 | G108: ceo@samgnya.in | H108: CEO | I108: IITM CDOT Samgnya Technologies Foundation | J108: Chennai | K108: =VLOOKUP(G108,Dataset!F:H,2,0) -> #N/A | L108: IIT Madras | M108: =VLOOKUP(G108,Dataset!F:H,3,0) -> #N/A | N108: CEO
A109: 46079.807 | B109: Kiran | C109: Shesh | D109: Industry | F109: (+91) 9820007330 | G109: ceo@qmettech.com | H109: CEO | I109: Qmet Tech Foundation | J109: Mumbai | K109: =VLOOKUP(G109,Dataset!F:H,2,0) -> #N/A | L109: IIT Bombay | M109: =VLOOKUP(G109,Dataset!F:H,3,0) -> #N/A | N109: CEO
A110: 46080.391 | B110: Dr. Venkateswaran | C110: PS | D110: Industry | F110: (+91) 7895734999 | G110: venkatps@qcinnovation.co.in | H110: Chief Operating Officer (COO) | I110: FQCI, DST-NQM, IISC | J110: Bengaluru | K110: =VLOOKUP(G110,Dataset!F:H,2,0) -> #N/A | L110: IISc Bangalore | M110: =VLOOKUP(G110,Dataset!F:H,3,0) -> #N/A | N110: COO
A111: 46080.394 | B111: Kunj | C111: Tandon | D111: Govt | F111: (+91) 9731562513 | G111: kunjtandon@quantech.org.in | H111: CEO | I111: I-Hub Quantum Technology Foundation | J111: Pune | K111: =VLOOKUP(G111,Dataset!F:H,2,0) -> #N/A | L111: I-Hub Quantum Technology Foundation | M111: =VLOOKUP(G111,Dataset!F:H,3,0) -> #N/A | N111: COO
A112: 46084.518 | B112: Aditya SG | C112: Vyas | D112: Academician/Researcher | E112: QMD Foundation | F112: (+91) 9214094775 | G112: ceo@qmdhub.co.in | H112: CEO | J112: Delhi | K112: =VLOOKUP(G112,Dataset!F:H,2,0) -> #N/A | L112: IIT Delhi | M112: =VLOOKUP(G112,Dataset!F:H,3,0) -> #N/A | N112: CEO
...

Sheet Confirmed Email List 
A1: Name | B1: Email | C1: Tag
A2: Ritik Jain | B2: ritikjain@iiserb.ac.in | C2: Student | F2: EXPO Emails sent | J2: Poster Presentation
A3: Sourabh Jain | B3: sourabh.jain@students.iiserpune.ac.in | C3: Student | F3: srishic@rri.res.in | G3: =VLOOKUP(F3,$B:$B,1,0) -> srishic@rri.res.in | H3: =VLOOKUP(F3,$J:$J,1,0) -> #N/A | J3: eez248406@ee.iitd.ac.in | K3: =VLOOKUP(J3,$B:$B,1,0) -> #N/A | L3: =VLOOKUP(J3,$F:$F,1,0) -> eez248406@ee.iitd.ac.in
A4: Vinod Kumar | B4: vinod.kumar@students.iiserpune.ac.in | C4: Student | F4: eez248406@ee.iitd.ac.in | G4: =VLOOKUP(F4,$B:$B,1,0) -> #N/A | H4: =VLOOKUP(F4,$J:$J,1,0) -> eez248406@ee.iitd.ac.in | J4: rajat21@iisertvm.ac.in | K4: =VLOOKUP(J4,$B:$B,1,0) -> #N/A | L4: =VLOOKUP(J4,$F:$F,1,0) -> rajat21@iisertvm.ac.in
A5: Aparna Shinde | B5: aparna.shinde@students.iiserpune.ac.in | C5: Student | F5: rajat21@iisertvm.ac.in | G5: =VLOOKUP(F5,$B:$B,1,0) -> #N/A | H5: =VLOOKUP(F5,$J:$J,1,0) -> rajat21@iisertvm.ac.in | J5: umakant.rapol@iiserpune.ac.in | K5: =VLOOKUP(J5,$B:$B,1,0) -> umakant.rapol@iiserpune.ac.in | L5: =VLOOKUP(J5,$F:$F,1,0) -> umakant.rapol@iiserpune.ac.in
A6: Soorya S | B6: sooryas@iiserb.ac.in | C6: Student | F6: sujaimatta@iisc.ac.in | G6: =VLOOKUP(F6,$B:$B,1,0) -> #N/A | H6: =VLOOKUP(F6,$J:$J,1,0) -> #N/A | J6: nishithn@iisc.ac.in | K6: =VLOOKUP(J6,$B:$B,1,0) -> #N/A | L6: =VLOOKUP(J6,$F:$F,1,0) -> #N/A
A7: Chayan Purkait | B7: chayanpurkaitcareer@gmail.com | C7: Student | F7: shankraks@iisc.ac.in | G7: =VLOOKUP(F7,$B:$B,1,0) -> #N/A | H7: =VLOOKUP(F7,$J:$J,1,0) -> #N/A | J7: sancharic@iisc.ac.in | K7: =VLOOKUP(J7,$B:$B,1,0) -> #N/A | L7: =VLOOKUP(J7,$F:$F,1,0) -> #N/A
A8: Dhairya Bhandari | B8: dhairya.bhandari@students.iiserpune.ac.in | C8: Student | F8: shantharamk@iisc.ac.in | G8: =VLOOKUP(F8,$B:$B,1,0) -> #N/A | H8: =VLOOKUP(F8,$J:$J,1,0) -> #N/A | J8: srijitadas22@gmail.com | K8: =VLOOKUP(J8,$B:$B,1,0) -> #N/A | L8: =VLOOKUP(J8,$F:$F,1,0) -> #N/A
A9: Sunny Bajaj | B9: sunny.25phz0023@iitrpr.ac.in | C9: Student | F9: vaishnavi.vaichal@scicomsoftware.com | G9: =VLOOKUP(F9,$B:$B,1,0) -> #N/A | H9: =VLOOKUP(F9,$J:$J,1,0) -> #N/A | J9: phz228454@iitd.ac.in | K9: =VLOOKUP(J9,$B:$B,1,0) -> #N/A | L9: =VLOOKUP(J9,$F:$F,1,0) -> phz228454@iitd.ac.in
A10: Raja Mondal | B10: raja.25phz0021@iitrpr.ac.in | C10: Student | F10: bodhaditya.santra@gmail.com | G10: =VLOOKUP(F10,$B:$B,1,0) -> #N/A | H10: =VLOOKUP(F10,$J:$J,1,0) -> #N/A | J10: debadrita@rrimail.rri.res.in | K10: =VLOOKUP(J10,$B:$B,1,0) -> #N/A | L10: =VLOOKUP(J10,$F:$F,1,0) -> #N/A
A11: Neethu K | B11: staff.neethu@iitrpr.ac.in | C11: Student | F11: sunil@qnulabs.com | G11: =VLOOKUP(F11,$B:$B,1,0) -> #N/A | H11: =VLOOKUP(F11,$J:$J,1,0) -> #N/A | J11: anaghagayathri@smail.iitm.ac.in | K11: =VLOOKUP(J11,$B:$B,1,0) -> #N/A | L11: =VLOOKUP(J11,$F:$F,1,0) -> #N/A
A12: Hrdya Joshi | B12: hrdya.joshi@gmail.com | C12: Student | F12: vamsi.k@qpiai.tech | G12: =VLOOKUP(F12,$B:$B,1,0) -> #N/A | H12: =VLOOKUP(F12,$J:$J,1,0) -> #N/A | J12: siddhartha.chowdhury92@gmail.com | K12: =VLOOKUP(J12,$B:$B,1,0) -> #N/A | L12: =VLOOKUP(J12,$F:$F,1,0) -> #N/A
A13: Rahul Mohanty | B13: rahul.mohanty@tifr.res.in | C13: Student | F13: vidur.raj@quanastra.com | G13: =VLOOKUP(F13,$B:$B,1,0) -> #N/A | H13: =VLOOKUP(F13,$J:$J,1,0) -> #N/A | K13: =VLOOKUP(J13,$B:$B,1,0) -> #N/A | L13: =VLOOKUP(J13,$F:$F,1,0) -> #N/A
A14: Satyabrata Baidya | B14: satyabrata.baidya@tifr.res.in | C14: Student | F14: devendra.mishra@qulabs.ai | G14: =VLOOKUP(F14,$B:$B,1,0) -> #N/A | H14: =VLOOKUP(F14,$J:$J,1,0) -> #N/A | J14: kamalt24@iitk.ac.in | K14: =VLOOKUP(J14,$B:$B,1,0) -> #N/A | L14: =VLOOKUP(J14,$F:$F,1,0) -> #N/A
A15: Vikas R | B15: vikasramaswamy@cdac.in | C15: Student | F15: ashutosh@ee.iitm.ac.in | G15: =VLOOKUP(F15,$B:$B,1,0) -> #N/A | H15: =VLOOKUP(F15,$J:$J,1,0) -> #N/A | J15: pmohta@iitk.ac.in | K15: =VLOOKUP(J15,$B:$B,1,0) -> #N/A | L15: =VLOOKUP(J15,$F:$F,1,0) -> pmohta@iitk.ac.in
A16: Foram P Shingala | B16: foram@setsindia.net | C16: Student | F16: abhilashkd@iitbhilai.ac.in | G16: =VLOOKUP(F16,$B:$B,1,0) -> #N/A | H16: =VLOOKUP(F16,$J:$J,1,0) -> #N/A | J16: eklavy.vashist@qmettech.com | K16: =VLOOKUP(J16,$B:$B,1,0) -> #N/A | L16: =VLOOKUP(J16,$F:$F,1,0) -> #N/A
A17: SELVAGANGAI C | B17: selvagangi@setsindia.net | C17: Student | G17: =VLOOKUP(F17,$B:$B,1,0) -> #N/A | H17: =VLOOKUP(F17,$J:$J,1,0) -> #N/A | J17: dpralekh@iiserb.ac.in | K17: =VLOOKUP(J17,$B:$B,1,0) -> #N/A | L17: =VLOOKUP(J17,$F:$F,1,0) -> #N/A
F18: bkanseri@physics.iitd.ac.in | G18: =VLOOKUP(F18,$B:$B,1,0) -> bkanseri@physics.iitd.ac.in | H18: =VLOOKUP(F18,$J:$J,1,0) -> #N/A | J18: pratyushrajbiswas@gmail.com | K18: =VLOOKUP(J18,$B:$B,1,0) -> #N/A | L18: =VLOOKUP(J18,$F:$F,1,0) -> #N/A
F19: shubham.prajapati@synergyquantum.in | G19: =VLOOKUP(F19,$B:$B,1,0) -> #N/A | H19: =VLOOKUP(F19,$J:$J,1,0) -> #N/A | J19: kumarpawan.ece@gmail.com | K19: =VLOOKUP(J19,$B:$B,1,0) -> #N/A | L19: =VLOOKUP(J19,$F:$F,1,0) -> #N/A
A20: Anupam Patra | B20: anupam.patra.137@tcgcrest.org | C20: Student | F20: aniketnag24@iitk.ac.in | G20: =VLOOKUP(F20,$B:$B,1,0) -> #N/A | H20: =VLOOKUP(F20,$J:$J,1,0) -> #N/A | J20: mahanti.subham25@gmail.com | K20: =VLOOKUP(J20,$B:$B,1,0) -> #N/A | L20: =VLOOKUP(J20,$F:$F,1,0) -> #N/A
F21: prasobh.padmanabhan@qmettech.com | G21: =VLOOKUP(F21,$B:$B,1,0) -> #N/A | H21: =VLOOKUP(F21,$J:$J,1,0) -> #N/A | J21: deepesh.sharma@ee.iitd.ac.in | K21: =VLOOKUP(J21,$B:$B,1,0) -> #N/A | L21: =VLOOKUP(J21,$F:$F,1,0) -> deepesh.sharma@ee.iitd.ac.in
F22: vinayak.rane@qmettech.com | G22: =VLOOKUP(F22,$B:$B,1,0) -> #N/A | H22: =VLOOKUP(F22,$J:$J,1,0) -> #N/A | K22: =VLOOKUP(J22,$B:$B,1,0) -> #N/A | L22: =VLOOKUP(J22,$F:$F,1,0) -> #N/A
A23: Aishwarya L | B23: aishwarya1820@gmail.com | C23: Student | F23: vinayak.rane@qmettech.com | G23: =VLOOKUP(F23,$B:$B,1,0) -> #N/A | H23: =VLOOKUP(F23,$J:$J,1,0) -> #N/A | J23: a.mohapatra@niser.ac.in | K23: =VLOOKUP(J23,$B:$B,1,0) -> a.mohapatra@niser.ac.in | L23: =VLOOKUP(J23,$F:$F,1,0) -> #N/A
A24: Mithilesh Kumar PARIT | B24: mithilesh_25ps76@iitp.ac.in | C24: Student | F24: msrrao@iitm.ac.in | G24: =VLOOKUP(F24,$B:$B,1,0) -> msrrao@iitm.ac.in | H24: =VLOOKUP(F24,$J:$J,1,0) -> #N/A | K24: =VLOOKUP(J24,$B:$B,1,0) -> #N/A | L24: =VLOOKUP(J24,$F:$F,1,0) -> #N/A
A25: Rakesh Pradhan | B25: rakesh.25phz0003@iitrpr.ac.in | C25: Student | F25: ep23b052@smail.iitm.ac.in | G25: =VLOOKUP(F25,$B:$B,1,0) -> #N/A | H25: =VLOOKUP(F25,$J:$J,1,0) -> #N/A | J25: akshait@iisc.ac.in | K25: =VLOOKUP(J25,$B:$B,1,0) -> #N/A | L25: =VLOOKUP(J25,$F:$F,1,0) -> #N/A
A26: Ravindra Barlingay | B26: ceo@samgnya.in | C26: CEO | F26: Ikram@ismobiophotonics.com | G26: =VLOOKUP(F26,$B:$B,1,0) -> #N/A | H26: =VLOOKUP(F26,$J:$J,1,0) -> #N/A | J26: vaibhavas@iisc.ac.in | K26: =VLOOKUP(J26,$B:$B,1,0) -> #N/A | L26: =VLOOKUP(J26,$F:$F,1,0) -> #N/A
A27: Kiran Shesh | B27: ceo@qmettech.com | C27: CEO | G27: =VLOOKUP(F27,$B:$B,1,0) -> #N/A | H27: =VLOOKUP(F27,$J:$J,1,0) -> #N/A | J27: shahnoorali1989@gmail.com | K27: =VLOOKUP(J27,$B:$B,1,0) -> #N/A | L27: =VLOOKUP(J27,$F:$F,1,0) -> #N/A
A28: Dr. Venkateswaran PS | B28: venkatps@qcinnovation.co.in | C28: COO | F28: johnj.tifr@gmail.com | G28: =VLOOKUP(F28,$B:$B,1,0) -> #N/A | H28: =VLOOKUP(F28,$J:$J,1,0) -> #N/A | J28: dr.satishseth@iisermohali.ac.in | K28: =VLOOKUP(J28,$B:$B,1,0) -> #N/A | L28: =VLOOKUP(J28,$F:$F,1,0) -> #N/A
A29: Kunj Tandon | B29: kunjtandon@quantech.org.in | C29: CEO | F29: roopaj@iisc.ac.in | G29: =VLOOKUP(F29,$B:$B,1,0) -> #N/A | H29: =VLOOKUP(F29,$J:$J,1,0) -> #N/A | J29: ee19d021@smail.iitm.ac.in | K29: =VLOOKUP(J29,$B:$B,1,0) -> #N/A | L29: =VLOOKUP(J29,$F:$F,1,0) -> ee19d021@smail.iitm.ac.in
A30: Aditya SG Vyas | B30: ceo@qmdhub.co.in | C30: CEO | F30: shouvik@qubeats.com | G30: =VLOOKUP(F30,$B:$B,1,0) -> #N/A | H30: =VLOOKUP(F30,$J:$J,1,0) -> #N/A | J30: baratamsaitarun@gmail.com | K30: =VLOOKUP(J30,$B:$B,1,0) -> #N/A | L30: =VLOOKUP(J30,$F:$F,1,0) -> #N/A
A31: Dr. Tejas Naik | B31: tejasnaikr@gmail.com | C31: Hub Staff | F31: rsingh@physics.iitd.ac.in | G31: =VLOOKUP(F31,$B:$B,1,0) -> #N/A | H31: =VLOOKUP(F31,$J:$J,1,0) -> #N/A | K31: =VLOOKUP(J31,$B:$B,1,0) -> #N/A | L31: =VLOOKUP(J31,$F:$F,1,0) -> #N/A
A32: Vijay A Ramanujan | B32: vijay@qcinnovation.co.in | C32: CEO | F32: slodha@iitb.ac.in | G32: =VLOOKUP(F32,$B:$B,1,0) -> #N/A | H32: =VLOOKUP(F32,$J:$J,1,0) -> #N/A | J32: rakeshd24@iitk.ac.in | K32: =VLOOKUP(J32,$B:$B,1,0) -> #N/A | L32: =VLOOKUP(J32,$F:$F,1,0) -> #N/A
A33: Ramya Raman | B33: ramya@samgnya.in | C33: Hub Staff | F33: ashish.arora@iiserpune.ac.in | G33: =VLOOKUP(F33,$B:$B,1,0) -> ashish.arora@iiserpune.ac.in | H33: =VLOOKUP(F33,$J:$J,1,0) -> #N/A | K33: =VLOOKUP(J33,$B:$B,1,0) -> #N/A | L33: =VLOOKUP(J33,$F:$F,1,0) -> #N/A
A34: Venkata Sudhakar Guduru | B34: sudhakar@samgnya.in | C34: Hub Staff | F34: skvarshney@ece.iitkgp.ac.in | G34: =VLOOKUP(F34,$B:$B,1,0) -> skvarshney@ece.iitkgp.ac.in | H34: =VLOOKUP(F34,$J:$J,1,0) -> #N/A | K34: =VLOOKUP(J34,$B:$B,1,0) -> #N/A | L34: =VLOOKUP(J34,$F:$F,1,0) -> #N/A
A35: Nahid Chaudhary | B35: technologymanager2@qmdhub.co.in | C35: Hub Staff | F35: umakant.rapol@iiserpune.ac.in | G35: =VLOOKUP(F35,$B:$B,1,0) -> umakant.rapol@iiserpune.ac.in | H35: =VLOOKUP(F35,$J:$J,1,0) -> umakant.rapol@iiserpune.ac.in | K35: =VLOOKUP(J35,$B:$B,1,0) -> #N/A | L35: =VLOOKUP(J35,$F:$F,1,0) -> #N/A
A36: Sourav Sarkar | B36: projectconsultant1@qmdhub.co.in | C36: Hub Staff | F36: deepesh.sharma@ee.iitd.ac.in | G36: =VLOOKUP(F36,$B:$B,1,0) -> #N/A | H36: =VLOOKUP(F36,$J:$J,1,0) -> deepesh.sharma@ee.iitd.ac.in | J36: sangeet.ph@sric.iitr.ac.in | K36: =VLOOKUP(J36,$B:$B,1,0) -> #N/A | L36: =VLOOKUP(J36,$F:$F,1,0) -> #N/A
A37: Dr. Jagrati Dwivedi | B37: projectconsultant2@qmdhub.co.in | C37: Hub Staff | F37: 204120010@iitb.ac.in | G37: =VLOOKUP(F37,$B:$B,1,0) -> #N/A | H37: =VLOOKUP(F37,$J:$J,1,0) -> #N/A | J37: pawan.ece@sric.iitr.ac.in | K37: =VLOOKUP(J37,$B:$B,1,0) -> #N/A | L37: =VLOOKUP(J37,$F:$F,1,0) -> #N/A
A38: James Johnson | B38: james_j@quantech.org.in | C38: Hub Staff | F38: soumyaasokan@iisc.ac.in | G38: =VLOOKUP(F38,$B:$B,1,0) -> #N/A | H38: =VLOOKUP(F38,$J:$J,1,0) -> #N/A | J38: amrita.majumder@iitb.ac.in | K38: =VLOOKUP(J38,$B:$B,1,0) -> #N/A | L38: =VLOOKUP(J38,$F:$F,1,0) -> #N/A
A39: Rajan Kumar Singh | B39: rajanks@iitk.ac.in | C39: Hub Staff | G39: =VLOOKUP(F39,$B:$B,1,0) -> #N/A | H39: =VLOOKUP(F39,$J:$J,1,0) -> #N/A
A40: Gayathri Raman | B40: g3raman@iitb.ac.in | C40: Hub Staff
A41: Maheshwar Mangat | B41: maheshwar.mangat@iitb.ac.in | C41: IITB Staff
A42: RAMSHANKER | B42: ramshanker@qcinnovation.co.in | H42: =VLOOKUP(F42,$J:$J,1,0) -> #N/A
A43: Dr. Akshay Naik | B43: anaik@iisc.ac.in | C43: Professor | F43: pavkalyan100@gmail.com | G43: =VLOOKUP(F43,$B:$B,1,0) -> #N/A | H43: =VLOOKUP(F43,$J:$J,1,0) -> #N/A
A44: Dr. Akshay Singh | B44: aksy@iisc.ac.in | C44: Professor | F44: suhas.kulkarni@scicomsoftware.com | G44: =VLOOKUP(F44,$B:$B,1,0) -> #N/A | H44: =VLOOKUP(F44,$J:$J,1,0) -> #N/A
A45: Dr. Amitangshu Pal | B45: amitangshu@cse.iitk.ac.in | C45: Professor | F45: shubhamutreja77@gmail.com | G45: =VLOOKUP(F45,$B:$B,1,0) -> #N/A | H45: =VLOOKUP(F45,$J:$J,1,0) -> #N/A
A46: Dr. Anil Shaji | B46: shaji@iisertvm.ac.in | C46: Professor | G46: =VLOOKUP(F46,$B:$B,1,0) -> #N/A | H46: =VLOOKUP(F46,$J:$J,1,0) -> #N/A
A47: Dr. Anirban Mitra | B47: anirban.mitra@ph.iitr.ac.in | C47: Professor | F47: Firoz.t@qpiai.tech | G47: =VLOOKUP(F47,$B:$B,1,0) -> #N/A | H47: =VLOOKUP(F47,$J:$J,1,0) -> #N/A
A48: Dr. Ankur Raina | B48: ankur@iiserb.ac.in | C48: Professor | F48: s21027@students.iitmandi.ac.in | G48: =VLOOKUP(F48,$B:$B,1,0) -> #N/A | H48: =VLOOKUP(F48,$J:$J,1,0) -> #N/A
A49: Dr. Anshul Jaiswal | B49: anshul.jaiswal@ece.iitr.ac.in | C49: Professor | F49: sanjay@thequantum.ai | G49: =VLOOKUP(F49,$B:$B,1,0) -> #N/A | H49: =VLOOKUP(F49,$J:$J,1,0) -> #N/A
A50: Dr. Anshuman Kumar | B50: anshuman.kumar@iitb.ac. in | C50: Professor | F50: ee19d021@smail.iitm.ac.in | G50: =VLOOKUP(F50,$B:$B,1,0) -> #N/A | H50: =VLOOKUP(F50,$J:$J,1,0) -> ee19d021@smail.iitm.ac.in
A51: Dr. Arijit Sharma | B51: arijit@iittp.ac.in | C51: Professor | G51: =VLOOKUP(F51,$B:$B,1,0) -> #N/A | H51: =VLOOKUP(F51,$J:$J,1,0) -> #N/A
A52: Dr. Ashok K Mohapatra | B52: a.mohapatra@niser.ac.in | C52: Professor | G52: =VLOOKUP(F52,$B:$B,1,0) -> #N/A | H52: =VLOOKUP(F52,$J:$J,1,0) -> #N/A
A53: Dr. Awanish Pandey | B53: awanish@ee.iitd.ac.in | C53: Professor | F53: phz228454@iitd.ac.in | G53: =VLOOKUP(F53,$B:$B,1,0) -> #N/A | H53: =VLOOKUP(F53,$J:$J,1,0) -> phz228454@iitd.ac.in
A54: Dr. Baladitya Suri | B54: surib@iisc.ac.in | C54: Professor | F54: snehal@synergyquantum.in | G54: =VLOOKUP(F54,$B:$B,1,0) -> #N/A | H54: =VLOOKUP(F54,$J:$J,1,0) -> #N/A
A55: Dr. Bhaskar Kanseri | B55: bkanseri@physics.iitd.ac.in | C55: Professor | F55: pmohta@iitk.ac.in | G55: =VLOOKUP(F55,$B:$B,1,0) -> #N/A | H55: =VLOOKUP(F55,$J:$J,1,0) -> pmohta@iitk.ac.in
A56: Dr. Bimalendu Deb | B56: msbd@iacs.res.in | C56: Professor | F56: shishir.dasika@qmettech.com | G56: =VLOOKUP(F56,$B:$B,1,0) -> #N/A | H56: =VLOOKUP(F56,$J:$J,1,0) -> #N/A
A57: Dr. D. S. Rawal | B57: ds-rawal.sspl@gov.in | C57: Professor | F57: abhijeet.ghodgaonkar@qmettech.com | G57: =VLOOKUP(F57,$B:$B,1,0) -> #N/A | H57: =VLOOKUP(F57,$J:$J,1,0) -> #N/A
A58: Dr. Debapriya Basu Roy | B58: dbroy@cse.iitk.ac.in | C58: Professor | F58: abhijeet.ghodgaonkar@qmettech.com | G58: =VLOOKUP(F58,$B:$B,1,0) -> #N/A | H58: =VLOOKUP(F58,$J:$J,1,0) -> #N/A
A59: Dr. Debdeep Mukhopadhyay | B59: debdeep@cse.iitkgp.ac.in | C59: Professor | G59: =VLOOKUP(F59,$B:$B,1,0) -> #N/A | H59: =VLOOKUP(F59,$J:$J,1,0) -> #N/A
A60: Dr. Dhiman Saha | B60: dhiman@iitbhilai.ac.in | C60: Professor | F60: ep22b019@smail.iitm.ac.in | G60: =VLOOKUP(F60,$B:$B,1,0) -> #N/A | H60: =VLOOKUP(F60,$J:$J,1,0) -> #N/A
A61: Dr. G Rajalakshmi | B61: raji@tifrh.res.in | C61: Professor | F61: p.hegde@physics.iitm.ac.in | G61: =VLOOKUP(F61,$B:$B,1,0) -> #N/A | H61: =VLOOKUP(F61,$J:$J,1,0) -> #N/A
A62: Dr. Girish Vasant Kulkarni | B62: girishk@iitrpr.ac.in | C62: Professor | G62: =VLOOKUP(F62,$B:$B,1,0) -> #N/A | H62: =VLOOKUP(F62,$J:$J,1,0) -> #N/A
A63: Dr. Kanhaiya Pandey | B63: kanhaiyapandey@iitg.ac.in | C63: Professor | F63: poojagunjal1212@gmail.com | G63: =VLOOKUP(F63,$B:$B,1,0) -> #N/A | H63: =VLOOKUP(F63,$J:$J,1,0) -> #N/A
A64: Dr. Kasturi Saha | B64: pic@qmettech.com | C64: Professor | F64: purnapal@iisc.ac.in | G64: =VLOOKUP(F64,$B:$B,1,0) -> #N/A | H64: =VLOOKUP(F64,$J:$J,1,0) -> #N/A
A65: Dr. Madhu Thalakulam | B65: madhu@iisertvm.ac.in | C65: Professor | F65: pritam@qubeats.com | G65: =VLOOKUP(F65,$B:$B,1,0) -> #N/A | H65: =VLOOKUP(F65,$J:$J,1,0) -> #N/A
A66: Dr. Mrigank Sharad | B66: mrigank@see.iitkgp.ac.in | C66: Professor | F66: samareshdas@care.iitd.ac.in | G66: =VLOOKUP(F66,$B:$B,1,0) -> #N/A | H66: =VLOOKUP(F66,$J:$J,1,0) -> #N/A
A67: Dr. Natarajan Venkatachalam | B67: natarajan@setsindia.net | C67: Professor | F67: anshuman.kumar@iitb.ac.in | G67: =VLOOKUP(F67,$B:$B,1,0) -> #N/A | H67: =VLOOKUP(F67,$J:$J,1,0) -> #N/A
A68: Dr. Neel Kanth Kundu | B68: neelkanth@iitd.ac.in | C68: Professor | G68: =VLOOKUP(F68,$B:$B,1,0) -> #N/A | H68: =VLOOKUP(F68,$J:$J,1,0) -> #N/A
A69: Dr. Parvendra Kumar | B69: parvendra@opc.iitd.ac.in | C69: Professor | F69: rajesh.kumar@ph.iitr.ac.in | G69: =VLOOKUP(F69,$B:$B,1,0) -> #N/A | H69: =VLOOKUP(F69,$J:$J,1,0) -> #N/A
A70: Dr. Phani Kumar Peddibhotla | B70: phani@iiserb.ac.in | C70: Professor
A71: Dr. Prabha Mandayam | B71: prabhamd@physics.iitm.ac.in | C71: Professor
A72: Dr. Prasana Kumar Sahoo | B72: prasana@matsc.iitkgp.ac.in | C72: Professor
A73: Dr. Prosenjit Sen | B73: prosenjits@iisc.ac.in | C73: Professor
A74: Dr. Raghavan K Easwaran | B74: raghavanke@iitp.ac.in | C74: Professor
A75: Dr. Rahul Singh | B75: rahuls_ee@iitb.ac.in | C75: Professor
A76: Dr. Rajamani Vijayaraghavan | B76: rvijay26@gmail.com | C76: Professor
A77: Dr. Rajesh Kumar | B77: rajesh.kumar@bt.iitr.ac.in | C77: Professor
A78: Dr. Rakesh Kumar Palani | B78: palanirakesh@gmail.com | C78: Professor
A79: Dr. Rejish Nath Gopinathan Rejani | B79: rejish@iiserpune.ac.in | C79: Professor
A80: Dr. Rituraj | B80: rituraj@iitk.ac.in | C80: Professor
A81: Dr. Rohit Chaurasiya | B81: rohit.chaurasiya@iitjammu.ac.in | C81: Professor
... A149: MS Ramchandra Rao | B149: msrrao@iitm.ac.in | C149: Professor

Sheet Student list
A1: Name | B1: Name of the Hub/Institution | C1: Email ID | D1: Hub | E1: PI Name
A2: Ritik Jain | B2: IISER Bhopal | D2: IIT Madras | E2: Dr. Ankur raina | G2: =VLOOKUP(A2, 'Student list'!G2:G23, 1, FALSE) -> 0 | H2: =VLOOKUP(A2, 'Student list'!I2:I23, 1, FALSE) -> #N/A
A3: Sourabh Jain | B3: Indian Institute of Science Education and Research, Pune | D3: IIT Delhi | E3: Dr. Ashish Arora | G3: =VLOOKUP(A3, 'Student list'!G3:G24, 1, FALSE) -> 0 | H3: =VLOOKUP(A3, 'Student list'!I3:I24, 1, FALSE) -> #N/A
A4: Vinod Kumar | B4: IISER Pune | D4: IIT Delhi | E4: Dr. Ashish Arora | G4: =VLOOKUP(A4, 'Student list'!G4:G25, 1, FALSE) -> 0 | H4: =VLOOKUP(A4, 'Student list'!I4:I25, 1, FALSE) -> #N/A
A5: Aparna Shinde | B5: IISER Pune | D5: IIT Delhi | E5: Dr. Ashish Arora | G5: =VLOOKUP(A5, 'Student list'!G5:G26, 1, FALSE) -> 0 | H5: =VLOOKUP(A5, 'Student list'!I5:I26, 1, FALSE) -> #N/A
A6: Soorya S | B6: IISER Bhopal | D6: IIT Madras | E6: Dr. Ankur raina | G6: =VLOOKUP(A6, 'Student list'!G6:G27, 1, FALSE) -> 0 | H6: =VLOOKUP(A6, 'Student list'!I6:I27, 1, FALSE) -> #N/A
A7: Chayan Purkait | B7: Indian Association for the Cultivation of Science | D7: IIT Bombay | E7: Prof. Bimalendu deb | G7: =VLOOKUP(A7, 'Student list'!G7:G28, 1, FALSE) -> 0 | H7: =VLOOKUP(A7, 'Student list'!I7:I28, 1, FALSE) -> #N/A
A8: Dhairya Bhandari | B8: IISER, Pune | D8: QMD IIT DELHI | E8: Dr. Ashish Arora | G8: =VLOOKUP(A8, 'Student list'!G8:G29, 1, FALSE) -> 0 | H8: =VLOOKUP(A8, 'Student list'!I8:I29, 1, FALSE) -> #N/A
A9: Sunny Bajaj | B9: IIT Ropar | D9: IIT Bombay | E9: Dr. Vishwapal | G9: =VLOOKUP(A9, 'Student list'!G9:G30, 1, FALSE) -> 0 | H9: =VLOOKUP(A9, 'Student list'!I9:I30, 1, FALSE) -> #N/A
A10: Raja Mondal | B10: IIT Ropar | D10: IIT Bombay | E10: Dr. Vishwapal | G10: =VLOOKUP(A10, 'Student list'!G10:G31, 1, FALSE) -> 0 | H10: =VLOOKUP(A10, 'Student list'!I10:I31, 1, FALSE) -> #N/A
A11: Neethu K | B11: IIT Ropar | D11: IIT Bombay | E11: Dr. Vishwapal | G11: =VLOOKUP(A11, 'Student list'!G11:G32, 1, FALSE) -> 0 | H11: =VLOOKUP(A11, 'Student list'!I11:I32, 1, FALSE) -> #N/A
A12: Hrdya Joshi | B12: Tata Institute of Fundamental Research | D12: IIT Bombay | E12: Dr. Sourav dutta | G12: =VLOOKUP(A12, 'Student list'!G12:G33, 1, FALSE) -> 0 | H12: =VLOOKUP(A12, 'Student list'!I12:I33, 1, FALSE) -> #N/A
A13: Rahul Mohanty | B13: Tata Institute of Fundamental Research | D13: IIT Bombay | E13: Dr. Sourav dutta | G13: =VLOOKUP(A13, 'Student list'!G13:G34, 1, FALSE) -> 0 | H13: =VLOOKUP(A13, 'Student list'!I13:I34, 1, FALSE) -> #N/A
... A20: Anupam Patra | B20: TCG Crest | D20: IIT Bombay | E20: Dr. Tanmoy basu | G20: =VLOOKUP(A20, 'Student list'!G20:G41, 1, FALSE) -> 0 | H20: =VLOOKUP(A20, 'Student list'!I20:I41, 1, FALSE) -> #N/A
A21: Dr. Pawan Kumar | B21: QMD Foundation at IIT Delhi | C21: kumarpawan.ece@gmail.com | D21: IIT Delhi | E21: Prof. Rajendra Singh | G21: =VLOOKUP(A21, 'Student list'!G21:G43, 1, FALSE) -> 0 | H21: =VLOOKUP(A21, 'Student list'!I21:I43, 1, FALSE) -> #N/A
A22: Pawan Shukla | B22: QMD Foundation at IIT Delhi | C22: pawan.ece@sric.iitr.ac.in | D22: IIT Delhi | E22: Prof. Karun Rawat | G22: =VLOOKUP(A22, 'Student list'!G22:G44, 1, FALSE) -> 0 | H22: =VLOOKUP(A22, 'Student list'!I22:I44, 1, FALSE) -> #N/A
A23: Aishwarya L | B23: TIFR Mumbai | C23: aishwarya1820@gmail.com | D23: IIT Bombay | E23: Prof. Sourav Dutta | G23: =VLOOKUP(A23, 'Student list'!G23:G46, 1, FALSE) -> 0 | H23: =VLOOKUP(A23, 'Student list'!I23:I46, 1, FALSE) -> #N/A
A24: Mithilesh Kumar PARIT | C24: mithilesh_25ps76@iitp.ac.in | D24: IIT Madras | E24: Prof. Raghavan k easwaran | G24: =VLOOKUP(A24, 'Student list'!G24:G47, 1, FALSE) -> 0 | H24: =VLOOKUP(A24, 'Student list'!I24:I47, 1, FALSE) -> #N/A
A25: Rakesh Pradhan | B25: Qmet Tech | D25: IIT Ropar | E25: Prof Girish Kulkarni

Sheet Hostel
A1: Student Name | B1: Gender | C1: Accomodation | D1: Email
A2: Pulak Ghoshal | B2: Male | C2: Hostel | D2: eez248406@ee.iitd.ac.in | E2: Male | F2: 20
A3: Deepesh Sharma | B3: Male | C3: Hostel | D3: deepesh.sharma@ee.iitd.ac.in | E3: Female | F3: 7
A4: Rajat Bharadwaj | B4: Male | C4: Hostel | D4: rajat21@iisertvm.ac.in
A5: Nishitha N | B5: Female | C5: Hostel | D5: nishithn@iisc.ac.in
A6: Sanchari Chakraborti | B6: Female | C6: Hostel | D6: sancharic@iisc.ac.in
A7: Akshai Krishnan T | B7: Male | C7: Hostel | D7: akshait@iisc.ac.in
A8: Srijita Das | B8: Female | C8: Hostel | D8: srijitadas22@gmail.com
A9: Vaibhav Anand Srivastava | B9: Male | C9: Hostel | D9: vaibhavas@iisc.ac.in
A10: Abhay Dulta | B10: Male | C10: Hostel | D10: phz228454@iitd.ac.in
A11: Shahnoor Ali | B11: Male | C11: Hostel | D11: shahnoorali1989@gmail.com
A12: Debadrita Ghosh | B12: Female | C12: Hostel | D12: debadrita@rrimail.rri.res.in
A13: Satish Kumar | B13: Male | C13: Hostel | D13: dr.satishseth@iisermohali.ac.in
A14: Anagha Gayathri | B14: Female | C14: Hostel | D14: anaghagayathri@smail.iitm.ac.in
A15: Saravana Vilashini M | B15: Female | C15: Hostel | D15: ee19d021@smail.iitm.ac.in
... A28: Amrita Majumder | B28: Female | C28: Hostel | D28: amrita.majumder@iitb.ac.in

Sheet Poster Presentation
B1: Hub | C1: TG | D1: Registration Status | E1: Poster received | F1: Title of the Poster | G1: Faculty Mentor Name | H1: Team Member 1 | I1: Email 1 | J1: Team Member 2 | K1: Email 2 | L1: 20
B2: Foundation for QC Innovation IISc Bangalore | C2: Highly Scalable Quantum Computer using Semiconducting Qubits | D2: YES | F2: TG3 Progress & Challenges | G2: Prof. Abhisek Dixit | H2: Pulak Ghoshal | I2: eez248406@ee.iitd.ac.in | J2: Deepesh Sharma | K2: deepesh.sharma@ee.iitd.ac.in
B3: Foundation for QC Innovation IISc Bangalore | C3: Development of a 50-qubit quantum information processor with electron spins in silicon | D3: YES | F3: Active Noise Reduction in Si/SiGe Gated Quantum Dot | G3: Madhu Thalakulam | H3: Rajat Bharadwaj | I3: rajat21@iisertvm.ac.in
B4: Foundation for QC Innovation IISc Bangalore | C4: Quantum Computing with Neutral Atoms, Trapped Ions and Related Hybrid Systems | D4: YES | F4: Neutral atom and trapped ion based quantum computing architecture | G4: Saptarishi Chaudhuri | H4: Umakant Rapol | I4: umakant.rapol@iiserpune.ac.in | J4: Ashok Kumar Mohapatra | K4: a.mohapatra@niser.ac.in
B5: Foundation for QC Innovation IISc Bangalore | C5: Photonics quantum processor development | D5: YES | F5: Scalable Photonic Integrated circuit based photonic quantum processor | G5: Shankar Kumar Selvaraja | H5: Nishitha N | I5: nishithn@iisc.ac.in
B6: Foundation for QC Innovation IISc Bangalore | C6: Programmable photonic quantum computing using qubits encoded in different degrees of freedom of a photon | D6: YES | E6: yes | F6: Deterministic Quantum Teleportation in a 3-Qubit Photonic System | G6: Prof. C. M. Chandrashekar | H6: Sanchari Chakraborti | I6: sancharic@iisc.ac.in | J6: Akshai Krishnan T | K6: akshait@iisc.ac.in
B7: Foundation for QC Innovation IISc Bangalore | C7: Quantum computers with superconducting qubits | D7: YES | F7: Methodologies for achieving high coherence superconducting qubits | G7: Rajamani Vijayaraghavan | H7: Srijita Das | I7: srijitadas22@gmail.com | J7: Vaibhav Anand Srivastava | K7: vaibhavas@iisc.ac.in
B8: IITM CDOT Samgnya Technologies Foundation at IIT Madras | C8: Towards Trusted-Node-Free Hybrid Quantum Secure Communication Networks - TAHQEECAT | D8: YES | E8: yes | F8: Towards Trusted node free hybrid quantum secure communication network | G8: Bhaskar Kanseri | H8: Abhay Dulta | I8: phz228454@iitd.ac.in | J8: Shahnoor Ali | K8: shahnoorali1989@gmail.com
B9: IITM CDOT Samgnya Technologies Foundation at IIT Madras | C9: A multi node quantum repeater network for entanglement distribution based quantum communication | D9: YES | E9: yes | F9: Toward a Multi-Node Quantum Repeater Network for Entanglement-Based Quantum Communication | G9: "Urbasi Sinha Aditi Sen De Arijit Sharma Raghavan Easwaran Sandeep Goyal" | H9: Debadrita Ghosh | I9: debadrita@rrimail.rri.res.in | J9: Satish Kumar | K9: dr.satishseth@iisermohali.ac.in
B10: IITM CDOT Samgnya Technologies Foundation at IIT Madras | C10: Quantum Internet with Local Access QuILA | D10: YES | E10: yes | F10: INDIA'S QUANTUM NETWORK TESTBED | G10: Anil Prabhakar | H10: Anagha Gayathri | I10: anaghagayathri@smail.iitm.ac.in | J10: Saravana Vilashini M | K10: ee19d021@smail.iitm.ac.in
B11: IITM CDOT Samgnya Technologies Foundation at IIT Madras | C11: Post-quantum IP encryptor and TLS Accelerator | D11: YES | E11: yes | F11: Hardware Acceleration of Post-Quantum TLS: A Unified Kyber–Dilithium ASIC | G11: Debdeep Mukhopadhyay | H11: Siddhartha Chowdhury | I11: siddhartha.chowdhury92@gmail.com | J11: Sai Tarun Baratam | K11: baratamsaitarun@gmail.com
B12: IITM CDOT Samgnya Technologies Foundation at IIT Madras | C12: Satellite Based Quantum Key Distribution Systems
B13: Qmet Tech Foundation at IIT Bombay | C13: Field-deployable quantum-enhanced sensors on integrated hybrid platform | D13: YES | F13: Magnetic Anomaly Detection | G13: "Dr Saikat Ghosh Dr Amitangshu Pal" | H13: Kamal Kant Tripathi | I13: kamalt24@iitk.ac.in | J13: Rakesh Dash | K13: rakeshd24@iitk.ac.in
B14: Qmet Tech Foundation at IIT Bombay | C14: Design and development of quantum entanglement-enhanced imaging systems | D14: YES | E14: yes | F14: Noise-resilient imaging through coherence filtering | G14: Prof. Anand Kumar Jha | H14: Pranay Mohta | I14: pmohta@iitk.ac.in
B15: Qmet Tech Foundation at IIT Bombay | C15: Diamond quantum defects-based sensing | D15: YES | E15: yes | F15: Magnetically Maneuvered Quantum Sensors | G15: Ambarish Ghosh | H15: Eklavy Vashist | I15: eklavy.vashist@qmettech.com
C16: Diamond quantum defects-based sensing | F16: Diamond quantum sensors for nano-magnetometry | G16: Phani Kumar | H16: Pralekh Dubey | I16: dpralekh@iiserb.ac.in
B17: QMD Foundation at IIT Delhi | C17: Reconfigurable and Scalable Photonic Qubit Architecture for Quantum Computing Heterogeneous and Monolithic Approaches RASPAC | D17: YES | E17: yes | F17: Reconfigurable and Scalable Photonic Qubit Architecture for Quantum Computing Heterogeneous and Monolithic Approaches RASPAC | G17: Shailendra Kumar Varshney, Prasana Kumar Sahoo, Mrigank Sharad, Anshuman Kumar, Rajesh Kumar, Anirban Mitra, Rajan Jha | H17: Pratyush Biswas | I17: pratyushrajbiswas@gmail.com | J17: Sangeet Rathi | K17: sangeet.ph@sric.iitr.ac.in
B18: QMD Foundation at IIT Delhi | C18: Development of On-Demand Single Photon Emitters, Single Photon Avalanche Detectors, High-Frequency Devices and Nanowire Quantum Devices Utilizing GaAs and InP-Based Epitaxial Semiconductors | D18: YES | E18: yes | F18: Development of On-Demand Single Photon Emitters, Single Photon Avalanche Detectors, High-Frequency Devices and InP-Based Epitaxial Semiconductors | G18: "Prof. Rajendra Singh Prof. Samaresh Das Prof. Dibyajyoti Ghosh Prof. Karun Rawat Prof. Swaroop Ganguly Prof. Dipankar Saha" | H18: Dr. Pawan Kumar | I18: kumarpawan.ece@gmail.com | J18: Dr. Pawan Kumar Shukla | K18: pawan.ece@sric.iitr.ac.in
B19: QMD Foundation at IIT Delhi | C19: Wafer-scale Emitter and Detector Arrays for Multi-wavelength Room Temperature Photonic Quantum Technologies | D19: YES | E19: yes | F19: TG2: Wafer-scale Emitter and Detector Arrays for Multi-wavelength Room Temperature Photonic Quantum Technologies | G19: "1. Prof. Saurabh Lodha, IIT Bombay 2. Prof. Anshuman Kumar, IIT Bombay 3. Prof. Tanushree H. Choudhury, IIT Bombay 4. Prof. Ashish Arora, IISER Pune" | H19: Subham Mahanti | I19: mahanti.subham25@gmail.com | J19: Amrita Majumder | K19: amrita.majumder@iitb.ac.in

Sheet Expo
A1: Sr. no. | B1: Name of the Hub | C1: Name on the Fascia | D1: Team Member 1 Name - First Name | E1: Team Member 1 Name - Last Name | F1: Gender | G1: Email Address | H1: Phone Number | I1: Team Member 2 Name - First Name | J1: Team Member 2 Name - Last Name | K1: Gender | L1: Email Address | M1: Phone Number | N1: Upload Product/Technology Image (300 dpi) | O1: Technology Focus | P1: Power Requirements | Q1: Brief Description of Your Startup and Product (in 200 words)
A2: 1 | B2: Foundation for QC Innovation IISc Bangalore | C2: Neutral atom and trapped ion quantum computer | D2: Saptarishi | E2: Chaudhuri | F2: Male | G2: srishic@rri.res.in | H2: (+91) 7259899430 | I2: Umakant | J2: Rapol | K2: Male | L2: umakant.rapol@iiserpune.ac.in | M2: (+91) 9689908421 | N2: https://www.jotform.com/uploads/Qmet/260672027148052/6494586702916808495/Display.png | O2: Atom and ion based quantum computing | P2: 2 | Q2: Our technology consortium focuses on indigenously developing neutral atom and trapped ion based quantum computing platform. While two cloud accessible system will soon be operational and work towards demonstration of the technology readiness is ongoing, we also intend to productise both the full stack system as well as many peripheral components. During the AQC, there will be one 3D scaled down display unit of the actual set-up hosted at RRI + components developed at IISER Pune, NISER Bhubaneswar and IIT Roorkee and IIT Guwahati.
A3: 2 | B3: Foundation for QC Innovation IISc Bangalore | C3: A Highly Scalable Quantum Computer using Silicon Qubits (sharing) | D3: Pulak (also part of poster) | E3: Ghoshal | F3: Male | G3: eez248406@ee.iitd.ac.in | H3: (+91) 7290804546 | I3: Deepesh (also part of poster) | J3: Sharma | K3: Male | L3: deepesh.sharma@ee.iitd.ac.in | M3: (+91) 9858911301 | N3: https://www.jotform.com/uploads/Qmet/260672027148052/6495553635606105708/TG3-IITD-Quantum-Computer-Schematic.jpg | O3: Quantum Computing | P3: 3 X 220V | Q3: To achieve a beyond NISQ (>1000 qubits) quantum computer, high density qubits, passives, and wiring are essential. Silicon CMOS process has the optimum BEOL for such work. With minor tweaks in standard CMOS, a derivative process for fabrication of quantum dot-based qubits can be created, and an all-Silicon Quantum Computer can be realized. In this Technical Group (TG3), we are developing the system at all levels, starting from system-level and then going down to the chip and qubit levels. Our mission objective is to demonstrate a working quantum computer with 50 qubits. | R3: To be merged with Cryogenic electronics for spin qubits
A4: 3 | B4: Foundation for QC Innovation IISc Bangalore | C4: Control & Measurement Electronics for Superconducting Qubits | D4: Shantharam | E4: Kalipatnapu | F4: Male | G4: shantharamk@iisc.ac.in | H4: (+91) 8972246283 | I4: Venkata Pavan Kalyan | J4: Missula | K4: Male | L4: pavkalyan100@gmail.com | M4: (+91) 7294874910 | N4: https://www.jotform.com/uploads/Qmet/260672027148052/6495812735188358844/ConElec-SuperCQ.jpg | O4: Superconducting Qubits | P4: 4 / 220V | Q4: We will display prototypes of FPGA based control & measurement electronics, cryogenic filters , and Josephson Parametric Amplifiers
A5: 4 | B5: Foundation for QC Innovation IISc Bangalore | C5: 6 qubit photonic system (sharing) | D5: Sujai | E5: Matta | F5: Male | G5: sujaimatta@iisc.ac.in | H5: (+91) 9491238120 | I5: Soumya | J5: Asokan | K5: Female | L5: soumyaasokan@iisc.ac.in | M5: (+91) 9567246448 | N5: https://www.jotform.com/uploads/Qmet/260672027148052/6496277264281228497/6qubit-QC.png | O5: Photonic Quantum Computing | P5: 4 socket, 10Amp 240V | Q5: It's a device developed at Photonic Quantum Computing TG at IISc. A 6-qubit photonic system with provision for implementing 4 two-qubit gates, 4 single-qubit gates, and generating a 6-qubit maximally entangled state. Image is a representation; it will be packaged.
A6: 5 | B6: Foundation for QC Innovation IISc Bangalore | C6: Cryogenic Electronics for Spin qubits (sharing) | D6: Rajat (also part of poster) | E6: Bharadwaj | F6: Male | G6: rajat21@iisertvm.ac.in | H6: (+91) 9933832246 | I6: Varsha | J6: Jangir | K6: Female | L6: 204120010@iitb.ac.in | N6: https://www.jotform.com/uploads/Qmet/260672027148052/6496502828185510048/nqm%20sub-low_8300.png | O6: Silicon Quantum Dot Spin Qubits | P6: NA | Q6: A suite of advanced cryogenic and qubit-control devices designed to ensure high-fidelity signal integrity and effective noise suppression in quantum experiments. The Cryo Damp-24 is a 24-channel low-pass filter based on a copper powder-epoxy composite, offering a cut-off frequency of 300 MHz for efficient attenuation of high-frequency noise. The μ Shield-12 incorporates 12 isolated DC lines in a compact module, providing comparable filtering performance with enhanced isolation. The San Noise-25 device features a finite ground coplanar waveguide fabricated on sapphire with aluminium, enabling superior thermalization and achieving a cut-off frequency below 100 kHz. Complementing these, the Cryo Pass-L24 is a fully customizable, modular 24-channel cryogenic low-pass filter. For qubit control, the Q-Nest provides a modular PCB system enclosed within a shielding enclosure, supporting 24 DC lines, 8 ohmic lines, and integrated passive filtering. Finally, the Q-CARD-24080601 is a versatile qubit control and readout platform incorporating DC, ohmic, RF, and readout lines, along with environmental shielding, LED integration, and ESD protection mechanisms for robust and reliable operation.
A7: 6 | B7: Foundation for QC Innovation IISc Bangalore | C7: Photonics Quantum Processor 9(sharing) | D7: Shankar Kumar | E7: Selvaraja | F7: Male | G7: shankraks@iisc.ac.in | H7: (91) 9481283513 | N7: https://www.jotform.com/uploads/Qmet/260672027148052/6502142416158167143/Picture1.png | O7: Photonics quantum processor | P7: No | Q7: Display of a model of a photonics quantum processor, Wafer display with photonic circuit, single photon emitter chip and testing jig display. | R7: 6.5021424e+18
A9: 1 | B9: I-Hub QTF, IISER Pune | C9: SCI-COM SOFTWARE INDIA PRIVATE LIMITED | D9: Vaishnavi | E9: Vaichal | F9: Female | G9: vaishnavi.vaichal@scicomsoftware.com | H9: (+91) 7768074457 | I9: Suhas | J9: Kulkarni | K9: Male | L9: suhas.kulkarni@scicomsoftware.com | M9: (+91) 9403768214 | N9: https://www.jotform.com/uploads/Qmet/260672027148052/6495522526427438722/IMG_1743.JPEG | O9: Instrumentation and Control for Quantum Technology Research and Development | P9: 4 | Q9: SCI-COM was founded in 1998 and has been working in areas such as signal and image processing, high-speed FPGA electronics, Digital Signal Processing and microcontroller-based boards, RF modules, power distribution modules (industrial and MIL-grade), software development, and embedded systems. We also provide independent verification and validation services for DRDO and other PSUs. iQUANTROL-1.0 is an Instrumentation and Control Unit to be used in Laboratory Setups for Quantum Technology Research and Development. This unit provides a host computer based GUI Application to configure different Instrumentation and Control parameters required by the Laboratory Setup. It has a high performance electronics platform interfaced over ethernet with the host PC to perform real time functions such as high speed signal generation, high speed signal sampling/acquisition, signal processing for signal features estimation, control loops implementation through embedded software and diagnostics/log reports.
A10: 2 | B10: I-Hub QTF, IISER Pune | C10: Prenishq | D10: Bodhaditya | E10: Santra | F10: Male | G10: bodhaditya.santra@gmail.com | H10: (+91) 7047373599 | I10: Shubham | J10: Utreja | K10: Male | L10: shubhamutreja77@gmail.com | M10: (+91) 9829825823 | N10: https://www.jotform.com/uploads/Qmet/260672027148052/6495799308513351203/Prenishq%20Laser%20Launch%20flyer%20revised.pdf | O10: High precision diode laser for quantum computing, sensing, metrology and communication | P10: 4 | Q10: Prenishq Pvt. Ltd., a spin-off from IIT Delhi and supported by the National Quantum Mission manufactures high precision diode lasers for quantum computing, sensing, metrology and communication. The Prenishq Opal Laser is a high-performance, precision-engineered system designed for quantum research, education, and advanced experiments. With exceptional beam quality, stability, and long-term durability, it’s ideal for seamless integration into scientific and quantum equipment. These lasers stand out for its low cost of ownership, ease of installation, minimal maintenance, light weight, and assured availability to promise. Combining performance, efficiency, and accessibility, Prenishq’s lasers position India at the forefront of laser technology and quantum innovation.
A11: 3 | B11: I-Hub QTF, IISER Pune | C11: QpiAI India Private Limited | D11: Vamsi | E11: Krishna | F11: Male | G11: vamsi.k@qpiai.tech | H11: (91) 7895873873 | I11: Firoz | J11: Tahashildar | K11: Male | L11: Firoz.t@qpiai.tech | M11: () 7353155091 | N11: https://www.jotform.com/uploads/Qmet/260672027148052/6500608394918164434/IMG_1064%20%281%29.jpeg | O11: Quantum error correction | P11: 2 sockets 220v | Q11: QpiAI QEC is developed to enhance qubit reliability and system performance. Using advanced algorithms , it detects and corrects errors in real time, improving fidelity and extending coherence time of physical qubits. The system implements a distance-5 rotated surface code using 49 physical qubits. Each decoder instance runs on a single QpiAI Kaveri QPU, which provides 64 qubits, allowing one decoder instance per chip. The architecture is optimized to support efficient decoding and integration with existing quantum hardware. | R11: 6.5006084e+18
A12: 4 | B12: I-Hub QTF, IISER Pune | C12: QuNu Labs Private Limited | D12: Sunil | E12: Gupta | F12: Male | G12: sunil@qnulabs.com | H12: (+91) 7899791155 | N12: https://www.jotform.com/uploads/Qmet/260672027148052/6496353206325463976/QNu%20Product.png | O12: Quantum Communication | P12: 2 | Q12: QNu Labs is India’s pioneering quantum cybersecurity company focused on building technologies that protect digital infrastructure from future quantum computing threats. Founded in 2016 and incubated at IIT Madras Research Park, the company’s mission is to make India self-reliant in digital security while enabling a global transition toward quantum-safe communication. As quantum computing advances, today’s encryption methods such as RSA and ECC will become vulnerable, posing serious risks to governments, financial systems, telecom networks, and critical infrastructure. QNu Labs addresses this challenge through an indigenous ecosystem of quantum-safe technologies that combine hardware and software innovations. Its portfolio includes Armos (Quantum Key Distribution), Tropos (Quantum Random Number Generator), the QShield crypto-agile security platform, and quantum communication chips for secure edge systems. QNu’s hybrid architecture integrates quantum physics-based security with post-quantum cryptography, enabling organizations to transition to quantum-safe infrastructure without replacing existing systems. These solutions secure communications, data, and identity across sectors such as defence, telecom, banking, and government. With multiple patents, defence validations, and real-world deployments—including long-distance quantum networks—QNu Labs is positioning India at the forefront of the emerging quantum security era, enabling governments and enterprises to achieve digital sovereignty, long-term data protection, and resilient cybersecurity for the post-quantum world.
A13: 5 | B13: I-Hub QTF, IISER Pune | C13: Quanastra Pvt Ltd | D13: Vidur | E13: Raj | F13: Male | G13: vidur.raj@quanastra.com | H13: (+91) 9205771590 | I13: Anand | J13: Mohan | K13: Male | L13: s21027@students.iitmandi.ac.in | M13: (+91) 7678310811 | N13: https://www.jotform.com/uploads/Qmet/260672027148052/6495604869251620860/Picture1.png | O13: Quantum Sensing | P13: 2 | Q13: Quanastra is a deep-tech startup operating at the forefront of quantum and photonics technologies, with a long-term vision to establish itself as a hub for quantum and photonics chip manufacturing. In near term, we are developing Single photon detectors, and associated hardware under national Quantum Mission. Some of our market ready products: UHV Fiber Feedthrough, DC cryoelectronic wiring, High Precision Microampere Current. Some of these we will be showcasing at the IIT Bombay Expo. | R13: 6.4956049e+18
A15: 1 | B15: IITM CDOT Samgnya Technologies Foundation at IIT Madras | C15: Settlor Lab, IIT Kanpur | D15: Suraj | E15: Mandal | F15: Male | G15: surajm22@iitk.ac.in | H15: (+91) 8617844701 | N15: https://www.jotform.com/uploads/Qmet/260672027148052/6501556695026954019/CWLite.jpeg | O15: Side Channel Analysis | P15: 3 | Q15: CRYSTALS-Kyber is a CCA2-secure key encapsulation mechanism defined over the quotient ring ( Z_q[x]/(X^n + 1) ), with parameters ( q = 3329 ) and ( n = 256 ). It has three variants—Kyber-512, Kyber-768, and Kyber-1024—based on different security levels. The scheme consists of three main operations: key generation, encapsulation, and decapsulation. Although the algorithm itself is secure, its hardware implementation is vulnerable to side-channel attacks due to inherent physical leakage. This work demonstrates a successful attack using Correlation Power Analysis (CPA). For trace acquisition, ChipWhisperer CW305 was used along with ChipWhisperer Lite, enabling efficient and cost-effective power trace collection. A total of 50,000 random and 50,000 fixed traces were captured to perform TVLA (Test Vector Leakage Assessment). The results showed TVLA values consistently above 4.5, often exceeding 20 and even reaching beyond 40, confirming significant leakage. The attack targets the decapsulation step, specifically the computation ( v - s^T u ), focusing on the point-wise multiplication ( s^T . u ). A chosen ciphertext attack was conducted on the hardware implementation, which operates with a latency of 256 clock cycles. Approximately 10,000 traces were required to recover one coefficient of the secret key, resulting in about 280,000 traces to extract the full key. | R15: 6.5015567e+18
A16: 2 | B16: IITM CDOT Samgnya Technologies Foundation at IIT Madras | C16: IIT Bhilai: Fault Injection Attack on Kyber-768 | D16: Abhilash Kumar | E16: Das | F16: Male | G16: abhilashkd@iitbhilai.ac.in | H16: (+91) 9362672150 | I16: Anirudh | J16: Jaiswal | K16: Male | L16: anirudh_202200138@smit.smu.edu.in | M16: (+91) 7439215216 | N16: https://www.jotform.com/uploads/Qmet/260672027148052/6502483482521778987/cw-lite-32.jpg.jpeg | O16: Clock glitching | P16: 2 sockets, 220V | Q16: The team will demonstrate a practical fault-injection attack (published in ASIACRYPT 2021 by Xagawa et al.) on Key Encapsulation Mechanism (CRYSTALS-Kyber) using ChipWhisperer Lite Part - I. The demo is followed by the recovery of long-term secret. First, the board specifications are configured, the firmware is compiled, and the clock glitching parameters are set before running the main glitching script. The process then involves sweeping through the maximum ranges of the parameters, namely width (w) and offset (o). By analyzing combinations of (w, o, ext_o), instances of crashes and resets can be identified, which confirm that the glitch is affecting the execution pipeline of the algorithm. The parameter ext_o plays a crucial role, as it determines when the capture board inserts the glitch after receiving the trigger, allowing precise control of the glitch timing at the nanosecond level within a clock cycle. As a result, the expected outcomes include downgrading the security of Kyber-768 from CCA-secure to CPA-secure through fault injection, and obtaining a 32-byte shared secret K for any crafted ciphertext. | R16: 6.5024835e+18
A17: 3 | B17: IITM CDOT Samgnya Technologies Foundation at IIT Madras | C17: QuiLA - TG! | D17: Ashutosh | E17: Singh | F17: Male | G17: ashutosh@ee.iitm.ac.in | H17: (+91) 9122866323 | I17: Saravana Vilashini | J17: M | K17: Female | L17: ee19d021@smail.iitm.ac.in | M17: (+91) 8754325797 | N17: https://www.jotform.com/uploads/Qmet/260672027148052/6502691282497432140/QuiLA.jpg | O17: QuiLA | P17: 4 | Q17: Working under TG-1 with Prof. Anil Prabhakar | R17: 6.5026913e+18
A18: 4 | B18: IITM CDOT Samgnya Technologies Foundation at IIT Madras | C18: QuEPRAN-TG4 | D18: Dr. Debadrita | E18: Ghosh | F18: Female | G18: debadrita@rrimail.rri.res.in | H18: (+91) 7022009257 | I18: Anagha | J18: Gayatri | K18: Female | L18: anaghagayathri@smail.iitm.ac.in | M18: (+91) 9048435490 | N18: https://www.jotform.com/uploads/Qmet/260672027148052/6502711742492972140/QuEPRAN.png | O18: QuePRAN | P18: 5 | Q18: Quantum Memory Nodes, BSM (Bell state measurement | R18: 6.5027117e+18
A20: 1 | B20: Qmet Tech Foundation at IIT Bombay | C20: Quantum Imaging Techncial Group, IIT Kanpur | D20: Aniket | E20: Nag | F20: Male | G20: aniketnag24@iitk.ac.in | H20: (+91) 8972799320 | I20: Pranay (also in poster) | J20: Mohta | K20: Male | L20: pmohta@iitk.ac.in | M20: () 7980625513 | N20: https://www.jotform.com/uploads/Qmet/260672027148052/6501594666024789905/coherence%20detector.jpg https://www.jotform.com/uploads/Qmet/260672027148052/6501594666024789905/image%20rotator.jpg | O20: Quantum imaging and high-dimensional quantum information | P20: One Socket (5/15 Amp) for Image Rotator and Two Sockets (5/15 Amp) | Q20: 1. Image Rotator: This can be used for rotating any wavefront with ( Angular Deviation < 1 milli-radian and Mean Polarisation Change < 5%). The commercially available IRs have angular deviation > 100 milli-radian and Mean Polarisation Changes are > 40%). This can be commercialised and will have application in high-dimensional classical and quantum information and quantum imaging. 2. Spatial Coherence Detector: Device for measuring spatial coherence. This is a detector for measuring complex spatial coherence of light, with more than 95% fidelity in the presence of background noise of signal to noise ratio (SNR) as low as 1/10. This is a crucial device for noise-resilient imaging. | R20: 6.5015947e+18
A21: 2 | B21: Qmet Tech Foundation at IIT Bombay | C21: - Magnetic microscope based on NV- centers in diamond (sharing) | D21: Prasobh | E21: Padmanabhan | F21: Male | G21: prasobh.padmanabhan@qmettech.com | H21: (+91) 8073277036 | I21: Shishir | J21: Dasika | K21: Male | L21: shishir.dasika@qmettech.com | M21: () 73820336590 | N21: https://www.jotform.com/uploads/Qmet/260672027148052/6502451804853886749/QDM_Image.jpg | O21: NV Centre Sensing | P21: 5 kW | Q21: The Quantum Diamond Microscopes (QDM) works in room temperature and generates magnetic field maps, which can be used for the detection of Hardware trojans. The QDM maps the magnetic field of a chip while it processes the data. By comparing this map to a trusted chip, defense analysts can spot tiny, unauthorized circuits that shouldn't be there. Similarly, these magnetic field maps can be used for the defect detection of chips. They can also help in non-destructively reverse engineering the chips, by revealing the internal architecture. Qmet’s quantum diamond microscope delivers high-performance magnetic imaging by combining a magnetic field sensitivity of 0.7 µT/√Hz with a spatial resolution of 1 µm. This configuration allows for the detection of subtle magnetic field variations while maintaining the ability to resolve localized features at the micron scale. The system features a 100 µm field of view, enabling simultaneous wide-field characterization of magnetic textures or current distributions across a significant sample area. Side illumination, Normal illumination and Cryogenic setup of QDM are available in the lab. Technical specifications: Sensitivity: 0.7 µT/√Hz, Resolution: 1 um, FOV: 100 µm | R21: 6.5024518e+18
A22: 3 | B22: Qmet Tech Foundation at IIT Bombay | C22: Quantum Diamond Magnetometer (sharing) | D22: Vinayak | E22: Rane | F22: Male | G22: vinaya.rane@qmettech.com | H22: (+91) 9867236112 | I22: Abhijeet | J22: Ghodgaonkar | K22: Male | L22: abhijeet.ghodgaonkar@qmettech.com | M22: (+91) 9962648741 | N22: https://www.jotform.com/uploads/Qmet/260672027148052/6502478419741009952/MagPI_Photo_2898.JPG | O22: NV Centre Sensing | P22: 4 sockets with 230 V Ac | Q22: Quantum magnetometers offer a potential alternative for aerial navigation in environments where GPS is unreliable. By utilizing the Earth’s magnetic field, these sensors provide a passive navigation source that is difficult to defeat. While the technology is still maturing, it holds specific value for defense and space sectors requiring positioning redundancy in contested or remote areas. Additionally, the high sensitivity of these devices may improve the detection of localized magnetic anomalies, such as those generated by submerged vessels or metallic structures. Ultimately, integrating quantum magnetometry into existing sensor suites could provide a potential solution to vulnerabilities of satellite-dependent systems. Qmet’s magnetometer offers high-precision magnetic field characterization with a sensitivity of 0.7 nT/√Hz and full vector measurement capabilities. Operating within a bandwidth of DC to 0.1 kHz, the system is optimized for stable static measurements and low-frequency signal detection. It features an expansive dynamic range spanning from pT to mT levels, allowing it to transition seamlessly between measuring subtle fluctuations and strong magnetic environments. Consuming 50 W of power, the device is designed to maintain robust performance for industrial or laboratory-grade applications. We have already working on improving the form factor to make it compatible with a variety of mobile applications. Technical specifications: Sensitivity: 0.7 nT/√Hz Bandwidth: DC – 0.1 kHz, Dynamic Range: pT to mT, Power: 50 W, Vector capability: Yes | R22: 6.5024784e+18
A23: 4 | B23: Qmet Tech Foundation at IIT Bombay | C23: V-PAR Microsystems Pvt. Ltd. | D23: Roopa | E23: J | F23: Female | G23: roopaj@iisc.ac.in | H23: (91) 9739815213 | I23: Purna | J23: Pal | K23: Female | L23: purnapal@iisc.ac.in | M23: (91) 8617013318 | N23: https://www.jotform.com/uploads/Qmet/260672027148052/6504131075184348606/Vapor%20cell-Tech.jpeg | O23: Chip-Scale Atomic Metrology | P23: 2 sockets and One monitor | Q23: Our startup is a deep-tech venture focused on the indigenization of high-performance MEMS alkali vapor cells, the essential "physics package" for miniaturized quantum technologies. By moving away from traditional, manual glass-blowing techniques toward automated, wafer-level semiconductor batch fabrication, we produce hermetically sealed Rubidium and Cesium cells at a scale and precision previously unavailable in the domestic market. Our core product enables the transition of quantum sensors from bulky laboratory setups to chip-scale components, specifically targeting the Strategic Sector for ISRO and DRDO's GPS-denied navigation and satellite timing requirements. Beyond defense, we provide the hardware foundation for 5G/6G network synchronization and advanced medical brain imaging via Optically Pumped Magnetometers (OPMs). Based within the IISc-CeNSE ecosystem, we bridge the critical gap between complex quantum physics and industrial mass production. Our mission is to secure a sovereign, ITAR-free supply chain for the global quantum metrology market, offering high-reliability, low-power sensing solutions that are ready for seamless integration into the next generation of aerospace, telecommunications, and healthcare infrastructure. | R23: 6.5041311e+18
B24: Qmet Tech Foundation at IIT Bombay | C24: TIFR-QMet cryogenic inertial positioner | D24: John | E24: Jesudasan | F24: Male | G24: johnj.tifr@gmail.com | H24: (+91) 9869279569 | I24: Pooja | J24: Gunjal | K24: Female | L24: poojagunjal1212@gmail.com | M24: (+91) 8010538448 | N24: https://www.jotform.com/uploads/Qmet/260672027148052/6506815553427022903/Picsart_26-03-30_17-33-41-145.jpg | O24: we develop a compact, low cost Nanopositioning system capable of precise motion at nanometer scale over millimetre ranges and operating at cryogenic temperature (down to 2.0 K) | P24: four 5 amps power point with switches. | Q24: The inertial nanopositioner has a very compact, lightweight and simple construction and operates using a slip-stick mechanism driven by piezoelectric actuation. The basic design has three principal parts. The active part is a piezoelectric ceramic stack, glued to a moving stage on one side and the other side is glued to a triangular metallic monorail, acting as the guiding rod. The system is supported by a fully automated, microcontroller-based control electronics with computer interfacing. Sawtooth waveform with an amplitude of 6 to 60 volts is essential in driving the piezoelectric element. We generate a sawtooth waveform using analog output from a microcontroller and OP-amp based amplifier. We use LabVIEW or python-based user interface to control the mode of operation, amplitude and frequency of the sawtooth. X and Y nanopositioner can be stack on the Z-nanopositioner. Currently fabricated two stacks of X-Y-Z nanopositioners, each with footprints of 15 × 15 mm² and 24 × 24 mm², respectively. Also the position of the nanopositioner can be sensed with an Encoder module which is incorporated within the nanopositioner. | R24: 6.5068156e+18
A26: 1 | B26: QMD Foundation at IIT Delhi | C26: III-V Semiconductor based LNA and SPAD | D26: Rajendra | E26: Singh | F26: Male | G26: rsingh@physics.iitd.ac.in | H26: (91) 9582774442 | I26: Samaresh | J26: Das | K26: Male | L26: samareshdas@care.iitd.ac.in | M26: (91) 9899130814 | N26: https://www.jotform.com/uploads/Qmet/260672027148052/6501600758606575847/Picture2.jpg | O26: Quantum Materials and Devices | P26: 3/220 | Q26: Low Noise Amplifier (LNA) • High-performance LNAs using SiGe technology with a COTS transistor tested at room temperature • Achieved noise figure < 1.4 dB over 1.5–4.5 GHz • InP-based dies introduced to reduce noise figure and improve input matching • Operating frequency range: 1–5 GHz • Two-stage cascaded and balanced LNAs investigated • Devices use 200 μm and 150 μm gate-width InP HEMTs • Cascaded LNA performance (296 K, unconditionally stable): o Gain: 25.4 dB o Noise figure: < 0.9 dB o Input return loss: > 5.6 dB • Achieved performance parameters: o Return loss: > 15 dB o Gain: 24.7 dB o Noise figure: < 1.18 dB Single-Photon Avalanche Detector (SPAD) • Device structure: InGaAs/InP SAGCM SPAD • Layers: absorption, grading, charge, and multiplication regions • TCAD simulations used to study: o Charge layer engineering o Zn diffusion effects o Breakdown characteristics • Electric field confined in multiplication region (~3.5 × 10⁵ V/cm) • Absorption region maintains low electric field (< 1 × 10⁵ V/cm) • Device designed for 1550 nm wavelength (telecommunication band) • Fabrication includes hard mask design for planar and mesa SPADs • Integrated simulation and fabrication improve: o Photon Detection Efficiency (PDE) o Noise performance | R26: 6.5016008e+18
A27: 2 | B27: QMD Foundation at IIT Delhi | C27: 2D Photon Emitter & Avalanche Detector Arrays | D27: Prof. Saurabh | E27: Lodha | F27: Male | G27: slodha@iitb.ac.in | H27: (+91) 9819927460 | I27: Prof. Anshuman | J27: Kumar | K27: Male | L27: anshuman.kumar@iitb.ac.in | M27: (+91) 9958713346 | N27: https://www.jotform.com/uploads/Qmet/260672027148052/6501616470659994834/2D%20Photon%20Emitter%20%26%20Detector%20Arrays.jpg | O27: Qunatum Materials & Devices | P27: 3/220V | Q27: 1. India’s 1st (a) quantum emitter array chip and (b) submicron 2D Avalanche photodetector and. 2. Images and Schematics of (a) hBN based device with integrated nanocavity for optimized and (b) brightness WSe₂ flake based device with Ti/Pt/Au (5 nm/30 nm/100 nm) and Ti/Ni/Au (5 nm/30 nm/100 nm) contacts. 3. Optical images of (a) the device on Si/SiO2 substrate for potential application of large area arrays of SPE arrays and (b) an array of ALD grown MoS2 transistors transferred on a back gate Si/SiO2 substrate for potential application of large area arrays of APDs. | R27: 6.5016165e+18
A28: 3 | B28: QMD Foundation at IIT Delhi | C28: 2D Transfer Setup & Precision Power Supply | D28: Prof. Ashish | E28: Arora | F28: Male | G28: ashish.arora@iiserpune.ac.in | H28: (+91) 9892294386 | N28: https://www.jotform.com/uploads/Qmet/260672027148052/6501618690652254627/2D%20Transfer%20Setup%20%26%20Precision%20Power%20Supply.jpg | O28: Qunatum Materials & Devices | P28: 3/220V | Q28: (a) Key feature of 2D materials transfer setup: 1. Advanced optical & imaging capabilities: Includes Koehler illumination, integrated photoluminescence imaging/spectroscopy (532 nm excitation), and reflectance spectroscopy (450–750 nm). 2. Flexible sample handling & automation: Supports tilt/rotation, up to 20 mm substrates, heating to 180 °C, remote XYZ control, and custom imaging software. (b) High performance electronics engineered power supply for quantum technologies: Precision ~ 1–10 ppm current & voltage sources | R28: 6.5016187e+18
A29: 4 | B29: QMD Foundation at IIT Delhi | C29: Silicon Nitride Micro Ring Resonators (MRR) and Optical Nanofiber (ONF) Tip | D29: Shailendra Kumar | E29: Varshney | F29: Male | G29: skvarshney@ece.iitkgp.ac.in | H29: (91) 3222-283504 | I29: Rajesh | J29: Kumar | K29: Male | L29: rajesh.kumar@ph.iitr.ac.in | M29: (91) 4869 | N29: https://www.jotform.com/uploads/Qmet/260672027148052/6501626320656386319/TG3.png | O29: Quantum Materials and Devices | P29: 3/220 | Q29: Si3N4 Micro Ring Resonators • High-Q, low-loss resonators on Silicon Nitride platforms for narrow linewidth filtering, frequency comb generation, and photon-pair production via nonlinear optics • Si3N4 waveguides optimized for zero-dispersion operation over 700–1100 nm were designed with thicknesses of 200–500 nm and heights of 100–200 nm • First-round fabrication of micro-ring resonators with bus–waveguide coupling gaps ≥200 nm successfully completed, enabling wavelength-selective routing and resonant enhancement for quantum photonic circuits • Coupled ring–bus structures used to control light coupling for filtering, switching, and nonlinear interactions. Optical nanofiber (ONF) Tip Fabricated Probe • Optical nanofiber tapered tips allow strong evanescent field interaction for single-photon coupling and near-field sensing. • Sub-wavelength diameter (D < lamda) . • Fundamental mode (HE11) as the only guided mode • Strong Transverse Confinement of evanescent field manipulating atoms and photons • Quantum Channel in inline fiber network demonstrated. | R29: 6.5016263e+18

Sheet PI registrations -Hub wise
A3: Count of Registration Status | B3: Column Labels
A4: Row Labels | B4: No | C4: Yes | D4: Grand Total
A5: IISc Bangalore | B5: 10 | C5: 41 | D5: 51
A6: IISc Bangalore | IIT Bombay | C6: 2 | D6: 2
A7: IIT Bombay | B7: 13 | C7: 24 | D7: 37
A8: IIT Delhi | B8: 11 | C8: 20 | D8: 31
A9: IIT Madras | B9: 10 | C9: 22 | D9: 32
A10: Grand Total | B10: 44 | C10: 109 | D10: 153

Sheet Dataset
A1: Sr. No. | B1: PI Name | C1: Department | D1: Institute | E1: Role | F1: Email ID | G1: Hub | H1: TG Name | I1: Validation | J1: Registration status
A2: 14 | B2: Dr. Ashok Kumar | C2: Physics | D2: Indian Institute of Space Science and Technology (IIST), DoS | I2: =VLOOKUP(F2,Registrations!G:N,6,0) -> #N/A | J2: =IF(I2="#NA","No", "Yes") -> #N/A
A3: 28 | B3: Dr. K R Yogesh Prasad | C3: Communication Systems | D3: ISRO Satellite Center | I3: =VLOOKUP(F3,Registrations!G:N,6,0) -> #N/A | J3: =IF(I3="#NA","No", "Yes") -> #N/A
A4: 41 | B4: Dr. Pradeep Kiran Sarvepalli | C4: EE | D4: Indian Institute of Technology Madras | F4: pradeep@ee.iitm.ac.in | I4: =VLOOKUP(F4,Registrations!G:N,6,0) -> #N/A | J4: =IF(I4="#NA","No", "Yes") -> #N/A
A5: 48 | B5: Dr. Rakesh Kumar Palani | C5: Department of Electrical Engineering | D5: Indian Institute of Technology Delhi | E5: MPI | F5: palanirakesh@gmail.com | H5: TG 3 Design and Demonstration of a Highly Scalable Quantum Computer using Semiconducting Qubits | I5: =VLOOKUP(F5,Registrations!G:N,6,0) -> #N/A | J5: =IF(I5="#NA","No", "Yes") -> #N/A
A6: 53 | B6: Dr. Saikat Ghosh | C6: Department of Physics | D6: Indian Institute of Technology Kanpur | F6: gsaikat@iitk.ac.in | G6: IIT Bombay | H6: TG 2 Saikat Ghosh | I6: =VLOOKUP(F6,Registrations!G:N,6,0) -> IIT Bombay | J6: =IF(I6="#NA","No", "Yes") -> Yes
A7: 70 | B7: Dr. Sumit Gautam | C7: Department of Electrical Engineering | D7: Indian Institute of Technology Indore | F7: sumit.gautam@iiti.ac.in | I7: =VLOOKUP(F7,Registrations!G:N,6,0) -> #N/A | J7: =IF(I7="#NA","No", "Yes") -> #N/A
A8: 84 | B8: Er. Adarsh Jain | C8: Quantum Systems Technology Division | D8: Space Application Centre, ISRO | I8: =VLOOKUP(F8,Registrations!G:N,6,0) -> #N/A | J8: =IF(I8="#NA","No", "Yes") -> #N/A
A9: 85 | B9: Er. Chandra Prakash Sharma | C9: Quantum Technology Group | D9: Space Application Centre, ISRO | I9: =VLOOKUP(F9,Registrations!G:N,6,0) -> #N/A | J9: =IF(I9="#NA","No", "Yes") -> #N/A
A10: 86 | B10: Er. K Kalpana | C10: Opto Quantum Communication Program | D10: ISRO Satellite Center | I10: =VLOOKUP(F10,Registrations!G:N,6,0) -> #N/A | J10: =IF(I10="#NA","No", "Yes") -> #N/A
A11: 87 | B11: Er. Pankaj Kumar Gupta | C11: Quantum Electronics and Photonics Division | D11: Space Application Centre, ISRO | I11: =VLOOKUP(F11,Registrations!G:N,6,0) -> #N/A | J11: =IF(I11="#NA","No", "Yes") -> #N/A
A12: 112 | B12: Prof. Deepa Venkitesh | C12: Department of Electrical Engineering | D12: Indian Institute of Technology Madras | F12: deepa@ee.iitm.ac.in | I12: =VLOOKUP(F12,Registrations!G:N,6,0) -> #N/A | J12: =IF(I12="#NA","No", "Yes") -> #N/A
A13: 125 | B13: Prof. Krishna Jagannathan | C13: Department of Electrical Engineering | D13: Indian Institute of Technology Madras | F13: krishnaj@ee.iitm.ac.in | I13: =VLOOKUP(F13,Registrations!G:N,6,0) -> #N/A | J13: =IF(I13="#NA","No", "Yes") -> #N/A
A14: 135 | B14: Prof. Preeti Ranjan Panda | C14: Department of Computer Science and Engineering | D14: Indian Institute of Technology Delhi | I14: =VLOOKUP(F14,Registrations!G:N,6,0) -> #N/A | J14: =IF(I14="#NA","No", "Yes") -> #N/A
A15: 165 | B15: Ashok Kumar | D15: IIST | I15: =VLOOKUP(F15,Registrations!G:N,6,0) -> #N/A | J15: =IF(I15="#NA","No", "Yes") -> #N/A
A16: 3 | B16: Dr. Akshay Singh | C16: Physics | D16: Indian Institute of Science Bangalore | E16: MPI | F16: aksy@iisc.ac.in | G16: IISc Bangalore | H16: TG 1 Photonics quantum processor development | I16: =VLOOKUP(F16,Registrations!G:N,6,0) -> IISc Bangalore | J16: =IF(I16="#NA","No", "Yes") -> Yes
A17: 6 | B17: Dr. Anil Shaji | C17: Physics | D17: Indian Institute of Science Education and Research Thiruvananthapuram | E17: MPI | F17: shaji@iisertvm.ac.in | G17: IISc Bangalore | H17: TG 4 Development of a 50-qubit quantum information processor with electron spins in silicon | I17: =VLOOKUP(F17,Registrations!G:N,6,0) -> #N/A | J17: Yes
A18: 13 | B18: Dr. Ashok K Mohapatra | C18: Physics | D18: National Institue of Science Education and Research Bhubaneswar | E18: MPI | F18: a.mohapatra@niser.ac.in | G18: IISc Bangalore | H18: TG 6 Quantum Computing with Neutral Atoms, Trapped Ions and Related Hybrid Systems | I18: =VLOOKUP(F18,Registrations!G:N,6,0) -> IISc Bangalore | J18: =IF(I18="#NA","No", "Yes") -> Yes
A19: 15 | B19: Dr. Awanish Pandey | C19: Optics and Photonics Centre | D19: Indian Institute of Technology Delhi | E19: MPI | F19: awanish@ee.iitd.ac.in | G19: IISc Bangalore | H19: TG 1 Photonics quantum processor development | I19: =VLOOKUP(F19,Registrations!G:N,6,0) -> #N/A | J19: =IF(I19="#NA","No", "Yes") -> #N/A
A20: 17 | B20: Dr. Baladitya Suri | C20: Instrumentation and Applied Physics | D20: Indian Institute of Science Bangalore | E20: MPI | F20: surib@iisc.ac.in | G20: IISc Bangalore | H20: TG 5 Quantum computers with Superconducting Qubits | I20: =VLOOKUP(F20,Registrations!G:N,6,0) -> IISc Bangalore | J20: =IF(I20="#NA","No", "Yes") -> Yes
A21: 29 | B21: Dr. Kanhaiya Pandey | C21: Physics | D21: Indian Institute of Technology Guwahati | E21: MPI | F21: kanhaiyapandey@iitg.ac.in | G21: IISc Bangalore | H21: TG 6 Quantum Computing with Neutral Atoms, Trapped Ions and Related Hybrid Systems | I21: =VLOOKUP(F21,Registrations!G:N,6,0) -> IISc Bangalore | J21: =IF(I21="#NA","No", "Yes") -> Yes
A22: 31 | B22: Dr. Kaushik Saha | C22: EE | D22: Indian Institute of Technology Delhi | E22: MPI | F22: ksaha@ee.iitd.ac.in | G22: IISc Bangalore | H22: TG 3 Design and Demonstration of a Highly Scalable Quantum Computer using Semiconducting Qubits | I22: =VLOOKUP(F22,Registrations!G:N,6,0) -> #N/A | J22: =IF(I22="#NA","No", "Yes") -> #N/A
A23: 32 | B23: Dr. Madhu Thalakulam | C23: Physics | D23: Indian Institute of Science Education and Research Thiruvananthapuram | E23: MPI | F23: madhu@iisertvm.ac.in | G23: IISc Bangalore | H23: TG 4 Development of a 50-qubit quantum information processor with electron spins in silicon | I23: =VLOOKUP(F23,Registrations!G:N,6,0) -> IISc Bangalore | J23: =IF(I23="#NA","No", "Yes") -> Yes
A24: 36 | B24: Dr. Natarajan Venkatachalam | C24: Quantum Technology | D24: Society for Electronic Transactions and Security (SETS) | E24: MPI | F24: natarajan@setsindia.net | G24: IISc Bangalore | H24: QuILA | I24: =VLOOKUP(F24,Registrations!G:N,6,0) -> IISc Bangalore | J24: =IF(I24="#NA","No", "Yes") -> Yes
A25: 40 | B25: Dr. Prabha Mandayam | C25: Physics | D25: Indian Institute of Technology Madras | E25: MPI | F25: prabhamd@physics.iitm.ac.in | G25: IISc Bangalore | H25: TG 5 Quantum computers with Superconducting Qubits | I25: =VLOOKUP(F25,Registrations!G:N,6,0) -> IISc Bangalore | J25: =IF(I25="#NA","No", "Yes") -> Yes
A26: 45 | B26: Dr. Rahul Singh | C26: EE | D26: Indian Institute of Technology Bombay | E26: MPI | F26: rahuls_ee@iitb.ac.in | G26: IISc Bangalore | H26: TG 4 Development of a 50-qubit quantum information processor with electron spins in silicon | I26: =VLOOKUP(F26,Registrations!G:N,6,0) -> IISc Bangalore | J26: =IF(I26="#NA","No", "Yes") -> Yes
A27: 46 | B27: Dr. Rajamani Vijayaraghavan | C27: Condensed Matter Physics and Materials Science | D27: Tata Institute of Fundamental Research Mumbai | E27: LPI | F27: rvijay26@gmail.com | G27: IISc Bangalore | H27: TG 5 Quantum computers with Superconducting Qubits | I27: =VLOOKUP(F27,Registrations!G:N,6,0) -> #N/A | J27: Yes
A28: 52 | B28: Dr. Sai Vinjanampathy | C28: Department of Physics | D28: Indian Institute of Technology Bombay | E28: MPI | F28: sai@quantumlah.org | G28: IISc Bangalore | H28: TG 5 Quantum computers with Superconducting Qubits | I28: =VLOOKUP(F28,Registrations!G:N,6,0) -> #N/A | J28: =IF(I28="#NA","No", "Yes") -> #N/A
A29: 58 | B29: Dr. Sapam Ranjita Chanu | C29: Department of Physics CELP | D29: Indian Institute of Technology Kanpur | E29: MPI | F29: sranjita@iitk.ac.in | G29: IISc Bangalore | H29: TG 6 Quantum Computing with Neutral Atoms, Trapped Ions and Related Hybrid Systems | I29: =VLOOKUP(F29,Registrations!G:N,6,0) -> #N/A | J29: =IF(I29="#NA","No", "Yes") -> #N/A
A30: 59 | B30: Dr. Saptarishi Chaudhuri | C30: Department of Light and Matter Physics | D30: Raman Research Institute | E30: LPI | F30: srishic@rri.res.in | G30: IISc Bangalore | H30: TG 6 Quantum Computing with Neutral Atoms, Trapped Ions and Related Hybrid Systems | I30: =VLOOKUP(F30,Registrations!G:N,6,0) -> IISc Bangalore | J30: =IF(I30="#NA","No", "Yes") -> Yes
A31: 61 | B31: Dr. Saravana Kumar M | C31: Department of Electronics & Communication Engineering | D31: Indian Institute of Technology Roorkee | E31: MPI | F31: saravana.kumar@ece.iitr.ac.in | G31: IISc Bangalore | H31: TG 3 Design and Demonstration of a Highly Scalable Quantum Computer using Semiconducting Qubits | I31: =VLOOKUP(F31,Registrations!G:N,6,0) -> IISc Bangalore | J31: =IF(I31="#NA","No", "Yes") -> Yes
